Workbook
Name 선택가능종목: 'ETF데이터'!$A$4:$A$594
Name 검색어: '제안서'!$E$17
Name 검색건수: COUNTIF('ETF데이터'!$AC$4:$AC$594,1)
Name 검색결과: OFFSET('ETF데이터'!$AE$4,0,0,MAX(1,COUNTIF('ETF데이터'!$AC$4:$AC$594,1)),1)
Name 담긴목록: '종목조회'!$R$20:$R$79
Name 담긴수: '종목조회'!$Q$79
Name 조회_주기: '종목조회'!$C$10
Name 조회_최소: '종목조회'!$C$11
Name 조회_최대: '종목조회'!$C$12

Sheet 제안서
A1: 사내한 · Confidential | J1: 계산 보조 (수정하지 마십시오)
A2: 월배당 ETF 투자 제안서
A3: Monthly Distribution ETF Portfolio
A5: 자료 ETFCHECK · 기준일 2026-10-02 · 매월 1일 자동 갱신
A8: 1 | B8: 고객 정보 및 투자 조건
B10: 고객명 | C10: 홍길동
B11: 총 투자금액 (원) | C11: 100000000
B12: 배분 방식 | C12: 비율 | E12: 비율 = 총액을 %로 나눔 · 금액 = 종목별 금액 직접 입력
B13: 배당소득세율 | C13: 0.154 | E13: 국내 상장 ETF 분배금 기준 15.4% (지방소득세 포함)
B14: 제안일 | C14: 2026-10-04
A17: 2 | B17: 투자 포트폴리오 (최대 10종목) | D17: 종목 검색 | F17: =IF(검색어="","← 글자 일부를 넣으면 아래 '투자 ETF' 의 ▼ 목록이 그만큼만 남습니다 (예: 커버드콜)",IF(검색건수=0,"→ '"&검색어&"' 에 맞는 종목이 없습니다. 글자를 줄여 보십시오.","→ '"&검색어&"' 로 "&검색건수&"종목. 아래 '투자 ETF' 칸의 ▼ 를 누르십시오."))
B19: 투자 ETF | C19: =IF($C$12="비율","배분 비율 (%)","배분 금액 (원)") | D19: 배정 금액 | E19: 매수 수량 | F19: 실투자금액 | G19: 월 분배금(세전) | H19: 월 분배금(세후)
B20: =IF(담긴수=0,"TIGER 미국배당다우존스",IFERROR(INDEX(담긴목록,1),"")) | C20: =IF($B20="","",IF($C$12="비율",IF(1<MAX(담긴수,1),ROUND(100/MAX(담긴수,1),2),100-ROUND(100/MAX(담긴수,1),2)*(MAX(담긴수,1)-1)),IF(1<MAX(담긴수,1),ROUNDDOWN($C$11/MAX(담긴수,1),0),$C$11-ROUNDDOWN($C$11/MAX(담긴수,1),0)*(MAX(담긴수,1)-1)))) | D20: =IF($K20=0,0,IF($C$12="비율",ROUND($C$11*$C20/100,0),$C20)) | E20: =IF($K20=0,0,ROUNDDOWN($D20/INDEX('ETF데이터'!$D$4:$D$594,$K20),0)) | F20: =IF($K20=0,0,$E20*INDEX('ETF데이터'!$D$4:$D$594,$K20)) | G20: =IF($K20=0,0,$F20*INDEX('ETF데이터'!$J$4:$J$594,$K20)/12) | H20: =$G20*(1-$C$13*$O20) | K20: =IF($B20="",0,IFERROR(MATCH($B20,선택가능종목,0),0)) | L20: =IF($K20=0,"",INDEX('ETF데이터'!$M$4:$M$594,$K20)) | M20: =IF($K20=0,"",INDEX('ETF데이터'!$R$4:$R$594,$K20)) | N20: =IF(OR($M20="",$M20="월배당"),0,1) | O20: =IF($K20=0,1,IF(INDEX('ETF데이터'!$T$4:$T$594,$K20)="",1,INDEX('ETF데이터'!$T$4:$T$594,$K20))) | P20: =IF($K20=0,0,IF(INDEX('ETF데이터'!$T$4:$T$594,$K20)="",1,0))
B21: =IF(담긴수=0,"",IFERROR(INDEX(담긴목록,2),"")) | C21: =IF($B21="","",IF($C$12="비율",IF(2<MAX(담긴수,1),ROUND(100/MAX(담긴수,1),2),100-ROUND(100/MAX(담긴수,1),2)*(MAX(담긴수,1)-1)),IF(2<MAX(담긴수,1),ROUNDDOWN($C$11/MAX(담긴수,1),0),$C$11-ROUNDDOWN($C$11/MAX(담긴수,1),0)*(MAX(담긴수,1)-1)))) | D21: =IF($K21=0,0,IF($C$12="비율",ROUND($C$11*$C21/100,0),$C21)) | E21: =IF($K21=0,0,ROUNDDOWN($D21/INDEX('ETF데이터'!$D$4:$D$594,$K21),0)) | F21: =IF($K21=0,0,$E21*INDEX('ETF데이터'!$D$4:$D$594,$K21)) | G21: =IF($K21=0,0,$F21*INDEX('ETF데이터'!$J$4:$J$594,$K21)/12) | H21: =$G21*(1-$C$13*$O21) | K21: =IF($B21="",0,IFERROR(MATCH($B21,선택가능종목,0),0)) | L21: =IF($K21=0,"",INDEX('ETF데이터'!$M$4:$M$594,$K21)) | M21: =IF($K21=0,"",INDEX('ETF데이터'!$R$4:$R$594,$K21)) | N21: =IF(OR($M21="",$M21="월배당"),0,1) | O21: =IF($K21=0,1,IF(INDEX('ETF데이터'!$T$4:$T$594,$K21)="",1,INDEX('ETF데이터'!$T$4:$T$594,$K21))) | P21: =IF($K21=0,0,IF(INDEX('ETF데이터'!$T$4:$T$594,$K21)="",1,0))
B22: =IF(담긴수=0,"",IFERROR(INDEX(담긴목록,3),"")) | C22: =IF($B22="","",IF($C$12="비율",IF(3<MAX(담긴수,1),ROUND(100/MAX(담긴수,1),2),100-ROUND(100/MAX(담긴수,1),2)*(MAX(담긴수,1)-1)),IF(3<MAX(담긴수,1),ROUNDDOWN($C$11/MAX(담긴수,1),0),$C$11-ROUNDDOWN($C$11/MAX(담긴수,1),0)*(MAX(담긴수,1)-1)))) | D22: =IF($K22=0,0,IF($C$12="비율",ROUND($C$11*$C22/100,0),$C22)) | E22: =IF($K22=0,0,ROUNDDOWN($D22/INDEX('ETF데이터'!$D$4:$D$594,$K22),0)) | F22: =IF($K22=0,0,$E22*INDEX('ETF데이터'!$D$4:$D$594,$K22)) | G22: =IF($K22=0,0,$F22*INDEX('ETF데이터'!$J$4:$J$594,$K22)/12) | H22: =$G22*(1-$C$13*$O22) | K22: =IF($B22="",0,IFERROR(MATCH($B22,선택가능종목,0),0)) | L22: =IF($K22=0,"",INDEX('ETF데이터'!$M$4:$M$594,$K22)) | M22: =IF($K22=0,"",INDEX('ETF데이터'!$R$4:$R$594,$K22)) | N22: =IF(OR($M22="",$M22="월배당"),0,1) | O22: =IF($K22=0,1,IF(INDEX('ETF데이터'!$T$4:$T$594,$K22)="",1,INDEX('ETF데이터'!$T$4:$T$594,$K22))) | P22: =IF($K22=0,0,IF(INDEX('ETF데이터'!$T$4:$T$594,$K22)="",1,0))
B23: =IF(담긴수=0,"",IFERROR(INDEX(담긴목록,4),"")) | C23: =IF($B23="","",IF($C$12="비율",IF(4<MAX(담긴수,1),ROUND(100/MAX(담긴수,1),2),100-ROUND(100/MAX(담긴수,1),2)*(MAX(담긴수,1)-1)),IF(4<MAX(담긴수,1),ROUNDDOWN($C$11/MAX(담긴수,1),0),$C$11-ROUNDDOWN($C$11/MAX(담긴수,1),0)*(MAX(담긴수,1)-1)))) | D23: =IF($K23=0,0,IF($C$12="비율",ROUND($C$11*$C23/100,0),$C23)) | E23: =IF($K23=0,0,ROUNDDOWN($D23/INDEX('ETF데이터'!$D$4:$D$594,$K23),0)) | F23: =IF($K23=0,0,$E23*INDEX('ETF데이터'!$D$4:$D$594,$K23)) | G23: =IF($K23=0,0,$F23*INDEX('ETF데이터'!$J$4:$J$594,$K23)/12) | H23: =$G23*(1-$C$13*$O23) | K23: =IF($B23="",0,IFERROR(MATCH($B23,선택가능종목,0),0)) | L23: =IF($K23=0,"",INDEX('ETF데이터'!$M$4:$M$594,$K23)) | M23: =IF($K23=0,"",INDEX('ETF데이터'!$R$4:$R$594,$K23)) | N23: =IF(OR($M23="",$M23="월배당"),0,1) | O23: =IF($K23=0,1,IF(INDEX('ETF데이터'!$T$4:$T$594,$K23)="",1,INDEX('ETF데이터'!$T$4:$T$594,$K23))) | P23: =IF($K23=0,0,IF(INDEX('ETF데이터'!$T$4:$T$594,$K23)="",1,0))
B24: =IF(담긴수=0,"",IFERROR(INDEX(담긴목록,5),"")) | C24: =IF($B24="","",IF($C$12="비율",IF(5<MAX(담긴수,1),ROUND(100/MAX(담긴수,1),2),100-ROUND(100/MAX(담긴수,1),2)*(MAX(담긴수,1)-1)),IF(5<MAX(담긴수,1),ROUNDDOWN($C$11/MAX(담긴수,1),0),$C$11-ROUNDDOWN($C$11/MAX(담긴수,1),0)*(MAX(담긴수,1)-1)))) | D24: =IF($K24=0,0,IF($C$12="비율",ROUND($C$11*$C24/100,0),$C24)) | E24: =IF($K24=0,0,ROUNDDOWN($D24/INDEX('ETF데이터'!$D$4:$D$594,$K24),0)) | F24: =IF($K24=0,0,$E24*INDEX('ETF데이터'!$D$4:$D$594,$K24)) | G24: =IF($K24=0,0,$F24*INDEX('ETF데이터'!$J$4:$J$594,$K24)/12) | H24: =$G24*(1-$C$13*$O24) | K24: =IF($B24="",0,IFERROR(MATCH($B24,선택가능종목,0),0)) | L24: =IF($K24=0,"",INDEX('ETF데이터'!$M$4:$M$594,$K24)) | M24: =IF($K24=0,"",INDEX('ETF데이터'!$R$4:$R$594,$K24)) | N24: =IF(OR($M24="",$M24="월배당"),0,1) | O24: =IF($K24=0,1,IF(INDEX('ETF데이터'!$T$4:$T$594,$K24)="",1,INDEX('ETF데이터'!$T$4:$T$594,$K24))) | P24: =IF($K24=0,0,IF(INDEX('ETF데이터'!$T$4:$T$594,$K24)="",1,0))
B25: =IF(담긴수=0,"",IFERROR(INDEX(담긴목록,6),"")) | C25: =IF($B25="","",IF($C$12="비율",IF(6<MAX(담긴수,1),ROUND(100/MAX(담긴수,1),2),100-ROUND(100/MAX(담긴수,1),2)*(MAX(담긴수,1)-1)),IF(6<MAX(담긴수,1),ROUNDDOWN($C$11/MAX(담긴수,1),0),$C$11-ROUNDDOWN($C$11/MAX(담긴수,1),0)*(MAX(담긴수,1)-1)))) | D25: =IF($K25=0,0,IF($C$12="비율",ROUND($C$11*$C25/100,0),$C25)) | E25: =IF($K25=0,0,ROUNDDOWN($D25/INDEX('ETF데이터'!$D$4:$D$594,$K25),0)) | F25: =IF($K25=0,0,$E25*INDEX('ETF데이터'!$D$4:$D$594,$K25)) | G25: =IF($K25=0,0,$F25*INDEX('ETF데이터'!$J$4:$J$594,$K25)/12) | H25: =$G25*(1-$C$13*$O25) | K25: =IF($B25="",0,IFERROR(MATCH($B25,선택가능종목,0),0)) | L25: =IF($K25=0,"",INDEX('ETF데이터'!$M$4:$M$594,$K25)) | M25: =IF($K25=0,"",INDEX('ETF데이터'!$R$4:$R$594,$K25)) | N25: =IF(OR($M25="",$M25="월배당"),0,1) | O25: =IF($K25=0,1,IF(INDEX('ETF데이터'!$T$4:$T$594,$K25)="",1,INDEX('ETF데이터'!$T$4:$T$594,$K25))) | P25: =IF($K25=0,0,IF(INDEX('ETF데이터'!$T$4:$T$594,$K25)="",1,0))
B26: =IF(담긴수=0,"",IFERROR(INDEX(담긴목록,7),"")) | C26: =IF($B26="","",IF($C$12="비율",IF(7<MAX(담긴수,1),ROUND(100/MAX(담긴수,1),2),100-ROUND(100/MAX(담긴수,1),2)*(MAX(담긴수,1)-1)),IF(7<MAX(담긴수,1),ROUNDDOWN($C$11/MAX(담긴수,1),0),$C$11-ROUNDDOWN($C$11/MAX(담긴수,1),0)*(MAX(담긴수,1)-1)))) | D26: =IF($K26=0,0,IF($C$12="비율",ROUND($C$11*$C26/100,0),$C26)) | E26: =IF($K26=0,0,ROUNDDOWN($D26/INDEX('ETF데이터'!$D$4:$D$594,$K26),0)) | F26: =IF($K26=0,0,$E26*INDEX('ETF데이터'!$D$4:$D$594,$K26)) | G26: =IF($K26=0,0,$F26*INDEX('ETF데이터'!$J$4:$J$594,$K26)/12) | H26: =$G26*(1-$C$13*$O26) | K26: =IF($B26="",0,IFERROR(MATCH($B26,선택가능종목,0),0)) | L26: =IF($K26=0,"",INDEX('ETF데이터'!$M$4:$M$594,$K26)) | M26: =IF($K26=0,"",INDEX('ETF데이터'!$R$4:$R$594,$K26)) | N26: =IF(OR($M26="",$M26="월배당"),0,1) | O26: =IF($K26=0,1,IF(INDEX('ETF데이터'!$T$4:$T$594,$K26)="",1,INDEX('ETF데이터'!$T$4:$T$594,$K26))) | P26: =IF($K26=0,0,IF(INDEX('ETF데이터'!$T$4:$T$594,$K26)="",1,0))
B27: =IF(담긴수=0,"",IFERROR(INDEX(담긴목록,8),"")) | C27: =IF($B27="","",IF($C$12="비율",IF(8<MAX(담긴수,1),ROUND(100/MAX(담긴수,1),2),100-ROUND(100/MAX(담긴수,1),2)*(MAX(담긴수,1)-1)),IF(8<MAX(담긴수,1),ROUNDDOWN($C$11/MAX(담긴수,1),0),$C$11-ROUNDDOWN($C$11/MAX(담긴수,1),0)*(MAX(담긴수,1)-1)))) | D27: =IF($K27=0,0,IF($C$12="비율",ROUND($C$11*$C27/100,0),$C27)) | E27: =IF($K27=0,0,ROUNDDOWN($D27/INDEX('ETF데이터'!$D$4:$D$594,$K27),0)) | F27: =IF($K27=0,0,$E27*INDEX('ETF데이터'!$D$4:$D$594,$K27)) | G27: =IF($K27=0,0,$F27*INDEX('ETF데이터'!$J$4:$J$594,$K27)/12) | H27: =$G27*(1-$C$13*$O27) | K27: =IF($B27="",0,IFERROR(MATCH($B27,선택가능종목,0),0)) | L27: =IF($K27=0,"",INDEX('ETF데이터'!$M$4:$M$594,$K27)) | M27: =IF($K27=0,"",INDEX('ETF데이터'!$R$4:$R$594,$K27)) | N27: =IF(OR($M27="",$M27="월배당"),0,1) | O27: =IF($K27=0,1,IF(INDEX('ETF데이터'!$T$4:$T$594,$K27)="",1,INDEX('ETF데이터'!$T$4:$T$594,$K27))) | P27: =IF($K27=0,0,IF(INDEX('ETF데이터'!$T$4:$T$594,$K27)="",1,0))
B28: =IF(담긴수=0,"",IFERROR(INDEX(담긴목록,9),"")) | C28: =IF($B28="","",IF($C$12="비율",IF(9<MAX(담긴수,1),ROUND(100/MAX(담긴수,1),2),100-ROUND(100/MAX(담긴수,1),2)*(MAX(담긴수,1)-1)),IF(9<MAX(담긴수,1),ROUNDDOWN($C$11/MAX(담긴수,1),0),$C$11-ROUNDDOWN($C$11/MAX(담긴수,1),0)*(MAX(담긴수,1)-1)))) | D28: =IF($K28=0,0,IF($C$12="비율",ROUND($C$11*$C28/100,0),$C28)) | E28: =IF($K28=0,0,ROUNDDOWN($D28/INDEX('ETF데이터'!$D$4:$D$594,$K28),0)) | F28: =IF($K28=0,0,$E28*INDEX('ETF데이터'!$D$4:$D$594,$K28)) | G28: =IF($K28=0,0,$F28*INDEX('ETF데이터'!$J$4:$J$594,$K28)/12) | H28: =$G28*(1-$C$13*$O28) | K28: =IF($B28="",0,IFERROR(MATCH($B28,선택가능종목,0),0)) | L28: =IF($K28=0,"",INDEX('ETF데이터'!$M$4:$M$594,$K28)) | M28: =IF($K28=0,"",INDEX('ETF데이터'!$R$4:$R$594,$K28)) | N28: =IF(OR($M28="",$M28="월배당"),0,1) | O28: =IF($K28=0,1,IF(INDEX('ETF데이터'!$T$4:$T$594,$K28)="",1,INDEX('ETF데이터'!$T$4:$T$594,$K28))) | P28: =IF($K28=0,0,IF(INDEX('ETF데이터'!$T$4:$T$594,$K28)="",1,0))
B29: =IF(담긴수=0,"",IFERROR(INDEX(담긴목록,10),"")) | C29: =IF($B29="","",IF($C$12="비율",IF(10<MAX(담긴수,1),ROUND(100/MAX(담긴수,1),2),100-ROUND(100/MAX(담긴수,1),2)*(MAX(담긴수,1)-1)),IF(10<MAX(담긴수,1),ROUNDDOWN($C$11/MAX(담긴수,1),0),$C$11-ROUNDDOWN($C$11/MAX(담긴수,1),0)*(MAX(담긴수,1)-1)))) | D29: =IF($K29=0,0,IF($C$12="비율",ROUND($C$11*$C29/100,0),$C29)) | E29: =IF($K29=0,0,ROUNDDOWN($D29/INDEX('ETF데이터'!$D$4:$D$594,$K29),0)) | F29: =IF($K29=0,0,$E29*INDEX('ETF데이터'!$D$4:$D$594,$K29)) | G29: =IF($K29=0,0,$F29*INDEX('ETF데이터'!$J$4:$J$594,$K29)/12) | H29: =$G29*(1-$C$13*$O29) | K29: =IF($B29="",0,IFERROR(MATCH($B29,선택가능종목,0),0)) | L29: =IF($K29=0,"",INDEX('ETF데이터'!$M$4:$M$594,$K29)) | M29: =IF($K29=0,"",INDEX('ETF데이터'!$R$4:$R$594,$K29)) | N29: =IF(OR($M29="",$M29="월배당"),0,1) | O29: =IF($K29=0,1,IF(INDEX('ETF데이터'!$T$4:$T$594,$K29)="",1,INDEX('ETF데이터'!$T$4:$T$594,$K29))) | P29: =IF($K29=0,0,IF(INDEX('ETF데이터'!$T$4:$T$594,$K29)="",1,0))
B30: 합계 | C30: =SUM(C20:C29) | D30: =SUM(D20:D29) | F30: =SUM(F20:F29) | G30: =SUM(G20:G29) | H30: =SUM(H20:H29)
B31: =IF($C$12="비율",IF(ABS($C30-100)>0.01,"※ 배분 비율 합계가 100%가 아닙니다. 배분 칸을 확인하십시오.",""),IF($D30>$C$11,"※ 배분 금액 합계가 총 투자금액을 넘습니다.",""))
B32: =IF(COUNTIF($L$20:$L$29,"제외")>0,"※ 유동성·변동성 기준에 미달한 종목이 담겨 있습니다. [ETF데이터] 장의 제외 사유를 확인하십시오.","")
B33: =IF(SUM($N$20:$N$29)>0,"※ 월배당이 아닌 종목이 담겨 있습니다. 위의 '월 예상 분배금' 은 연 분배금을 12로 나눈 월 환산액이며, 실제 지급은 그 종목의 주기(분기·연 등)를 따릅니다.","")
B34: =IF(SUM($P$20:$P$29)>0,"※ 과세표준을 확인하지 못한 종목이 담겨 있습니다. 그 종목은 분배금 전액에 세율을 적용해 계산했으므로, 실제 세후 수령액은 표시된 금액보다 많을 수 있습니다.","")
B35: 빈 줄은 계산에서 빠집니다. 한 종목만 담으려면 첫 줄에만 넣고 배분을 100 으로 두십시오.
A38: 3 | B38: 예상 분배금 요약
B40: 총 투자금액 | C40: =$C$11 | F40: 월 예상 분배금 (세전) | G40: =$G$30
B41: 실제 투자금액 | C41: =$F$30 | F41: 월 예상 분배금 (세후) | G41: =$H$30
B42: 미투자 잔액 | C42: =$C$11-$F$30 | F42: 연 예상 분배금 (세전) | G42: =$G$30*12
B43: 담은 종목 수 | C43: =COUNTIF($K$20:$K$29,">0") | F43: 연 예상 분배금 (세후) | G43: =$H$30*12
B44: 연 수익률 (세전, 가중평균) | C44: =IF($F$30=0,0,$G$30*12/$F$30) | F44: 월 수익률 (세전) | G44: =IF($F$30=0,0,$G$30/$F$30)
B45: 연 수익률 (세후, 가중평균) | C45: =IF($F$30=0,0,$H$30*12/$F$30) | F45: 월 수익률 (세후) | G45: =IF($F$30=0,0,$H$30/$F$30)
B46: 연 수익률은 담은 종목들의 최근 12개월 실제 분배금을 투자 비중으로 가중한 값입니다. 확정 수익률이 아니며 매월 달라집니다.
A49: 4 | B49: 총 투자금액별 예상 분배금 (위 구성을 그대로 두고 금액만 바꿨을 때)
B51: 투자금액 구간 | C51: 월 분배금(세전) | D51: 월 분배금(세후) | E51: 연 분배금(세전) | F51: 연 분배금(세후)
B52: 10000000 | C52: =$B52*$C$44/12 | D52: =$C52*IF($G$30=0,1-$C$13,$H$30/$G$30) | E52: =$B52*$C$44 | F52: =$E52*IF($G$30=0,1-$C$13,$H$30/$G$30)
B53: 30000000 | C53: =$B53*$C$44/12 | D53: =$C53*IF($G$30=0,1-$C$13,$H$30/$G$30) | E53: =$B53*$C$44 | F53: =$E53*IF($G$30=0,1-$C$13,$H$30/$G$30)
B54: 50000000 | C54: =$B54*$C$44/12 | D54: =$C54*IF($G$30=0,1-$C$13,$H$30/$G$30) | E54: =$B54*$C$44 | F54: =$E54*IF($G$30=0,1-$C$13,$H$30/$G$30)
B55: 100000000 | C55: =$B55*$C$44/12 | D55: =$C55*IF($G$30=0,1-$C$13,$H$30/$G$30) | E55: =$B55*$C$44 | F55: =$E55*IF($G$30=0,1-$C$13,$H$30/$G$30)
B56: 200000000 | C56: =$B56*$C$44/12 | D56: =$C56*IF($G$30=0,1-$C$13,$H$30/$G$30) | E56: =$B56*$C$44 | F56: =$E56*IF($G$30=0,1-$C$13,$H$30/$G$30)
B57: 300000000 | C57: =$B57*$C$44/12 | D57: =$C57*IF($G$30=0,1-$C$13,$H$30/$G$30) | E57: =$B57*$C$44 | F57: =$E57*IF($G$30=0,1-$C$13,$H$30/$G$30)
B58: 500000000 | C58: =$B58*$C$44/12 | D58: =$C58*IF($G$30=0,1-$C$13,$H$30/$G$30) | E58: =$B58*$C$44 | F58: =$E58*IF($G$30=0,1-$C$13,$H$30/$G$30)
B59: 1000000000 | C59: =$B59*$C$44/12 | D59: =$C59*IF($G$30=0,1-$C$13,$H$30/$G$30) | E59: =$B59*$C$44 | F59: =$E59*IF($G$30=0,1-$C$13,$H$30/$G$30)
B60: ※ 단주 절사를 반영하지 않은 근사치라 2·3. 의 값과 몇 천 원 차이가 날 수 있습니다.
A63: 5 | B63: 월배당 ETF 비교 (1억원 단독 투자 기준 · 연 분배율 상위 8 + 순자산 상위 6, 파킹형 제외 · 채택 월배당 67종목 중)
B65: 종목명 | C65: 유형 | D65: 현재가 | E65: 연 분배율 | F65: 월 분배금(세전) | G65: 월 분배금(세후) | H65: 변동성(1년)
B66: ='ETF데이터'!$A$4 | C66: ='ETF데이터'!$P$4 | D66: ='ETF데이터'!$D$4 | E66: ='ETF데이터'!$J$4 | F66: =IF($D66=0,0,ROUNDDOWN(100000000/$D66,0)*$D66*$E66/12) | G66: =$F66*(1-$C$13*'ETF데이터'!$T$4) | H66: ='ETF데이터'!$H$4
B67: ='ETF데이터'!$A$5 | C67: ='ETF데이터'!$P$5 | D67: ='ETF데이터'!$D$5 | E67: ='ETF데이터'!$J$5 | F67: =IF($D67=0,0,ROUNDDOWN(100000000/$D67,0)*$D67*$E67/12) | G67: =$F67*(1-$C$13*'ETF데이터'!$T$5) | H67: ='ETF데이터'!$H$5
B68: ='ETF데이터'!$A$6 | C68: ='ETF데이터'!$P$6 | D68: ='ETF데이터'!$D$6 | E68: ='ETF데이터'!$J$6 | F68: =IF($D68=0,0,ROUNDDOWN(100000000/$D68,0)*$D68*$E68/12) | G68: =$F68*(1-$C$13*'ETF데이터'!$T$6) | H68: ='ETF데이터'!$H$6
B69: ='ETF데이터'!$A$7 | C69: ='ETF데이터'!$P$7 | D69: ='ETF데이터'!$D$7 | E69: ='ETF데이터'!$J$7 | F69: =IF($D69=0,0,ROUNDDOWN(100000000/$D69,0)*$D69*$E69/12) | G69: =$F69*(1-$C$13*'ETF데이터'!$T$7) | H69: ='ETF데이터'!$H$7
B70: ='ETF데이터'!$A$8 | C70: ='ETF데이터'!$P$8 | D70: ='ETF데이터'!$D$8 | E70: ='ETF데이터'!$J$8 | F70: =IF($D70=0,0,ROUNDDOWN(100000000/$D70,0)*$D70*$E70/12) | G70: =$F70*(1-$C$13*'ETF데이터'!$T$8) | H70: ='ETF데이터'!$H$8
B71: ='ETF데이터'!$A$9 | C71: ='ETF데이터'!$P$9 | D71: ='ETF데이터'!$D$9 | E71: ='ETF데이터'!$J$9 | F71: =IF($D71=0,0,ROUNDDOWN(100000000/$D71,0)*$D71*$E71/12) | G71: =$F71*(1-$C$13*'ETF데이터'!$T$9) | H71: ='ETF데이터'!$H$9
B72: ='ETF데이터'!$A$10 | C72: ='ETF데이터'!$P$10 | D72: ='ETF데이터'!$D$10 | E72: ='ETF데이터'!$J$10 | F72: =IF($D72=0,0,ROUNDDOWN(100000000/$D72,0)*$D72*$E72/12) | G72: =$F72*(1-$C$13*'ETF데이터'!$T$10) | H72: ='ETF데이터'!$H$10
B73: ='ETF데이터'!$A$11 | C73: ='ETF데이터'!$P$11 | D73: ='ETF데이터'!$D$11 | E73: ='ETF데이터'!$J$11 | F73: =IF($D73=0,0,ROUNDDOWN(100000000/$D73,0)*$D73*$E73/12) | G73: =$F73*(1-$C$13*'ETF데이터'!$T$11) | H73: ='ETF데이터'!$H$11
B74: ='ETF데이터'!$A$17 | C74: ='ETF데이터'!$P$17 | D74: ='ETF데이터'!$D$17 | E74: ='ETF데이터'!$J$17 | F74: =IF($D74=0,0,ROUNDDOWN(100000000/$D74,0)*$D74*$E74/12) | G74: =$F74*(1-$C$13*'ETF데이터'!$T$17) | H74: ='ETF데이터'!$H$17
B75: ='ETF데이터'!$A$25 | C75: ='ETF데이터'!$P$25 | D75: ='ETF데이터'!$D$25 | E75: ='ETF데이터'!$J$25 | F75: =IF($D75=0,0,ROUNDDOWN(100000000/$D75,0)*$D75*$E75/12) | G75: =$F75*(1-$C$13*'ETF데이터'!$T$25) | H75: ='ETF데이터'!$H$25
B76: ='ETF데이터'!$A$40 | C76: ='ETF데이터'!$P$40 | D76: ='ETF데이터'!$D$40 | E76: ='ETF데이터'!$J$40 | F76: =IF($D76=0,0,ROUNDDOWN(100000000/$D76,0)*$D76*$E76/12) | G76: =$F76*(1-$C$13*'ETF데이터'!$T$40) | H76: ='ETF데이터'!$H$40
B77: ='ETF데이터'!$A$54 | C77: ='ETF데이터'!$P$54 | D77: ='ETF데이터'!$D$54 | E77: ='ETF데이터'!$J$54 | F77: =IF($D77=0,0,ROUNDDOWN(100000000/$D77,0)*$D77*$E77/12) | G77: =$F77*(1-$C$13*'ETF데이터'!$T$54) | H77: ='ETF데이터'!$H$54
B78: ='ETF데이터'!$A$64 | C78: ='ETF데이터'!$P$64 | D78: ='ETF데이터'!$D$64 | E78: ='ETF데이터'!$J$64 | F78: =IF($D78=0,0,ROUNDDOWN(100000000/$D78,0)*$D78*$E78/12) | G78: =$F78*(1-$C$13*'ETF데이터'!$T$64) | H78: ='ETF데이터'!$H$64
B79: ='ETF데이터'!$A$88 | C79: ='ETF데이터'!$P$88 | D79: ='ETF데이터'!$D$88 | E79: ='ETF데이터'!$J$88 | F79: =IF($D79=0,0,ROUNDDOWN(100000000/$D79,0)*$D79*$E79/12) | G79: =$F79*(1-$C$13*'ETF데이터'!$T$88) | H79: ='ETF데이터'!$H$88
B80: ※ 드롭다운에는 기준 미달 종목까지 전부 담겨 있습니다. 위 표에는 기준을 통과한 종목만 실었습니다.
A83: 6 | B83: 유의사항
B85: · 이 자료는 투자 권유가 아니라 참고 자료입니다. 최종 투자 판단과 그 결과는 투자자 본인에게 귀속됩니다.
B86: · ETF 는 예금자보호법의 보호를 받지 않으며, 원금 손실이 발생할 수 있습니다.
B87: · 분배금은 확정되지 않습니다. 커버드콜 ETF 의 분배 재원은 옵션 프리미엄이므로, 시장 변동성이 낮아지면 분배금도 함께 줄어듭니다.
B88: · 분배금의 일부가 원금에서 지급될 수 있습니다(자본 환급). 이 경우 기준가가 그만큼 낮아집니다.
B89: · 표시된 연 분배율은 최근 12개월 실제 분배금 합계를 현재가로 나눈 값(사후 수치)이며, 앞으로의 수익률을 보장하지 않습니다.
B90: · 세율은 국내 상장 ETF 분배금 기준 15.4%(배당소득세 14% + 지방소득세 1.4%)를 적용했습니다. 금융소득종합과세 대상자는 실효세율이 달라집니다.
B91: · 세금은 분배금 전액이 아니라 과세표준액에만 붙습니다. 국내주식 매매차익과 장내파생 손익은 과세표준에 들어가지 않으므로, 그 재원으로 분배하는 종목은 분배금의 상당 부분이 비과세입니다. 그래서 종목마다 다른 과세비율을 적용했습니다(고를 수 있는 591종목 중 591종목). 비율은 [ETF데이터] 장의 '과세비율' 칸에 있습니다.
B92: · 과세비율은 최근 12개월에 실제로 매겨진 과세표준액을 같은 기간 분배금으로 나눈 값입니다. 지나간 실적이므로 앞으로도 같다는 뜻은 아닙니다 — 분배 재원(배당·이자·매매차익·파생손익)의 구성이 바뀌면 비율도 함께 바뀌고, 실제로 한 종목 안에서도 회차마다 0%에서 17%까지 움직인 사례가 있습니다. 실제 세액은 지급 시점의 과세표준으로 확정되므로 이 표와 다를 수 있습니다. 과세비율을 확인하지 못한 종목은 그 칸이 비어 있고, 분배금 전액에 세율을 적용해 보수적으로 계산했으므로 실제 세후 수령액이 표시된 금액보다 많을 수 있습니다.
B93: · 세무 상담이 필요한 사안은 이 문서로 갈음하지 마시고 세무 전문가의 확인을 받으십시오.
B94: · 매매수수료·거래세·환율 변동은 반영하지 않았습니다. 총보수는 분배율에 이미 반영되어 있습니다(기준가 차감).
B95: · 수량은 정수 매수를 가정해 내림 처리했습니다. 남는 금액은 '미투자 잔액'에 표시됩니다.
B96: · 여러 종목에 나눠 담아도 분배 시기는 종목마다 다릅니다. 매월 같은 날 한꺼번에 들어오지 않습니다.
... B100: 자료 출처 ETFCHECK (www.etfcheck.co.kr) · 수집 2026-10-04T14:13:52.041Z · 대상 국내 상장 월배당 ETF · 채택 기준 순자산 300억원 이상, 60일 평균거래대금 5억원 이상, 연환산 변동성 35% 이하, 분배 이력 12개월 이상

Sheet 종목조회
A1: 사내한 · Confidential
A2: ETF 종목 조회
A3: ETF Screener
A5: 자료 ETFCHECK · 기준일 2026-10-02 · 지급주기와 연 분배율로 고릅니다
A8: 1 | B8: 조회 조건
B10: 지급주기 | C10: 전체 | E10: 분배율은 백분율로 넣으십시오 (예: 5%). 최소·최대 사이에 드는 종목만 나옵니다.
B11: 연 분배율 최소 | C11: 0 | E11: '판정 불가' 는 상장 1년이 안 돼 주기를 말할 수 없는 종목입니다. 빼지 않고 그대로 담았습니다.
B12: 연 분배율 최대 | C12: 1 | E12: 결과는 기준을 통과한 종목이 먼저, 그 안에서 연 분배율 높은 순입니다.
B14: 조건에 맞는 종목 | C14: =COUNTIF('ETF데이터'!$AA$4:$AA$594,1) | D14: 전체 591종목 중
A17: 2 | B17: 조회 결과 (최대 60종목)
B19: 종목명 | C19: 지급주기 | D19: 연 분배율 | E19: 월 환산 | F19: 현재가 | G19: 변동성 | H19: 순자산 | I19: 총수익 1년 | J19: 기준가 1년 | K19: 기준가 6개월 | L19: 기준가 3개월 | M19: 채택 | N19: 담기
B20: =IF($O20=0,"",INDEX('ETF데이터'!$A$4:$A$594,$O20)) | C20: =IF($O20=0,"",INDEX('ETF데이터'!$R$4:$R$594,$O20)) | D20: =IF($O20=0,"",INDEX('ETF데이터'!$J$4:$J$594,$O20)) | E20: =IF($O20=0,"",$D20/12) | F20: =IF($O20=0,"",INDEX('ETF데이터'!$D$4:$D$594,$O20)) | G20: =IF($O20=0,"",INDEX('ETF데이터'!$H$4:$H$594,$O20)) | H20: =IF($O20=0,"",INDEX('ETF데이터'!$E$4:$E$594,$O20)/100000000) | I20: =IF($O20=0,"",IF(INDEX('ETF데이터'!$U$4:$U$594,$O20)="","",INDEX('ETF데이터'!$U$4:$U$594,$O20))) | J20: =IF($O20=0,"",IF(INDEX('ETF데이터'!$V$4:$V$594,$O20)="","",INDEX('ETF데이터'!$V$4:$V$594,$O20))) | K20: =IF($O20=0,"",IF(INDEX('ETF데이터'!$W$4:$W$594,$O20)="","",INDEX('ETF데이터'!$W$4:$W$594,$O20))) | L20: =IF($O20=0,"",IF(INDEX('ETF데이터'!$X$4:$X$594,$O20)="","",INDEX('ETF데이터'!$X$4:$X$594,$O20))) | M20: =IF($O20=0,"",INDEX('ETF데이터'!$M$4:$M$594,$O20)) | O20: =IFERROR(MATCH(1,'ETF데이터'!$AB$4:$AB$594,0),0) | P20: =IF(AND($B20<>"",$N20<>""),1,0) | Q20: =IF($P20=1,0+1,0) | R20: =IFERROR(INDEX($B$20:$B$79,MATCH(1,$Q$20:$Q$79,0)),"")
B21: =IF($O21=0,"",INDEX('ETF데이터'!$A$4:$A$594,$O21)) | C21: =IF($O21=0,"",INDEX('ETF데이터'!$R$4:$R$594,$O21)) | D21: =IF($O21=0,"",INDEX('ETF데이터'!$J$4:$J$594,$O21)) | E21: =IF($O21=0,"",$D21/12) | F21: =IF($O21=0,"",INDEX('ETF데이터'!$D$4:$D$594,$O21)) | G21: =IF($O21=0,"",INDEX('ETF데이터'!$H$4:$H$594,$O21)) | H21: =IF($O21=0,"",INDEX('ETF데이터'!$E$4:$E$594,$O21)/100000000) | I21: =IF($O21=0,"",IF(INDEX('ETF데이터'!$U$4:$U$594,$O21)="","",INDEX('ETF데이터'!$U$4:$U$594,$O21))) | J21: =IF($O21=0,"",IF(INDEX('ETF데이터'!$V$4:$V$594,$O21)="","",INDEX('ETF데이터'!$V$4:$V$594,$O21))) | K21: =IF($O21=0,"",IF(INDEX('ETF데이터'!$W$4:$W$594,$O21)="","",INDEX('ETF데이터'!$W$4:$W$594,$O21))) | L21: =IF($O21=0,"",IF(INDEX('ETF데이터'!$X$4:$X$594,$O21)="","",INDEX('ETF데이터'!$X$4:$X$594,$O21))) | M21: =IF($O21=0,"",INDEX('ETF데이터'!$M$4:$M$594,$O21)) | O21: =IFERROR(MATCH(2,'ETF데이터'!$AB$4:$AB$594,0),0) | P21: =IF(AND($B21<>"",$N21<>""),1,0) | Q21: =IF($P21=1,$Q20+1,$Q20) | R21: =IFERROR(INDEX($B$20:$B$79,MATCH(2,$Q$20:$Q$79,0)),"")
B22: =IF($O22=0,"",INDEX('ETF데이터'!$A$4:$A$594,$O22)) | C22: =IF($O22=0,"",INDEX('ETF데이터'!$R$4:$R$594,$O22)) | D22: =IF($O22=0,"",INDEX('ETF데이터'!$J$4:$J$594,$O22)) | E22: =IF($O22=0,"",$D22/12) | F22: =IF($O22=0,"",INDEX('ETF데이터'!$D$4:$D$594,$O22)) | G22: =IF($O22=0,"",INDEX('ETF데이터'!$H$4:$H$594,$O22)) | H22: =IF($O22=0,"",INDEX('ETF데이터'!$E$4:$E$594,$O22)/100000000) | I22: =IF($O22=0,"",IF(INDEX('ETF데이터'!$U$4:$U$594,$O22)="","",INDEX('ETF데이터'!$U$4:$U$594,$O22))) | J22: =IF($O22=0,"",IF(INDEX('ETF데이터'!$V$4:$V$594,$O22)="","",INDEX('ETF데이터'!$V$4:$V$594,$O22))) | K22: =IF($O22=0,"",IF(INDEX('ETF데이터'!$W$4:$W$594,$O22)="","",INDEX('ETF데이터'!$W$4:$W$594,$O22))) | L22: =IF($O22=0,"",IF(INDEX('ETF데이터'!$X$4:$X$594,$O22)="","",INDEX('ETF데이터'!$X$4:$X$594,$O22))) | M22: =IF($O22=0,"",INDEX('ETF데이터'!$M$4:$M$594,$O22)) | O22: =IFERROR(MATCH(3,'ETF데이터'!$AB$4:$AB$594,0),0) | P22: =IF(AND($B22<>"",$N22<>""),1,0) | Q22: =IF($P22=1,$Q21+1,$Q21) | R22: =IFERROR(INDEX($B$20:$B$79,MATCH(3,$Q$20:$Q$79,0)),"")
B23: =IF($O23=0,"",INDEX('ETF데이터'!$A$4:$A$594,$O23)) | C23: =IF($O23=0,"",INDEX('ETF데이터'!$R$4:$R$594,$O23)) | D23: =IF($O23=0,"",INDEX('ETF데이터'!$J$4:$J$594,$O23)) | E23: =IF($O23=0,"",$D23/12) | F23: =IF($O23=0,"",INDEX('ETF데이터'!$D$4:$D$594,$O23)) | G23: =IF($O23=0,"",INDEX('ETF데이터'!$H$4:$H$594,$O23)) | H23: =IF($O23=0,"",INDEX('ETF데이터'!$E$4:$E$594,$O23)/100000000) | I23: =IF($O23=0,"",IF(INDEX('ETF데이터'!$U$4:$U$594,$O23)="","",INDEX('ETF데이터'!$U$4:$U$594,$O23))) | J23: =IF($O23=0,"",IF(INDEX('ETF데이터'!$V$4:$V$594,$O23)="","",INDEX('ETF데이터'!$V$4:$V$594,$O23))) | K23: =IF($O23=0,"",IF(INDEX('ETF데이터'!$W$4:$W$594,$O23)="","",INDEX('ETF데이터'!$W$4:$W$594,$O23))) | L23: =IF($O23=0,"",IF(INDEX('ETF데이터'!$X$4:$X$594,$O23)="","",INDEX('ETF데이터'!$X$4:$X$594,$O23))) | M23: =IF($O23=0,"",INDEX('ETF데이터'!$M$4:$M$594,$O23)) | O23: =IFERROR(MATCH(4,'ETF데이터'!$AB$4:$AB$594,0),0) | P23: =IF(AND($B23<>"",$N23<>""),1,0) | Q23: =IF($P23=1,$Q22+1,$Q22) | R23: =IFERROR(INDEX($B$20:$B$79,MATCH(4,$Q$20:$Q$79,0)),"")
B24: =IF($O24=0,"",INDEX('ETF데이터'!$A$4:$A$594,$O24)) | C24: =IF($O24=0,"",INDEX('ETF데이터'!$R$4:$R$594,$O24)) | D24: =IF($O24=0,"",INDEX('ETF데이터'!$J$4:$J$594,$O24)) | E24: =IF($O24=0,"",$D24/12) | F24: =IF($O24=0,"",INDEX('ETF데이터'!$D$4:$D$594,$O24)) | G24: =IF($O24=0,"",INDEX('ETF데이터'!$H$4:$H$594,$O24)) | H24: =IF($O24=0,"",INDEX('ETF데이터'!$E$4:$E$594,$O24)/100000000) | I24: =IF($O24=0,"",IF(INDEX('ETF데이터'!$U$4:$U$594,$O24)="","",INDEX('ETF데이터'!$U$4:$U$594,$O24))) | J24: =IF($O24=0,"",IF(INDEX('ETF데이터'!$V$4:$V$594,$O24)="","",INDEX('ETF데이터'!$V$4:$V$594,$O24))) | K24: =IF($O24=0,"",IF(INDEX('ETF데이터'!$W$4:$W$594,$O24)="","",INDEX('ETF데이터'!$W$4:$W$594,$O24))) | L24: =IF($O24=0,"",IF(INDEX('ETF데이터'!$X$4:$X$594,$O24)="","",INDEX('ETF데이터'!$X$4:$X$594,$O24))) | M24: =IF($O24=0,"",INDEX('ETF데이터'!$M$4:$M$594,$O24)) | O24: =IFERROR(MATCH(5,'ETF데이터'!$AB$4:$AB$594,0),0) | P24: =IF(AND($B24<>"",$N24<>""),1,0) | Q24: =IF($P24=1,$Q23+1,$Q23) | R24: =IFERROR(INDEX($B$20:$B$79,MATCH(5,$Q$20:$Q$79,0)),"")
B25: =IF($O25=0,"",INDEX('ETF데이터'!$A$4:$A$594,$O25)) | C25: =IF($O25=0,"",INDEX('ETF데이터'!$R$4:$R$594,$O25)) | D25: =IF($O25=0,"",INDEX('ETF데이터'!$J$4:$J$594,$O25)) | E25: =IF($O25=0,"",$D25/12) | F25: =IF($O25=0,"",INDEX('ETF데이터'!$D$4:$D$594,$O25)) | G25: =IF($O25=0,"",INDEX('ETF데이터'!$H$4:$H$594,$O25)) | H25: =IF($O25=0,"",INDEX('ETF데이터'!$E$4:$E$594,$O25)/100000000) | I25: =IF($O25=0,"",IF(INDEX('ETF데이터'!$U$4:$U$594,$O25)="","",INDEX('ETF데이터'!$U$4:$U$594,$O25))) | J25: =IF($O25=0,"",IF(INDEX('ETF데이터'!$V$4:$V$594,$O25)="","",INDEX('ETF데이터'!$V$4:$V$594,$O25))) | K25: =IF($O25=0,"",IF(INDEX('ETF데이터'!$W$4:$W$594,$O25)="","",INDEX('ETF데이터'!$W$4:$W$594,$O25))) | L25: =IF($O25=0,"",IF(INDEX('ETF데이터'!$X$4:$X$594,$O25)="","",INDEX('ETF데이터'!$X$4:$X$594,$O25))) | M25: =IF($O25=0,"",INDEX('ETF데이터'!$M$4:$M$594,$O25)) | O25: =IFERROR(MATCH(6,'ETF데이터'!$AB$4:$AB$594,0),0) | P25: =IF(AND($B25<>"",$N25<>""),1,0) | Q25: =IF($P25=1,$Q24+1,$Q24) | R25: =IFERROR(INDEX($B$20:$B$79,MATCH(6,$Q$20:$Q$79,0)),"")
B26: =IF($O26=0,"",INDEX('ETF데이터'!$A$4:$A$594,$O26)) | C26: =IF($O26=0,"",INDEX('ETF데이터'!$R$4:$R$594,$O26)) | D26: =IF($O26=0,"",INDEX('ETF데이터'!$J$4:$J$594,$O26)) | E26: =IF($O26=0,"",$D26/12) | F26: =IF($O26=0,"",INDEX('ETF데이터'!$D$4:$D$594,$O26)) | G26: =IF($O26=0,"",INDEX('ETF데이터'!$H$4:$H$594,$O26)) | H26: =IF($O26=0,"",INDEX('ETF데이터'!$E$4:$E$594,$O26)/100000000) | I26: =IF($O26=0,"",IF(INDEX('ETF데이터'!$U$4:$U$594,$O26)="","",INDEX('ETF데이터'!$U$4:$U$594,$O26))) | J26: =IF($O26=0,"",IF(INDEX('ETF데이터'!$V$4:$V$594,$O26)="","",INDEX('ETF데이터'!$V$4:$V$594,$O26))) | K26: =IF($O26=0,"",IF(INDEX('ETF데이터'!$W$4:$W$594,$O26)="","",INDEX('ETF데이터'!$W$4:$W$594,$O26))) | L26: =IF($O26=0,"",IF(INDEX('ETF데이터'!$X$4:$X$594,$O26)="","",INDEX('ETF데이터'!$X$4:$X$594,$O26))) | M26: =IF($O26=0,"",INDEX('ETF데이터'!$M$4:$M$594,$O26)) | O26: =IFERROR(MATCH(7,'ETF데이터'!$AB$4:$AB$594,0),0) | P26: =IF(AND($B26<>"",$N26<>""),1,0) | Q26: =IF($P26=1,$Q25+1,$Q25) | R26: =IFERROR(INDEX($B$20:$B$79,MATCH(7,$Q$20:$Q$79,0)),"")
B27: =IF($O27=0,"",INDEX('ETF데이터'!$A$4:$A$594,$O27)) | C27: =IF($O27=0,"",INDEX('ETF데이터'!$R$4:$R$594,$O27)) | D27: =IF($O27=0,"",INDEX('ETF데이터'!$J$4:$J$594,$O27)) | E27: =IF($O27=0,"",$D27/12) | F27: =IF($O27=0,"",INDEX('ETF데이터'!$D$4:$D$594,$O27)) | G27: =IF($O27=0,"",INDEX('ETF데이터'!$H$4:$H$594,$O27)) | H27: =IF($O27=0,"",INDEX('ETF데이터'!$E$4:$E$594,$O27)/100000000) | I27: =IF($O27=0,"",IF(INDEX('ETF데이터'!$U$4:$U$594,$O27)="","",INDEX('ETF데이터'!$U$4:$U$594,$O27))) | J27: =IF($O27=0,"",IF(INDEX('ETF데이터'!$V$4:$V$594,$O27)="","",INDEX('ETF데이터'!$V$4:$V$594,$O27))) | K27: =IF($O27=0,"",IF(INDEX('ETF데이터'!$W$4:$W$594,$O27)="","",INDEX('ETF데이터'!$W$4:$W$594,$O27))) | L27: =IF($O27=0,"",IF(INDEX('ETF데이터'!$X$4:$X$594,$O27)="","",INDEX('ETF데이터'!$X$4:$X$594,$O27))) | M27: =IF($O27=0,"",INDEX('ETF데이터'!$M$4:$M$594,$O27)) | O27: =IFERROR(MATCH(8,'ETF데이터'!$AB$4:$AB$594,0),0) | P27: =IF(AND($B27<>"",$N27<>""),1,0) | Q27: =IF($P27=1,$Q26+1,$Q26) | R27: =IFERROR(INDEX($B$20:$B$79,MATCH(8,$Q$20:$Q$79,0)),"")
B28: =IF($O28=0,"",INDEX('ETF데이터'!$A$4:$A$594,$O28)) | C28: =IF($O28=0,"",INDEX('ETF데이터'!$R$4:$R$594,$O28)) | D28: =IF($O28=0,"",INDEX('ETF데이터'!$J$4:$J$594,$O28)) | E28: =IF($O28=0,"",$D28/12) | F28: =IF($O28=0,"",INDEX('ETF데이터'!$D$4:$D$594,$O28)) | G28: =IF($O28=0,"",INDEX('ETF데이터'!$H$4:$H$594,$O28)) | H28: =IF($O28=0,"",INDEX('ETF데이터'!$E$4:$E$594,$O28)/100000000) | I28: =IF($O28=0,"",IF(INDEX('ETF데이터'!$U$4:$U$594,$O28)="","",INDEX('ETF데이터'!$U$4:$U$594,$O28))) | J28: =IF($O28=0,"",IF(INDEX('ETF데이터'!$V$4:$V$594,$O28)="","",INDEX('ETF데이터'!$V$4:$V$594,$O28))) | K28: =IF($O28=0,"",IF(INDEX('ETF데이터'!$W$4:$W$594,$O28)="","",INDEX('ETF데이터'!$W$4:$W$594,$O28))) | L28: =IF($O28=0,"",IF(INDEX('ETF데이터'!$X$4:$X$594,$O28)="","",INDEX('ETF데이터'!$X$4:$X$594,$O28))) | M28: =IF($O28=0,"",INDEX('ETF데이터'!$M$4:$M$594,$O28)) | O28: =IFERROR(MATCH(9,'ETF데이터'!$AB$4:$AB$594,0),0) | P28: =IF(AND($B28<>"",$N28<>""),1,0) | Q28: =IF($P28=1,$Q27+1,$Q27) | R28: =IFERROR(INDEX($B$20:$B$79,MATCH(9,$Q$20:$Q$79,0)),"")
B29: =IF($O29=0,"",INDEX('ETF데이터'!$A$4:$A$594,$O29)) | C29: =IF($O29=0,"",INDEX('ETF데이터'!$R$4:$R$594,$O29)) | D29: =IF($O29=0,"",INDEX('ETF데이터'!$J$4:$J$594,$O29)) | E29: =IF($O29=0,"",$D29/12) | F29: =IF($O29=0,"",INDEX('ETF데이터'!$D$4:$D$594,$O29)) | G29: =IF($O29=0,"",INDEX('ETF데이터'!$H$4:$H$594,$O29)) | H29: =IF($O29=0,"",INDEX('ETF데이터'!$E$4:$E$594,$O29)/100000000) | I29: =IF($O29=0,"",IF(INDEX('ETF데이터'!$U$4:$U$594,$O29)="","",INDEX('ETF데이터'!$U$4:$U$594,$O29))) | J29: =IF($O29=0,"",IF(INDEX('ETF데이터'!$V$4:$V$594,$O29)="","",INDEX('ETF데이터'!$V$4:$V$594,$O29))) | K29: =IF($O29=0,"",IF(INDEX('ETF데이터'!$W$4:$W$594,$O29)="","",INDEX('ETF데이터'!$W$4:$W$594,$O29))) | L29: =IF($O29=0,"",IF(INDEX('ETF데이터'!$X$4:$X$594,$O29)="","",INDEX('ETF데이터'!$X$4:$X$594,$O29))) | M29: =IF($O29=0,"",INDEX('ETF데이터'!$M$4:$M$594,$O29)) | O29: =IFERROR(MATCH(10,'ETF데이터'!$AB$4:$AB$594,0),0) | P29: =IF(AND($B29<>"",$N29<>""),1,0) | Q29: =IF($P29=1,$Q28+1,$Q28) | R29: =IFERROR(INDEX($B$20:$B$79,MATCH(10,$Q$20:$Q$79,0)),"")
B30: =IF($O30=0,"",INDEX('ETF데이터'!$A$4:$A$594,$O30)) | C30: =IF($O30=0,"",INDEX('ETF데이터'!$R$4:$R$594,$O30)) | D30: =IF($O30=0,"",INDEX('ETF데이터'!$J$4:$J$594,$O30)) | E30: =IF($O30=0,"",$D30/12) | F30: =IF($O30=0,"",INDEX('ETF데이터'!$D$4:$D$594,$O30)) | G30: =IF($O30=0,"",INDEX('ETF데이터'!$H$4:$H$594,$O30)) | H30: =IF($O30=0,"",INDEX('ETF데이터'!$E$4:$E$594,$O30)/100000000) | I30: =IF($O30=0,"",IF(INDEX('ETF데이터'!$U$4:$U$594,$O30)="","",INDEX('ETF데이터'!$U$4:$U$594,$O30))) | J30: =IF($O30=0,"",IF(INDEX('ETF데이터'!$V$4:$V$594,$O30)="","",INDEX('ETF데이터'!$V$4:$V$594,$O30))) | K30: =IF($O30=0,"",IF(INDEX('ETF데이터'!$W$4:$W$594,$O30)="","",INDEX('ETF데이터'!$W$4:$W$594,$O30))) | L30: =IF($O30=0,"",IF(INDEX('ETF데이터'!$X$4:$X$594,$O30)="","",INDEX('ETF데이터'!$X$4:$X$594,$O30))) | M30: =IF($O30=0,"",INDEX('ETF데이터'!$M$4:$M$594,$O30)) | O30: =IFERROR(MATCH(11,'ETF데이터'!$AB$4:$AB$594,0),0) | P30: =IF(AND($B30<>"",$N30<>""),1,0) | Q30: =IF($P30=1,$Q29+1,$Q29) | R30: =IFERROR(INDEX($B$20:$B$79,MATCH(11,$Q$20:$Q$79,0)),"")
B31: =IF($O31=0,"",INDEX('ETF데이터'!$A$4:$A$594,$O31)) | C31: =IF($O31=0,"",INDEX('ETF데이터'!$R$4:$R$594,$O31)) | D31: =IF($O31=0,"",INDEX('ETF데이터'!$J$4:$J$594,$O31)) | E31: =IF($O31=0,"",$D31/12) | F31: =IF($O31=0,"",INDEX('ETF데이터'!$D$4:$D$594,$O31)) | G31: =IF($O31=0,"",INDEX('ETF데이터'!$H$4:$H$594,$O31)) | H31: =IF($O31=0,"",INDEX('ETF데이터'!$E$4:$E$594,$O31)/100000000) | I31: =IF($O31=0,"",IF(INDEX('ETF데이터'!$U$4:$U$594,$O31)="","",INDEX('ETF데이터'!$U$4:$U$594,$O31))) | J31: =IF($O31=0,"",IF(INDEX('ETF데이터'!$V$4:$V$594,$O31)="","",INDEX('ETF데이터'!$V$4:$V$594,$O31))) | K31: =IF($O31=0,"",IF(INDEX('ETF데이터'!$W$4:$W$594,$O31)="","",INDEX('ETF데이터'!$W$4:$W$594,$O31))) | L31: =IF($O31=0,"",IF(INDEX('ETF데이터'!$X$4:$X$594,$O31)="","",INDEX('ETF데이터'!$X$4:$X$594,$O31))) | M31: =IF($O31=0,"",INDEX('ETF데이터'!$M$4:$M$594,$O31)) | O31: =IFERROR(MATCH(12,'ETF데이터'!$AB$4:$AB$594,0),0) | P31: =IF(AND($B31<>"",$N31<>""),1,0) | Q31: =IF($P31=1,$Q30+1,$Q30) | R31: =IFERROR(INDEX($B$20:$B$79,MATCH(12,$Q$20:$Q$79,0)),"")
B32: =IF($O32=0,"",INDEX('ETF데이터'!$A$4:$A$594,$O32)) | C32: =IF($O32=0,"",INDEX('ETF데이터'!$R$4:$R$594,$O32)) | D32: =IF($O32=0,"",INDEX('ETF데이터'!$J$4:$J$594,$O32)) | E32: =IF($O32=0,"",$D32/12) | F32: =IF($O32=0,"",INDEX('ETF데이터'!$D$4:$D$594,$O32)) | G32: =IF($O32=0,"",INDEX('ETF데이터'!$H$4:$H$594,$O32)) | H32: =IF($O32=0,"",INDEX('ETF데이터'!$E$4:$E$594,$O32)/100000000) | I32: =IF($O32=0,"",IF(INDEX('ETF데이터'!$U$4:$U$594,$O32)="","",INDEX('ETF데이터'!$U$4:$U$594,$O32))) | J32: =IF($O32=0,"",IF(INDEX('ETF데이터'!$V$4:$V$594,$O32)="","",INDEX('ETF데이터'!$V$4:$V$594,$O32))) | K32: =IF($O32=0,"",IF(INDEX('ETF데이터'!$W$4:$W$594,$O32)="","",INDEX('ETF데이터'!$W$4:$W$594,$O32))) | L32: =IF($O32=0,"",IF(INDEX('ETF데이터'!$X$4:$X$594,$O32)="","",INDEX('ETF데이터'!$X$4:$X$594,$O32))) | M32: =IF($O32=0,"",INDEX('ETF데이터'!$M$4:$M$594,$O32)) | O32: =IFERROR(MATCH(13,'ETF데이터'!$AB$4:$AB$594,0),0) | P32: =IF(AND($B32<>"",$N32<>""),1,0) | Q32: =IF($P32=1,$Q31+1,$Q31) | R32: =IFERROR(INDEX($B$20:$B$79,MATCH(13,$Q$20:$Q$79,0)),"")
B33: =IF($O33=0,"",INDEX('ETF데이터'!$A$4:$A$594,$O33)) | C33: =IF($O33=0,"",INDEX('ETF데이터'!$R$4:$R$594,$O33)) | D33: =IF($O33=0,"",INDEX('ETF데이터'!$J$4:$J$594,$O33)) | E33: =IF($O33=0,"",$D33/12) | F33: =IF($O33=0,"",INDEX('ETF데이터'!$D$4:$D$594,$O33)) | G33: =IF($O33=0,"",INDEX('ETF데이터'!$H$4:$H$594,$O33)) | H33: =IF($O33=0,"",INDEX('ETF데이터'!$E$4:$E$594,$O33)/100000000) | I33: =IF($O33=0,"",IF(INDEX('ETF데이터'!$U$4:$U$594,$O33)="","",INDEX('ETF데이터'!$U$4:$U$594,$O33))) | J33: =IF($O33=0,"",IF(INDEX('ETF데이터'!$V$4:$V$594,$O33)="","",INDEX('ETF데이터'!$V$4:$V$594,$O33))) | K33: =IF($O33=0,"",IF(INDEX('ETF데이터'!$W$4:$W$594,$O33)="","",INDEX('ETF데이터'!$W$4:$W$594,$O33))) | L33: =IF($O33=0,"",IF(INDEX('ETF데이터'!$X$4:$X$594,$O33)="","",INDEX('ETF데이터'!$X$4:$X$594,$O33))) | M33: =IF($O33=0,"",INDEX('ETF데이터'!$M$4:$M$594,$O33)) | O33: =IFERROR(MATCH(14,'ETF데이터'!$AB$4:$AB$594,0),0) | P33: =IF(AND($B33<>"",$N33<>""),1,0) | Q33: =IF($P33=1,$Q32+1,$Q32) | R33: =IFERROR(INDEX($B$20:$B$79,MATCH(14,$Q$20:$Q$79,0)),"")
B34: =IF($O34=0,"",INDEX('ETF데이터'!$A$4:$A$594,$O34)) | C34: =IF($O34=0,"",INDEX('ETF데이터'!$R$4:$R$594,$O34)) | D34: =IF($O34=0,"",INDEX('ETF데이터'!$J$4:$J$594,$O34)) | E34: =IF($O34=0,"",$D34/12) | F34: =IF($O34=0,"",INDEX('ETF데이터'!$D$4:$D$594,$O34)) | G34: =IF($O34=0,"",INDEX('ETF데이터'!$H$4:$H$594,$O34)) | H34: =IF($O34=0,"",INDEX('ETF데이터'!$E$4:$E$594,$O34)/100000000) | I34: =IF($O34=0,"",IF(INDEX('ETF데이터'!$U$4:$U$594,$O34)="","",INDEX('ETF데이터'!$U$4:$U$594,$O34))) | J34: =IF($O34=0,"",IF(INDEX('ETF데이터'!$V$4:$V$594,$O34)="","",INDEX('ETF데이터'!$V$4:$V$594,$O34))) | K34: =IF($O34=0,"",IF(INDEX('ETF데이터'!$W$4:$W$594,$O34)="","",INDEX('ETF데이터'!$W$4:$W$594,$O34))) | L34: =IF($O34=0,"",IF(INDEX('ETF데이터'!$X$4:$X$594,$O34)="","",INDEX('ETF데이터'!$X$4:$X$594,$O34))) | M34: =IF($O34=0,"",INDEX('ETF데이터'!$M$4:$M$594,$O34)) | O34: =IFERROR(MATCH(15,'ETF데이터'!$AB$4:$AB$594,0),0) | P34: =IF(AND($B34<>"",$N34<>""),1,0) | Q34: =IF($P34=1,$Q33+1,$Q33) | R34: =IFERROR(INDEX($B$20:$B$79,MATCH(15,$Q$20:$Q$79,0)),"")
B35: =IF($O35=0,"",INDEX('ETF데이터'!$A$4:$A$594,$O35)) | C35: =IF($O35=0,"",INDEX('ETF데이터'!$R$4:$R$594,$O35)) | D35: =IF($O35=0,"",INDEX('ETF데이터'!$J$4:$J$594,$O35)) | E35: =IF($O35=0,"",$D35/12) | F35: =IF($O35=0,"",INDEX('ETF데이터'!$D$4:$D$594,$O35)) | G35: =IF($O35=0,"",INDEX('ETF데이터'!$H$4:$H$594,$O35)) | H35: =IF($O35=0,"",INDEX('ETF데이터'!$E$4:$E$594,$O35)/100000000) | I35: =IF($O35=0,"",IF(INDEX('ETF데이터'!$U$4:$U$594,$O35)="","",INDEX('ETF데이터'!$U$4:$U$594,$O35))) | J35: =IF($O35=0,"",IF(INDEX('ETF데이터'!$V$4:$V$594,$O35)="","",INDEX('ETF데이터'!$V$4:$V$594,$O35))) | K35: =IF($O35=0,"",IF(INDEX('ETF데이터'!$W$4:$W$594,$O35)="","",INDEX('ETF데이터'!$W$4:$W$594,$O35))) | L35: =IF($O35=0,"",IF(INDEX('ETF데이터'!$X$4:$X$594,$O35)="","",INDEX('ETF데이터'!$X$4:$X$594,$O35))) | M35: =IF($O35=0,"",INDEX('ETF데이터'!$M$4:$M$594,$O35)) | O35: =IFERROR(MATCH(16,'ETF데이터'!$AB$4:$AB$594,0),0) | P35: =IF(AND($B35<>"",$N35<>""),1,0) | Q35: =IF($P35=1,$Q34+1,$Q34) | R35: =IFERROR(INDEX($B$20:$B$79,MATCH(16,$Q$20:$Q$79,0)),"")
B36: =IF($O36=0,"",INDEX('ETF데이터'!$A$4:$A$594,$O36)) | C36: =IF($O36=0,"",INDEX('ETF데이터'!$R$4:$R$594,$O36)) | D36: =IF($O36=0,"",INDEX('ETF데이터'!$J$4:$J$594,$O36)) | E36: =IF($O36=0,"",$D36/12) | F36: =IF($O36=0,"",INDEX('ETF데이터'!$D$4:$D$594,$O36)) | G36: =IF($O36=0,"",INDEX('ETF데이터'!$H$4:$H$594,$O36)) | H36: =IF($O36=0,"",INDEX('ETF데이터'!$E$4:$E$594,$O36)/100000000) | I36: =IF($O36=0,"",IF(INDEX('ETF데이터'!$U$4:$U$594,$O36)="","",INDEX('ETF데이터'!$U$4:$U$594,$O36))) | J36: =IF($O36=0,"",IF(INDEX('ETF데이터'!$V$4:$V$594,$O36)="","",INDEX('ETF데이터'!$V$4:$V$594,$O36))) | K36: =IF($O36=0,"",IF(INDEX('ETF데이터'!$W$4:$W$594,$O36)="","",INDEX('ETF데이터'!$W$4:$W$594,$O36))) | L36: =IF($O36=0,"",IF(INDEX('ETF데이터'!$X$4:$X$594,$O36)="","",INDEX('ETF데이터'!$X$4:$X$594,$O36))) | M36: =IF($O36=0,"",INDEX('ETF데이터'!$M$4:$M$594,$O36)) | O36: =IFERROR(MATCH(17,'ETF데이터'!$AB$4:$AB$594,0),0) | P36: =IF(AND($B36<>"",$N36<>""),1,0) | Q36: =IF($P36=1,$Q35+1,$Q35) | R36: =IFERROR(INDEX($B$20:$B$79,MATCH(17,$Q$20:$Q$79,0)),"")
B37: =IF($O37=0,"",INDEX('ETF데이터'!$A$4:$A$594,$O37)) | C37: =IF($O37=0,"",INDEX('ETF데이터'!$R$4:$R$594,$O37)) | D37: =IF($O37=0,"",INDEX('ETF데이터'!$J$4:$J$594,$O37)) | E37: =IF($O37=0,"",$D37/12) | F37: =IF($O37=0,"",INDEX('ETF데이터'!$D$4:$D$594,$O37)) | G37: =IF($O37=0,"",INDEX('ETF데이터'!$H$4:$H$594,$O37)) | H37: =IF($O37=0,"",INDEX('ETF데이터'!$E$4:$E$594,$O37)/100000000) | I37: =IF($O37=0,"",IF(INDEX('ETF데이터'!$U$4:$U$594,$O37)="","",INDEX('ETF데이터'!$U$4:$U$594,$O37))) | J37: =IF($O37=0,"",IF(INDEX('ETF데이터'!$V$4:$V$594,$O37)="","",INDEX('ETF데이터'!$V$4:$V$594,$O37))) | K37: =IF($O37=0,"",IF(INDEX('ETF데이터'!$W$4:$W$594,$O37)="","",INDEX('ETF데이터'!$W$4:$W$594,$O37))) | L37: =IF($O37=0,"",IF(INDEX('ETF데이터'!$X$4:$X$594,$O37)="","",INDEX('ETF데이터'!$X$4:$X$594,$O37))) | M37: =IF($O37=0,"",INDEX('ETF데이터'!$M$4:$M$594,$O37)) | O37: =IFERROR(MATCH(18,'ETF데이터'!$AB$4:$AB$594,0),0) | P37: =IF(AND($B37<>"",$N37<>""),1,0) | Q37: =IF($P37=1,$Q36+1,$Q36) | R37: =IFERROR(INDEX($B$20:$B$79,MATCH(18,$Q$20:$Q$79,0)),"")
B38: =IF($O38=0,"",INDEX('ETF데이터'!$A$4:$A$594,$O38)) | C38: =IF($O38=0,"",INDEX('ETF데이터'!$R$4:$R$594,$O38)) | D38: =IF($O38=0,"",INDEX('ETF데이터'!$J$4:$J$594,$O38)) | E38: =IF($O38=0,"",$D38/12) | F38: =IF($O38=0,"",INDEX('ETF데이터'!$D$4:$D$594,$O38)) | G38: =IF($O38=0,"",INDEX('ETF데이터'!$H$4:$H$594,$O38)) | H38: =IF($O38=0,"",INDEX('ETF데이터'!$E$4:$E$594,$O38)/100000000) | I38: =IF($O38=0,"",IF(INDEX('ETF데이터'!$U$4:$U$594,$O38)="","",INDEX('ETF데이터'!$U$4:$U$594,$O38))) | J38: =IF($O38=0,"",IF(INDEX('ETF데이터'!$V$4:$V$594,$O38)="","",INDEX('ETF데이터'!$V$4:$V$594,$O38))) | K38: =IF($O38=0,"",IF(INDEX('ETF데이터'!$W$4:$W$594,$O38)="","",INDEX('ETF데이터'!$W$4:$W$594,$O38))) | L38: =IF($O38=0,"",IF(INDEX('ETF데이터'!$X$4:$X$594,$O38)="","",INDEX('ETF데이터'!$X$4:$X$594,$O38))) | M38: =IF($O38=0,"",INDEX('ETF데이터'!$M$4:$M$594,$O38)) | O38: =IFERROR(MATCH(19,'ETF데이터'!$AB$4:$AB$594,0),0) | P38: =IF(AND($B38<>"",$N38<>""),1,0) | Q38: =IF($P38=1,$Q37+1,$Q37) | R38: =IFERROR(INDEX($B$20:$B$79,MATCH(19,$Q$20:$Q$79,0)),"")
B39: =IF($O39=0,"",INDEX('ETF데이터'!$A$4:$A$594,$O39)) | C39: =IF($O39=0,"",INDEX('ETF데이터'!$R$4:$R$594,$O39)) | D39: =IF($O39=0,"",INDEX('ETF데이터'!$J$4:$J$594,$O39)) | E39: =IF($O39=0,"",$D39/12) | F39: =IF($O39=0,"",INDEX('ETF데이터'!$D$4:$D$594,$O39)) | G39: =IF($O39=0,"",INDEX('ETF데이터'!$H$4:$H$594,$O39)) | H39: =IF($O39=0,"",INDEX('ETF데이터'!$E$4:$E$594,$O39)/100000000) | I39: =IF($O39=0,"",IF(INDEX('ETF데이터'!$U$4:$U$594,$O39)="","",INDEX('ETF데이터'!$U$4:$U$594,$O39))) | J39: =IF($O39=0,"",IF(INDEX('ETF데이터'!$V$4:$V$594,$O39)="","",INDEX('ETF데이터'!$V$4:$V$594,$O39))) | K39: =IF($O39=0,"",IF(INDEX('ETF데이터'!$W$4:$W$594,$O39)="","",INDEX('ETF데이터'!$W$4:$W$594,$O39))) | L39: =IF($O39=0,"",IF(INDEX('ETF데이터'!$X$4:$X$594,$O39)="","",INDEX('ETF데이터'!$X$4:$X$594,$O39))) | M39: =IF($O39=0,"",INDEX('ETF데이터'!$M$4:$M$594,$O39)) | O39: =IFERROR(MATCH(20,'ETF데이터'!$AB$4:$AB$594,0),0) | P39: =IF(AND($B39<>"",$N39<>""),1,0) | Q39: =IF($P39=1,$Q38+1,$Q38) | R39: =IFERROR(INDEX($B$20:$B$79,MATCH(20,$Q$20:$Q$79,0)),"")
B40: =IF($O40=0,"",INDEX('ETF데이터'!$A$4:$A$594,$O40)) | C40: =IF($O40=0,"",INDEX('ETF데이터'!$R$4:$R$594,$O40)) | D40: =IF($O40=0,"",INDEX('ETF데이터'!$J$4:$J$594,$O40)) | E40: =IF($O40=0,"",$D40/12) | F40: =IF($O40=0,"",INDEX('ETF데이터'!$D$4:$D$594,$O40)) | G40: =IF($O40=0,"",INDEX('ETF데이터'!$H$4:$H$594,$O40)) | H40: =IF($O40=0,"",INDEX('ETF데이터'!$E$4:$E$594,$O40)/100000000) | I40: =IF($O40=0,"",IF(INDEX('ETF데이터'!$U$4:$U$594,$O40)="","",INDEX('ETF데이터'!$U$4:$U$594,$O40))) | J40: =IF($O40=0,"",IF(INDEX('ETF데이터'!$V$4:$V$594,$O40)="","",INDEX('ETF데이터'!$V$4:$V$594,$O40))) | K40: =IF($O40=0,"",IF(INDEX('ETF데이터'!$W$4:$W$594,$O40)="","",INDEX('ETF데이터'!$W$4:$W$594,$O40))) | L40: =IF($O40=0,"",IF(INDEX('ETF데이터'!$X$4:$X$594,$O40)="","",INDEX('ETF데이터'!$X$4:$X$594,$O40))) | M40: =IF($O40=0,"",INDEX('ETF데이터'!$M$4:$M$594,$O40)) | O40: =IFERROR(MATCH(21,'ETF데이터'!$AB$4:$AB$594,0),0) | P40: =IF(AND($B40<>"",$N40<>""),1,0) | Q40: =IF($P40=1,$Q39+1,$Q39) | R40: =IFERROR(INDEX($B$20:$B$79,MATCH(21,$Q$20:$Q$79,0)),"")
B41: =IF($O41=0,"",INDEX('ETF데이터'!$A$4:$A$594,$O41)) | C41: =IF($O41=0,"",INDEX('ETF데이터'!$R$4:$R$594,$O41)) | D41: =IF($O41=0,"",INDEX('ETF데이터'!$J$4:$J$594,$O41)) | E41: =IF($O41=0,"",$D41/12) | F41: =IF($O41=0,"",INDEX('ETF데이터'!$D$4:$D$594,$O41)) | G41: =IF($O41=0,"",INDEX('ETF데이터'!$H$4:$H$594,$O41)) | H41: =IF($O41=0,"",INDEX('ETF데이터'!$E$4:$E$594,$O41)/100000000) | I41: =IF($O41=0,"",IF(INDEX('ETF데이터'!$U$4:$U$594,$O41)="","",INDEX('ETF데이터'!$U$4:$U$594,$O41))) | J41: =IF($O41=0,"",IF(INDEX('ETF데이터'!$V$4:$V$594,$O41)="","",INDEX('ETF데이터'!$V$4:$V$594,$O41))) | K41: =IF($O41=0,"",IF(INDEX('ETF데이터'!$W$4:$W$594,$O41)="","",INDEX('ETF데이터'!$W$4:$W$594,$O41))) | L41: =IF($O41=0,"",IF(INDEX('ETF데이터'!$X$4:$X$594,$O41)="","",INDEX('ETF데이터'!$X$4:$X$594,$O41))) | M41: =IF($O41=0,"",INDEX('ETF데이터'!$M$4:$M$594,$O41)) | O41: =IFERROR(MATCH(22,'ETF데이터'!$AB$4:$AB$594,0),0) | P41: =IF(AND($B41<>"",$N41<>""),1,0) | Q41: =IF($P41=1,$Q40+1,$Q40) | R41: =IFERROR(INDEX($B$20:$B$79,MATCH(22,$Q$20:$Q$79,0)),"")
B42: =IF($O42=0,"",INDEX('ETF데이터'!$A$4:$A$594,$O42)) | C42: =IF($O42=0,"",INDEX('ETF데이터'!$R$4:$R$594,$O42)) | D42: =IF($O42=0,"",INDEX('ETF데이터'!$J$4:$J$594,$O42)) | E42: =IF($O42=0,"",$D42/12) | F42: =IF($O42=0,"",INDEX('ETF데이터'!$D$4:$D$594,$O42)) | G42: =IF($O42=0,"",INDEX('ETF데이터'!$H$4:$H$594,$O42)) | H42: =IF($O42=0,"",INDEX('ETF데이터'!$E$4:$E$594,$O42)/100000000) | I42: =IF($O42=0,"",IF(INDEX('ETF데이터'!$U$4:$U$594,$O42)="","",INDEX('ETF데이터'!$U$4:$U$594,$O42))) | J42: =IF($O42=0,"",IF(INDEX('ETF데이터'!$V$4:$V$594,$O42)="","",INDEX('ETF데이터'!$V$4:$V$594,$O42))) | K42: =IF($O42=0,"",IF(INDEX('ETF데이터'!$W$4:$W$594,$O42)="","",INDEX('ETF데이터'!$W$4:$W$594,$O42))) | L42: =IF($O42=0,"",IF(INDEX('ETF데이터'!$X$4:$X$594,$O42)="","",INDEX('ETF데이터'!$X$4:$X$594,$O42))) | M42: =IF($O42=0,"",INDEX('ETF데이터'!$M$4:$M$594,$O42)) | O42: =IFERROR(MATCH(23,'ETF데이터'!$AB$4:$AB$594,0),0) | P42: =IF(AND($B42<>"",$N42<>""),1,0) | Q42: =IF($P42=1,$Q41+1,$Q41) | R42: =IFERROR(INDEX($B$20:$B$79,MATCH(23,$Q$20:$Q$79,0)),"")
B43: =IF($O43=0,"",INDEX('ETF데이터'!$A$4:$A$594,$O43)) | C43: =IF($O43=0,"",INDEX('ETF데이터'!$R$4:$R$594,$O43)) | D43: =IF($O43=0,"",INDEX('ETF데이터'!$J$4:$J$594,$O43)) | E43: =IF($O43=0,"",$D43/12) | F43: =IF($O43=0,"",INDEX('ETF데이터'!$D$4:$D$594,$O43)) | G43: =IF($O43=0,"",INDEX('ETF데이터'!$H$4:$H$594,$O43)) | H43: =IF($O43=0,"",INDEX('ETF데이터'!$E$4:$E$594,$O43)/100000000) | I43: =IF($O43=0,"",IF(INDEX('ETF데이터'!$U$4:$U$594,$O43)="","",INDEX('ETF데이터'!$U$4:$U$594,$O43))) | J43: =IF($O43=0,"",IF(INDEX('ETF데이터'!$V$4:$V$594,$O43)="","",INDEX('ETF데이터'!$V$4:$V$594,$O43))) | K43: =IF($O43=0,"",IF(INDEX('ETF데이터'!$W$4:$W$594,$O43)="","",INDEX('ETF데이터'!$W$4:$W$594,$O43))) | L43: =IF($O43=0,"",IF(INDEX('ETF데이터'!$X$4:$X$594,$O43)="","",INDEX('ETF데이터'!$X$4:$X$594,$O43))) | M43: =IF($O43=0,"",INDEX('ETF데이터'!$M$4:$M$594,$O43)) | O43: =IFERROR(MATCH(24,'ETF데이터'!$AB$4:$AB$594,0),0) | P43: =IF(AND($B43<>"",$N43<>""),1,0) | Q43: =IF($P43=1,$Q42+1,$Q42) | R43: =IFERROR(INDEX($B$20:$B$79,MATCH(24,$Q$20:$Q$79,0)),"")
B44: =IF($O44=0,"",INDEX('ETF데이터'!$A$4:$A$594,$O44)) | C44: =IF($O44=0,"",INDEX('ETF데이터'!$R$4:$R$594,$O44)) | D44: =IF($O44=0,"",INDEX('ETF데이터'!$J$4:$J$594,$O44)) | E44: =IF($O44=0,"",$D44/12) | F44: =IF($O44=0,"",INDEX('ETF데이터'!$D$4:$D$594,$O44)) | G44: =IF($O44=0,"",INDEX('ETF데이터'!$H$4:$H$594,$O44)) | H44: =IF($O44=0,"",INDEX('ETF데이터'!$E$4:$E$594,$O44)/100000000) | I44: =IF($O44=0,"",IF(INDEX('ETF데이터'!$U$4:$U$594,$O44)="","",INDEX('ETF데이터'!$U$4:$U$594,$O44))) | J44: =IF($O44=0,"",IF(INDEX('ETF데이터'!$V$4:$V$594,$O44)="","",INDEX('ETF데이터'!$V$4:$V$594,$O44))) | K44: =IF($O44=0,"",IF(INDEX('ETF데이터'!$W$4:$W$594,$O44)="","",INDEX('ETF데이터'!$W$4:$W$594,$O44))) | L44: =IF($O44=0,"",IF(INDEX('ETF데이터'!$X$4:$X$594,$O44)="","",INDEX('ETF데이터'!$X$4:$X$594,$O44))) | M44: =IF($O44=0,"",INDEX('ETF데이터'!$M$4:$M$594,$O44)) | O44: =IFERROR(MATCH(25,'ETF데이터'!$AB$4:$AB$594,0),0) | P44: =IF(AND($B44<>"",$N44<>""),1,0) | Q44: =IF($P44=1,$Q43+1,$Q43) | R44: =IFERROR(INDEX($B$20:$B$79,MATCH(25,$Q$20:$Q$79,0)),"")
B45: =IF($O45=0,"",INDEX('ETF데이터'!$A$4:$A$594,$O45)) | C45: =IF($O45=0,"",INDEX('ETF데이터'!$R$4:$R$594,$O45)) | D45: =IF($O45=0,"",INDEX('ETF데이터'!$J$4:$J$594,$O45)) | E45: =IF($O45=0,"",$D45/12) | F45: =IF($O45=0,"",INDEX('ETF데이터'!$D$4:$D$594,$O45)) | G45: =IF($O45=0,"",INDEX('ETF데이터'!$H$4:$H$594,$O45)) | H45: =IF($O45=0,"",INDEX('ETF데이터'!$E$4:$E$594,$O45)/100000000) | I45: =IF($O45=0,"",IF(INDEX('ETF데이터'!$U$4:$U$594,$O45)="","",INDEX('ETF데이터'!$U$4:$U$594,$O45))) | J45: =IF($O45=0,"",IF(INDEX('ETF데이터'!$V$4:$V$594,$O45)="","",INDEX('ETF데이터'!$V$4:$V$594,$O45))) | K45: =IF($O45=0,"",IF(INDEX('ETF데이터'!$W$4:$W$594,$O45)="","",INDEX('ETF데이터'!$W$4:$W$594,$O45))) | L45: =IF($O45=0,"",IF(INDEX('ETF데이터'!$X$4:$X$594,$O45)="","",INDEX('ETF데이터'!$X$4:$X$594,$O45))) | M45: =IF($O45=0,"",INDEX('ETF데이터'!$M$4:$M$594,$O45)) | O45: =IFERROR(MATCH(26,'ETF데이터'!$AB$4:$AB$594,0),0) | P45: =IF(AND($B45<>"",$N45<>""),1,0) | Q45: =IF($P45=1,$Q44+1,$Q44) | R45: =IFERROR(INDEX($B$20:$B$79,MATCH(26,$Q$20:$Q$79,0)),"")
B46: =IF($O46=0,"",INDEX('ETF데이터'!$A$4:$A$594,$O46)) | C46: =IF($O46=0,"",INDEX('ETF데이터'!$R$4:$R$594,$O46)) | D46: =IF($O46=0,"",INDEX('ETF데이터'!$J$4:$J$594,$O46)) | E46: =IF($O46=0,"",$D46/12) | F46: =IF($O46=0,"",INDEX('ETF데이터'!$D$4:$D$594,$O46)) | G46: =IF($O46=0,"",INDEX('ETF데이터'!$H$4:$H$594,$O46)) | H46: =IF($O46=0,"",INDEX('ETF데이터'!$E$4:$E$594,$O46)/100000000) | I46: =IF($O46=0,"",IF(INDEX('ETF데이터'!$U$4:$U$594,$O46)="","",INDEX('ETF데이터'!$U$4:$U$594,$O46))) | J46: =IF($O46=0,"",IF(INDEX('ETF데이터'!$V$4:$V$594,$O46)="","",INDEX('ETF데이터'!$V$4:$V$594,$O46))) | K46: =IF($O46=0,"",IF(INDEX('ETF데이터'!$W$4:$W$594,$O46)="","",INDEX('ETF데이터'!$W$4:$W$594,$O46))) | L46: =IF($O46=0,"",IF(INDEX('ETF데이터'!$X$4:$X$594,$O46)="","",INDEX('ETF데이터'!$X$4:$X$594,$O46))) | M46: =IF($O46=0,"",INDEX('ETF데이터'!$M$4:$M$594,$O46)) | O46: =IFERROR(MATCH(27,'ETF데이터'!$AB$4:$AB$594,0),0) | P46: =IF(AND($B46<>"",$N46<>""),1,0) | Q46: =IF($P46=1,$Q45+1,$Q45) | R46: =IFERROR(INDEX($B$20:$B$79,MATCH(27,$Q$20:$Q$79,0)),"")
B47: =IF($O47=0,"",INDEX('ETF데이터'!$A$4:$A$594,$O47)) | C47: =IF($O47=0,"",INDEX('ETF데이터'!$R$4:$R$594,$O47)) | D47: =IF($O47=0,"",INDEX('ETF데이터'!$J$4:$J$594,$O47)) | E47: =IF($O47=0,"",$D47/12) | F47: =IF($O47=0,"",INDEX('ETF데이터'!$D$4:$D$594,$O47)) | G47: =IF($O47=0,"",INDEX('ETF데이터'!$H$4:$H$594,$O47)) | H47: =IF($O47=0,"",INDEX('ETF데이터'!$E$4:$E$594,$O47)/100000000) | I47: =IF($O47=0,"",IF(INDEX('ETF데이터'!$U$4:$U$594,$O47)="","",INDEX('ETF데이터'!$U$4:$U$594,$O47))) | J47: =IF($O47=0,"",IF(INDEX('ETF데이터'!$V$4:$V$594,$O47)="","",INDEX('ETF데이터'!$V$4:$V$594,$O47))) | K47: =IF($O47=0,"",IF(INDEX('ETF데이터'!$W$4:$W$594,$O47)="","",INDEX('ETF데이터'!$W$4:$W$594,$O47))) | L47: =IF($O47=0,"",IF(INDEX('ETF데이터'!$X$4:$X$594,$O47)="","",INDEX('ETF데이터'!$X$4:$X$594,$O47))) | M47: =IF($O47=0,"",INDEX('ETF데이터'!$M$4:$M$594,$O47)) | O47: =IFERROR(MATCH(28,'ETF데이터'!$AB$4:$AB$594,0),0) | P47: =IF(AND($B47<>"",$N47<>""),1,0) | Q47: =IF($P47=1,$Q46+1,$Q46) | R47: =IFERROR(INDEX($B$20:$B$79,MATCH(28,$Q$20:$Q$79,0)),"")
B48: =IF($O48=0,"",INDEX('ETF데이터'!$A$4:$A$594,$O48)) | C48: =IF($O48=0,"",INDEX('ETF데이터'!$R$4:$R$594,$O48)) | D48: =IF($O48=0,"",INDEX('ETF데이터'!$J$4:$J$594,$O48)) | E48: =IF($O48=0,"",$D48/12) | F48: =IF($O48=0,"",INDEX('ETF데이터'!$D$4:$D$594,$O48)) | G48: =IF($O48=0,"",INDEX('ETF데이터'!$H$4:$H$594,$O48)) | H48: =IF($O48=0,"",INDEX('ETF데이터'!$E$4:$E$594,$O48)/100000000) | I48: =IF($O48=0,"",IF(INDEX('ETF데이터'!$U$4:$U$594,$O48)="","",INDEX('ETF데이터'!$U$4:$U$594,$O48))) | J48: =IF($O48=0,"",IF(INDEX('ETF데이터'!$V$4:$V$594,$O48)="","",INDEX('ETF데이터'!$V$4:$V$594,$O48))) | K48: =IF($O48=0,"",IF(INDEX('ETF데이터'!$W$4:$W$594,$O48)="","",INDEX('ETF데이터'!$W$4:$W$594,$O48))) | L48: =IF($O48=0,"",IF(INDEX('ETF데이터'!$X$4:$X$594,$O48)="","",INDEX('ETF데이터'!$X$4:$X$594,$O48))) | M48: =IF($O48=0,"",INDEX('ETF데이터'!$M$4:$M$594,$O48)) | O48: =IFERROR(MATCH(29,'ETF데이터'!$AB$4:$AB$594,0),0) | P48: =IF(AND($B48<>"",$N48<>""),1,0) | Q48: =IF($P48=1,$Q47+1,$Q47) | R48: =IFERROR(INDEX($B$20:$B$79,MATCH(29,$Q$20:$Q$79,0)),"")
B49: =IF($O49=0,"",INDEX('ETF데이터'!$A$4:$A$594,$O49)) | C49: =IF($O49=0,"",INDEX('ETF데이터'!$R$4:$R$594,$O49)) | D49: =IF($O49=0,"",INDEX('ETF데이터'!$J$4:$J$594,$O49)) | E49: =IF($O49=0,"",$D49/12) | F49: =IF($O49=0,"",INDEX('ETF데이터'!$D$4:$D$594,$O49)) | G49: =IF($O49=0,"",INDEX('ETF데이터'!$H$4:$H$594,$O49)) | H49: =IF($O49=0,"",INDEX('ETF데이터'!$E$4:$E$594,$O49)/100000000) | I49: =IF($O49=0,"",IF(INDEX('ETF데이터'!$U$4:$U$594,$O49)="","",INDEX('ETF데이터'!$U$4:$U$594,$O49))) | J49: =IF($O49=0,"",IF(INDEX('ETF데이터'!$V$4:$V$594,$O49)="","",INDEX('ETF데이터'!$V$4:$V$594,$O49))) | K49: =IF($O49=0,"",IF(INDEX('ETF데이터'!$W$4:$W$594,$O49)="","",INDEX('ETF데이터'!$W$4:$W$594,$O49))) | L49: =IF($O49=0,"",IF(INDEX('ETF데이터'!$X$4:$X$594,$O49)="","",INDEX('ETF데이터'!$X$4:$X$594,$O49))) | M49: =IF($O49=0,"",INDEX('ETF데이터'!$M$4:$M$594,$O49)) | O49: =IFERROR(MATCH(30,'ETF데이터'!$AB$4:$AB$594,0),0) | P49: =IF(AND($B49<>"",$N49<>""),1,0) | Q49: =IF($P49=1,$Q48+1,$Q48) | R49: =IFERROR(INDEX($B$20:$B$79,MATCH(30,$Q$20:$Q$79,0)),"")
B50: =IF($O50=0,"",INDEX('ETF데이터'!$A$4:$A$594,$O50)) | C50: =IF($O50=0,"",INDEX('ETF데이터'!$R$4:$R$594,$O50)) | D50: =IF($O50=0,"",INDEX('ETF데이터'!$J$4:$J$594,$O50)) | E50: =IF($O50=0,"",$D50/12) | F50: =IF($O50=0,"",INDEX('ETF데이터'!$D$4:$D$594,$O50)) | G50: =IF($O50=0,"",INDEX('ETF데이터'!$H$4:$H$594,$O50)) | H50: =IF($O50=0,"",INDEX('ETF데이터'!$E$4:$E$594,$O50)/100000000) | I50: =IF($O50=0,"",IF(INDEX('ETF데이터'!$U$4:$U$594,$O50)="","",INDEX('ETF데이터'!$U$4:$U$594,$O50))) | J50: =IF($O50=0,"",IF(INDEX('ETF데이터'!$V$4:$V$594,$O50)="","",INDEX('ETF데이터'!$V$4:$V$594,$O50))) | K50: =IF($O50=0,"",IF(INDEX('ETF데이터'!$W$4:$W$594,$O50)="","",INDEX('ETF데이터'!$W$4:$W$594,$O50))) | L50: =IF($O50=0,"",IF(INDEX('ETF데이터'!$X$4:$X$594,$O50)="","",INDEX('ETF데이터'!$X$4:$X$594,$O50))) | M50: =IF($O50=0,"",INDEX('ETF데이터'!$M$4:$M$594,$O50)) | O50: =IFERROR(MATCH(31,'ETF데이터'!$AB$4:$AB$594,0),0) | P50: =IF(AND($B50<>"",$N50<>""),1,0) | Q50: =IF($P50=1,$Q49+1,$Q49) | R50: =IFERROR(INDEX($B$20:$B$79,MATCH(31,$Q$20:$Q$79,0)),"")
B51: =IF($O51=0,"",INDEX('ETF데이터'!$A$4:$A$594,$O51)) | C51: =IF($O51=0,"",INDEX('ETF데이터'!$R$4:$R$594,$O51)) | D51: =IF($O51=0,"",INDEX('ETF데이터'!$J$4:$J$594,$O51)) | E51: =IF($O51=0,"",$D51/12) | F51: =IF($O51=0,"",INDEX('ETF데이터'!$D$4:$D$594,$O51)) | G51: =IF($O51=0,"",INDEX('ETF데이터'!$H$4:$H$594,$O51)) | H51: =IF($O51=0,"",INDEX('ETF데이터'!$E$4:$E$594,$O51)/100000000) | I51: =IF($O51=0,"",IF(INDEX('ETF데이터'!$U$4:$U$594,$O51)="","",INDEX('ETF데이터'!$U$4:$U$594,$O51))) | J51: =IF($O51=0,"",IF(INDEX('ETF데이터'!$V$4:$V$594,$O51)="","",INDEX('ETF데이터'!$V$4:$V$594,$O51))) | K51: =IF($O51=0,"",IF(INDEX('ETF데이터'!$W$4:$W$594,$O51)="","",INDEX('ETF데이터'!$W$4:$W$594,$O51))) | L51: =IF($O51=0,"",IF(INDEX('ETF데이터'!$X$4:$X$594,$O51)="","",INDEX('ETF데이터'!$X$4:$X$594,$O51))) | M51: =IF($O51=0,"",INDEX('ETF데이터'!$M$4:$M$594,$O51)) | O51: =IFERROR(MATCH(32,'ETF데이터'!$AB$4:$AB$594,0),0) | P51: =IF(AND($B51<>"",$N51<>""),1,0) | Q51: =IF($P51=1,$Q50+1,$Q50) | R51: =IFERROR(INDEX($B$20:$B$79,MATCH(32,$Q$20:$Q$79,0)),"")
B52: =IF($O52=0,"",INDEX('ETF데이터'!$A$4:$A$594,$O52)) | C52: =IF($O52=0,"",INDEX('ETF데이터'!$R$4:$R$594,$O52)) | D52: =IF($O52=0,"",INDEX('ETF데이터'!$J$4:$J$594,$O52)) | E52: =IF($O52=0,"",$D52/12) | F52: =IF($O52=0,"",INDEX('ETF데이터'!$D$4:$D$594,$O52)) | G52: =IF($O52=0,"",INDEX('ETF데이터'!$H$4:$H$594,$O52)) | H52: =IF($O52=0,"",INDEX('ETF데이터'!$E$4:$E$594,$O52)/100000000) | I52: =IF($O52=0,"",IF(INDEX('ETF데이터'!$U$4:$U$594,$O52)="","",INDEX('ETF데이터'!$U$4:$U$594,$O52))) | J52: =IF($O52=0,"",IF(INDEX('ETF데이터'!$V$4:$V$594,$O52)="","",INDEX('ETF데이터'!$V$4:$V$594,$O52))) | K52: =IF($O52=0,"",IF(INDEX('ETF데이터'!$W$4:$W$594,$O52)="","",INDEX('ETF데이터'!$W$4:$W$594,$O52))) | L52: =IF($O52=0,"",IF(INDEX('ETF데이터'!$X$4:$X$594,$O52)="","",INDEX('ETF데이터'!$X$4:$X$594,$O52))) | M52: =IF($O52=0,"",INDEX('ETF데이터'!$M$4:$M$594,$O52)) | O52: =IFERROR(MATCH(33,'ETF데이터'!$AB$4:$AB$594,0),0) | P52: =IF(AND($B52<>"",$N52<>""),1,0) | Q52: =IF($P52=1,$Q51+1,$Q51) | R52: =IFERROR(INDEX($B$20:$B$79,MATCH(33,$Q$20:$Q$79,0)),"")
B53: =IF($O53=0,"",INDEX('ETF데이터'!$A$4:$A$594,$O53)) | C53: =IF($O53=0,"",INDEX('ETF데이터'!$R$4:$R$594,$O53)) | D53: =IF($O53=0,"",INDEX('ETF데이터'!$J$4:$J$594,$O53)) | E53: =IF($O53=0,"",$D53/12) | F53: =IF($O53=0,"",INDEX('ETF데이터'!$D$4:$D$594,$O53)) | G53: =IF($O53=0,"",INDEX('ETF데이터'!$H$4:$H$594,$O53)) | H53: =IF($O53=0,"",INDEX('ETF데이터'!$E$4:$E$594,$O53)/100000000) | I53: =IF($O53=0,"",IF(INDEX('ETF데이터'!$U$4:$U$594,$O53)="","",INDEX('ETF데이터'!$U$4:$U$594,$O53))) | J53: =IF($O53=0,"",IF(INDEX('ETF데이터'!$V$4:$V$594,$O53)="","",INDEX('ETF데이터'!$V$4:$V$594,$O53))) | K53: =IF($O53=0,"",IF(INDEX('ETF데이터'!$W$4:$W$594,$O53)="","",INDEX('ETF데이터'!$W$4:$W$594,$O53))) | L53: =IF($O53=0,"",IF(INDEX('ETF데이터'!$X$4:$X$594,$O53)="","",INDEX('ETF데이터'!$X$4:$X$594,$O53))) | M53: =IF($O53=0,"",INDEX('ETF데이터'!$M$4:$M$594,$O53)) | O53: =IFERROR(MATCH(34,'ETF데이터'!$AB$4:$AB$594,0),0) | P53: =IF(AND($B53<>"",$N53<>""),1,0) | Q53: =IF($P53=1,$Q52+1,$Q52) | R53: =IFERROR(INDEX($B$20:$B$79,MATCH(34,$Q$20:$Q$79,0)),"")
B54: =IF($O54=0,"",INDEX('ETF데이터'!$A$4:$A$594,$O54)) | C54: =IF($O54=0,"",INDEX('ETF데이터'!$R$4:$R$594,$O54)) | D54: =IF($O54=0,"",INDEX('ETF데이터'!$J$4:$J$594,$O54)) | E54: =IF($O54=0,"",$D54/12) | F54: =IF($O54=0,"",INDEX('ETF데이터'!$D$4:$D$594,$O54)) | G54: =IF($O54=0,"",INDEX('ETF데이터'!$H$4:$H$594,$O54)) | H54: =IF($O54=0,"",INDEX('ETF데이터'!$E$4:$E$594,$O54)/100000000) | I54: =IF($O54=0,"",IF(INDEX('ETF데이터'!$U$4:$U$594,$O54)="","",INDEX('ETF데이터'!$U$4:$U$594,$O54))) | J54: =IF($O54=0,"",IF(INDEX('ETF데이터'!$V$4:$V$594,$O54)="","",INDEX('ETF데이터'!$V$4:$V$594,$O54))) | K54: =IF($O54=0,"",IF(INDEX('ETF데이터'!$W$4:$W$594,$O54)="","",INDEX('ETF데이터'!$W$4:$W$594,$O54))) | L54: =IF($O54=0,"",IF(INDEX('ETF데이터'!$X$4:$X$594,$O54)="","",INDEX('ETF데이터'!$X$4:$X$594,$O54))) | M54: =IF($O54=0,"",INDEX('ETF데이터'!$M$4:$M$594,$O54)) | O54: =IFERROR(MATCH(35,'ETF데이터'!$AB$4:$AB$594,0),0) | P54: =IF(AND($B54<>"",$N54<>""),1,0) | Q54: =IF($P54=1,$Q53+1,$Q53) | R54: =IFERROR(INDEX($B$20:$B$79,MATCH(35,$Q$20:$Q$79,0)),"")
B55: =IF($O55=0,"",INDEX('ETF데이터'!$A$4:$A$594,$O55)) | C55: =IF($O55=0,"",INDEX('ETF데이터'!$R$4:$R$594,$O55)) | D55: =IF($O55=0,"",INDEX('ETF데이터'!$J$4:$J$594,$O55)) | E55: =IF($O55=0,"",$D55/12) | F55: =IF($O55=0,"",INDEX('ETF데이터'!$D$4:$D$594,$O55)) | G55: =IF($O55=0,"",INDEX('ETF데이터'!$H$4:$H$594,$O55)) | H55: =IF($O55=0,"",INDEX('ETF데이터'!$E$4:$E$594,$O55)/100000000) | I55: =IF($O55=0,"",IF(INDEX('ETF데이터'!$U$4:$U$594,$O55)="","",INDEX('ETF데이터'!$U$4:$U$594,$O55))) | J55: =IF($O55=0,"",IF(INDEX('ETF데이터'!$V$4:$V$594,$O55)="","",INDEX('ETF데이터'!$V$4:$V$594,$O55))) | K55: =IF($O55=0,"",IF(INDEX('ETF데이터'!$W$4:$W$594,$O55)="","",INDEX('ETF데이터'!$W$4:$W$594,$O55))) | L55: =IF($O55=0,"",IF(INDEX('ETF데이터'!$X$4:$X$594,$O55)="","",INDEX('ETF데이터'!$X$4:$X$594,$O55))) | M55: =IF($O55=0,"",INDEX('ETF데이터'!$M$4:$M$594,$O55)) | O55: =IFERROR(MATCH(36,'ETF데이터'!$AB$4:$AB$594,0),0) | P55: =IF(AND($B55<>"",$N55<>""),1,0) | Q55: =IF($P55=1,$Q54+1,$Q54) | R55: =IFERROR(INDEX($B$20:$B$79,MATCH(36,$Q$20:$Q$79,0)),"")
B56: =IF($O56=0,"",INDEX('ETF데이터'!$A$4:$A$594,$O56)) | C56: =IF($O56=0,"",INDEX('ETF데이터'!$R$4:$R$594,$O56)) | D56: =IF($O56=0,"",INDEX('ETF데이터'!$J$4:$J$594,$O56)) | E56: =IF($O56=0,"",$D56/12) | F56: =IF($O56=0,"",INDEX('ETF데이터'!$D$4:$D$594,$O56)) | G56: =IF($O56=0,"",INDEX('ETF데이터'!$H$4:$H$594,$O56)) | H56: =IF($O56=0,"",INDEX('ETF데이터'!$E$4:$E$594,$O56)/100000000) | I56: =IF($O56=0,"",IF(INDEX('ETF데이터'!$U$4:$U$594,$O56)="","",INDEX('ETF데이터'!$U$4:$U$594,$O56))) | J56: =IF($O56=0,"",IF(INDEX('ETF데이터'!$V$4:$V$594,$O56)="","",INDEX('ETF데이터'!$V$4:$V$594,$O56))) | K56: =IF($O56=0,"",IF(INDEX('ETF데이터'!$W$4:$W$594,$O56)="","",INDEX('ETF데이터'!$W$4:$W$594,$O56))) | L56: =IF($O56=0,"",IF(INDEX('ETF데이터'!$X$4:$X$594,$O56)="","",INDEX('ETF데이터'!$X$4:$X$594,$O56))) | M56: =IF($O56=0,"",INDEX('ETF데이터'!$M$4:$M$594,$O56)) | O56: =IFERROR(MATCH(37,'ETF데이터'!$AB$4:$AB$594,0),0) | P56: =IF(AND($B56<>"",$N56<>""),1,0) | Q56: =IF($P56=1,$Q55+1,$Q55) | R56: =IFERROR(INDEX($B$20:$B$79,MATCH(37,$Q$20:$Q$79,0)),"")
B57: =IF($O57=0,"",INDEX('ETF데이터'!$A$4:$A$594,$O57)) | C57: =IF($O57=0,"",INDEX('ETF데이터'!$R$4:$R$594,$O57)) | D57: =IF($O57=0,"",INDEX('ETF데이터'!$J$4:$J$594,$O57)) | E57: =IF($O57=0,"",$D57/12) | F57: =IF($O57=0,"",INDEX('ETF데이터'!$D$4:$D$594,$O57)) | G57: =IF($O57=0,"",INDEX('ETF데이터'!$H$4:$H$594,$O57)) | H57: =IF($O57=0,"",INDEX('ETF데이터'!$E$4:$E$594,$O57)/100000000) | I57: =IF($O57=0,"",IF(INDEX('ETF데이터'!$U$4:$U$594,$O57)="","",INDEX('ETF데이터'!$U$4:$U$594,$O57))) | J57: =IF($O57=0,"",IF(INDEX('ETF데이터'!$V$4:$V$594,$O57)="","",INDEX('ETF데이터'!$V$4:$V$594,$O57))) | K57: =IF($O57=0,"",IF(INDEX('ETF데이터'!$W$4:$W$594,$O57)="","",INDEX('ETF데이터'!$W$4:$W$594,$O57))) | L57: =IF($O57=0,"",IF(INDEX('ETF데이터'!$X$4:$X$594,$O57)="","",INDEX('ETF데이터'!$X$4:$X$594,$O57))) | M57: =IF($O57=0,"",INDEX('ETF데이터'!$M$4:$M$594,$O57)) | O57: =IFERROR(MATCH(38,'ETF데이터'!$AB$4:$AB$594,0),0) | P57: =IF(AND($B57<>"",$N57<>""),1,0) | Q57: =IF($P57=1,$Q56+1,$Q56) | R57: =IFERROR(INDEX($B$20:$B$79,MATCH(38,$Q$20:$Q$79,0)),"")
B58: =IF($O58=0,"",INDEX('ETF데이터'!$A$4:$A$594,$O58)) | C58: =IF($O58=0,"",INDEX('ETF데이터'!$R$4:$R$594,$O58)) | D58: =IF($O58=0,"",INDEX('ETF데이터'!$J$4:$J$594,$O58)) | E58: =IF($O58=0,"",$D58/12) | F58: =IF($O58=0,"",INDEX('ETF데이터'!$D$4:$D$594,$O58)) | G58: =IF($O58=0,"",INDEX('ETF데이터'!$H$4:$H$594,$O58)) | H58: =IF($O58=0,"",INDEX('ETF데이터'!$E$4:$E$594,$O58)/100000000) | I58: =IF($O58=0,"",IF(INDEX('ETF데이터'!$U$4:$U$594,$O58)="","",INDEX('ETF데이터'!$U$4:$U$594,$O58))) | J58: =IF($O58=0,"",IF(INDEX('ETF데이터'!$V$4:$V$594,$O58)="","",INDEX('ETF데이터'!$V$4:$V$594,$O58))) | K58: =IF($O58=0,"",IF(INDEX('ETF데이터'!$W$4:$W$594,$O58)="","",INDEX('ETF데이터'!$W$4:$W$594,$O58))) | L58: =IF($O58=0,"",IF(INDEX('ETF데이터'!$X$4:$X$594,$O58)="","",INDEX('ETF데이터'!$X$4:$X$594,$O58))) | M58: =IF($O58=0,"",INDEX('ETF데이터'!$M$4:$M$594,$O58)) | O58: =IFERROR(MATCH(39,'ETF데이터'!$AB$4:$AB$594,0),0) | P58: =IF(AND($B58<>"",$N58<>""),1,0) | Q58: =IF($P58=1,$Q57+1,$Q57) | R58: =IFERROR(INDEX($B$20:$B$79,MATCH(39,$Q$20:$Q$79,0)),"")
B59: =IF($O59=0,"",INDEX('ETF데이터'!$A$4:$A$594,$O59)) | C59: =IF($O59=0,"",INDEX('ETF데이터'!$R$4:$R$594,$O59)) | D59: =IF($O59=0,"",INDEX('ETF데이터'!$J$4:$J$594,$O59)) | E59: =IF($O59=0,"",$D59/12) | F59: =IF($O59=0,"",INDEX('ETF데이터'!$D$4:$D$594,$O59)) | G59: =IF($O59=0,"",INDEX('ETF데이터'!$H$4:$H$594,$O59)) | H59: =IF($O59=0,"",INDEX('ETF데이터'!$E$4:$E$594,$O59)/100000000) | I59: =IF($O59=0,"",IF(INDEX('ETF데이터'!$U$4:$U$594,$O59)="","",INDEX('ETF데이터'!$U$4:$U$594,$O59))) | J59: =IF($O59=0,"",IF(INDEX('ETF데이터'!$V$4:$V$594,$O59)="","",INDEX('ETF데이터'!$V$4:$V$594,$O59))) | K59: =IF($O59=0,"",IF(INDEX('ETF데이터'!$W$4:$W$594,$O59)="","",INDEX('ETF데이터'!$W$4:$W$594,$O59))) | L59: =IF($O59=0,"",IF(INDEX('ETF데이터'!$X$4:$X$594,$O59)="","",INDEX('ETF데이터'!$X$4:$X$594,$O59))) | M59: =IF($O59=0,"",INDEX('ETF데이터'!$M$4:$M$594,$O59)) | O59: =IFERROR(MATCH(40,'ETF데이터'!$AB$4:$AB$594,0),0) | P59: =IF(AND($B59<>"",$N59<>""),1,0) | Q59: =IF($P59=1,$Q58+1,$Q58) | R59: =IFERROR(INDEX($B$20:$B$79,MATCH(40,$Q$20:$Q$79,0)),"")
B60: =IF($O60=0,"",INDEX('ETF데이터'!$A$4:$A$594,$O60)) | C60: =IF($O60=0,"",INDEX('ETF데이터'!$R$4:$R$594,$O60)) | D60: =IF($O60=0,"",INDEX('ETF데이터'!$J$4:$J$594,$O60)) | E60: =IF($O60=0,"",$D60/12) | F60: =IF($O60=0,"",INDEX('ETF데이터'!$D$4:$D$594,$O60)) | G60: =IF($O60=0,"",INDEX('ETF데이터'!$H$4:$H$594,$O60)) | H60: =IF($O60=0,"",INDEX('ETF데이터'!$E$4:$E$594,$O60)/100000000) | I60: =IF($O60=0,"",IF(INDEX('ETF데이터'!$U$4:$U$594,$O60)="","",INDEX('ETF데이터'!$U$4:$U$594,$O60))) | J60: =IF($O60=0,"",IF(INDEX('ETF데이터'!$V$4:$V$594,$O60)="","",INDEX('ETF데이터'!$V$4:$V$594,$O60))) | K60: =IF($O60=0,"",IF(INDEX('ETF데이터'!$W$4:$W$594,$O60)="","",INDEX('ETF데이터'!$W$4:$W$594,$O60))) | L60: =IF($O60=0,"",IF(INDEX('ETF데이터'!$X$4:$X$594,$O60)="","",INDEX('ETF데이터'!$X$4:$X$594,$O60))) | M60: =IF($O60=0,"",INDEX('ETF데이터'!$M$4:$M$594,$O60)) | O60: =IFERROR(MATCH(41,'ETF데이터'!$AB$4:$AB$594,0),0) | P60: =IF(AND($B60<>"",$N60<>""),1,0) | Q60: =IF($P60=1,$Q59+1,$Q59) | R60: =IFERROR(INDEX($B$20:$B$79,MATCH(41,$Q$20:$Q$79,0)),"")
B61: =IF($O61=0,"",INDEX('ETF데이터'!$A$4:$A$594,$O61)) | C61: =IF($O61=0,"",INDEX('ETF데이터'!$R$4:$R$594,$O61)) | D61: =IF($O61=0,"",INDEX('ETF데이터'!$J$4:$J$594,$O61)) | E61: =IF($O61=0,"",$D61/12) | F61: =IF($O61=0,"",INDEX('ETF데이터'!$D$4:$D$594,$O61)) | G61: =IF($O61=0,"",INDEX('ETF데이터'!$H$4:$H$594,$O61)) | H61: =IF($O61=0,"",INDEX('ETF데이터'!$E$4:$E$594,$O61)/100000000) | I61: =IF($O61=0,"",IF(INDEX('ETF데이터'!$U$4:$U$594,$O61)="","",INDEX('ETF데이터'!$U$4:$U$594,$O61))) | J61: =IF($O61=0,"",IF(INDEX('ETF데이터'!$V$4:$V$594,$O61)="","",INDEX('ETF데이터'!$V$4:$V$594,$O61))) | K61: =IF($O61=0,"",IF(INDEX('ETF데이터'!$W$4:$W$594,$O61)="","",INDEX('ETF데이터'!$W$4:$W$594,$O61))) | L61: =IF($O61=0,"",IF(INDEX('ETF데이터'!$X$4:$X$594,$O61)="","",INDEX('ETF데이터'!$X$4:$X$594,$O61))) | M61: =IF($O61=0,"",INDEX('ETF데이터'!$M$4:$M$594,$O61)) | O61: =IFERROR(MATCH(42,'ETF데이터'!$AB$4:$AB$594,0),0) | P61: =IF(AND($B61<>"",$N61<>""),1,0) | Q61: =IF($P61=1,$Q60+1,$Q60) | R61: =IFERROR(INDEX($B$20:$B$79,MATCH(42,$Q$20:$Q$79,0)),"")
B62: =IF($O62=0,"",INDEX('ETF데이터'!$A$4:$A$594,$O62)) | C62: =IF($O62=0,"",INDEX('ETF데이터'!$R$4:$R$594,$O62)) | D62: =IF($O62=0,"",INDEX('ETF데이터'!$J$4:$J$594,$O62)) | E62: =IF($O62=0,"",$D62/12) | F62: =IF($O62=0,"",INDEX('ETF데이터'!$D$4:$D$594,$O62)) | G62: =IF($O62=0,"",INDEX('ETF데이터'!$H$4:$H$594,$O62)) | H62: =IF($O62=0,"",INDEX('ETF데이터'!$E$4:$E$594,$O62)/100000000) | I62: =IF($O62=0,"",IF(INDEX('ETF데이터'!$U$4:$U$594,$O62)="","",INDEX('ETF데이터'!$U$4:$U$594,$O62))) | J62: =IF($O62=0,"",IF(INDEX('ETF데이터'!$V$4:$V$594,$O62)="","",INDEX('ETF데이터'!$V$4:$V$594,$O62))) | K62: =IF($O62=0,"",IF(INDEX('ETF데이터'!$W$4:$W$594,$O62)="","",INDEX('ETF데이터'!$W$4:$W$594,$O62))) | L62: =IF($O62=0,"",IF(INDEX('ETF데이터'!$X$4:$X$594,$O62)="","",INDEX('ETF데이터'!$X$4:$X$594,$O62))) | M62: =IF($O62=0,"",INDEX('ETF데이터'!$M$4:$M$594,$O62)) | O62: =IFERROR(MATCH(43,'ETF데이터'!$AB$4:$AB$594,0),0) | P62: =IF(AND($B62<>"",$N62<>""),1,0) | Q62: =IF($P62=1,$Q61+1,$Q61) | R62: =IFERROR(INDEX($B$20:$B$79,MATCH(43,$Q$20:$Q$79,0)),"")
B63: =IF($O63=0,"",INDEX('ETF데이터'!$A$4:$A$594,$O63)) | C63: =IF($O63=0,"",INDEX('ETF데이터'!$R$4:$R$594,$O63)) | D63: =IF($O63=0,"",INDEX('ETF데이터'!$J$4:$J$594,$O63)) | E63: =IF($O63=0,"",$D63/12) | F63: =IF($O63=0,"",INDEX('ETF데이터'!$D$4:$D$594,$O63)) | G63: =IF($O63=0,"",INDEX('ETF데이터'!$H$4:$H$594,$O63)) | H63: =IF($O63=0,"",INDEX('ETF데이터'!$E$4:$E$594,$O63)/100000000) | I63: =IF($O63=0,"",IF(INDEX('ETF데이터'!$U$4:$U$594,$O63)="","",INDEX('ETF데이터'!$U$4:$U$594,$O63))) | J63: =IF($O63=0,"",IF(INDEX('ETF데이터'!$V$4:$V$594,$O63)="","",INDEX('ETF데이터'!$V$4:$V$594,$O63))) | K63: =IF($O63=0,"",IF(INDEX('ETF데이터'!$W$4:$W$594,$O63)="","",INDEX('ETF데이터'!$W$4:$W$594,$O63))) | L63: =IF($O63=0,"",IF(INDEX('ETF데이터'!$X$4:$X$594,$O63)="","",INDEX('ETF데이터'!$X$4:$X$594,$O63))) | M63: =IF($O63=0,"",INDEX('ETF데이터'!$M$4:$M$594,$O63)) | O63: =IFERROR(MATCH(44,'ETF데이터'!$AB$4:$AB$594,0),0) | P63: =IF(AND($B63<>"",$N63<>""),1,0) | Q63: =IF($P63=1,$Q62+1,$Q62) | R63: =IFERROR(INDEX($B$20:$B$79,MATCH(44,$Q$20:$Q$79,0)),"")
B64: =IF($O64=0,"",INDEX('ETF데이터'!$A$4:$A$594,$O64)) | C64: =IF($O64=0,"",INDEX('ETF데이터'!$R$4:$R$594,$O64)) | D64: =IF($O64=0,"",INDEX('ETF데이터'!$J$4:$J$594,$O64)) | E64: =IF($O64=0,"",$D64/12) | F64: =IF($O64=0,"",INDEX('ETF데이터'!$D$4:$D$594,$O64)) | G64: =IF($O64=0,"",INDEX('ETF데이터'!$H$4:$H$594,$O64)) | H64: =IF($O64=0,"",INDEX('ETF데이터'!$E$4:$E$594,$O64)/100000000) | I64: =IF($O64=0,"",IF(INDEX('ETF데이터'!$U$4:$U$594,$O64)="","",INDEX('ETF데이터'!$U$4:$U$594,$O64))) | J64: =IF($O64=0,"",IF(INDEX('ETF데이터'!$V$4:$V$594,$O64)="","",INDEX('ETF데이터'!$V$4:$V$594,$O64))) | K64: =IF($O64=0,"",IF(INDEX('ETF데이터'!$W$4:$W$594,$O64)="","",INDEX('ETF데이터'!$W$4:$W$594,$O64))) | L64: =IF($O64=0,"",IF(INDEX('ETF데이터'!$X$4:$X$594,$O64)="","",INDEX('ETF데이터'!$X$4:$X$594,$O64))) | M64: =IF($O64=0,"",INDEX('ETF데이터'!$M$4:$M$594,$O64)) | O64: =IFERROR(MATCH(45,'ETF데이터'!$AB$4:$AB$594,0),0) | P64: =IF(AND($B64<>"",$N64<>""),1,0) | Q64: =IF($P64=1,$Q63+1,$Q63) | R64: =IFERROR(INDEX($B$20:$B$79,MATCH(45,$Q$20:$Q$79,0)),"")
B65: =IF($O65=0,"",INDEX('ETF데이터'!$A$4:$A$594,$O65)) | C65: =IF($O65=0,"",INDEX('ETF데이터'!$R$4:$R$594,$O65)) | D65: =IF($O65=0,"",INDEX('ETF데이터'!$J$4:$J$594,$O65)) | E65: =IF($O65=0,"",$D65/12) | F65: =IF($O65=0,"",INDEX('ETF데이터'!$D$4:$D$594,$O65)) | G65: =IF($O65=0,"",INDEX('ETF데이터'!$H$4:$H$594,$O65)) | H65: =IF($O65=0,"",INDEX('ETF데이터'!$E$4:$E$594,$O65)/100000000) | I65: =IF($O65=0,"",IF(INDEX('ETF데이터'!$U$4:$U$594,$O65)="","",INDEX('ETF데이터'!$U$4:$U$594,$O65))) | J65: =IF($O65=0,"",IF(INDEX('ETF데이터'!$V$4:$V$594,$O65)="","",INDEX('ETF데이터'!$V$4:$V$594,$O65))) | K65: =IF($O65=0,"",IF(INDEX('ETF데이터'!$W$4:$W$594,$O65)="","",INDEX('ETF데이터'!$W$4:$W$594,$O65))) | L65: =IF($O65=0,"",IF(INDEX('ETF데이터'!$X$4:$X$594,$O65)="","",INDEX('ETF데이터'!$X$4:$X$594,$O65))) | M65: =IF($O65=0,"",INDEX('ETF데이터'!$M$4:$M$594,$O65)) | O65: =IFERROR(MATCH(46,'ETF데이터'!$AB$4:$AB$594,0),0) | P65: =IF(AND($B65<>"",$N65<>""),1,0) | Q65: =IF($P65=1,$Q64+1,$Q64) | R65: =IFERROR(INDEX($B$20:$B$79,MATCH(46,$Q$20:$Q$79,0)),"")
B66: =IF($O66=0,"",INDEX('ETF데이터'!$A$4:$A$594,$O66)) | C66: =IF($O66=0,"",INDEX('ETF데이터'!$R$4:$R$594,$O66)) | D66: =IF($O66=0,"",INDEX('ETF데이터'!$J$4:$J$594,$O66)) | E66: =IF($O66=0,"",$D66/12) | F66: =IF($O66=0,"",INDEX('ETF데이터'!$D$4:$D$594,$O66)) | G66: =IF($O66=0,"",INDEX('ETF데이터'!$H$4:$H$594,$O66)) | H66: =IF($O66=0,"",INDEX('ETF데이터'!$E$4:$E$594,$O66)/100000000) | I66: =IF($O66=0,"",IF(INDEX('ETF데이터'!$U$4:$U$594,$O66)="","",INDEX('ETF데이터'!$U$4:$U$594,$O66))) | J66: =IF($O66=0,"",IF(INDEX('ETF데이터'!$V$4:$V$594,$O66)="","",INDEX('ETF데이터'!$V$4:$V$594,$O66))) | K66: =IF($O66=0,"",IF(INDEX('ETF데이터'!$W$4:$W$594,$O66)="","",INDEX('ETF데이터'!$W$4:$W$594,$O66))) | L66: =IF($O66=0,"",IF(INDEX('ETF데이터'!$X$4:$X$594,$O66)="","",INDEX('ETF데이터'!$X$4:$X$594,$O66))) | M66: =IF($O66=0,"",INDEX('ETF데이터'!$M$4:$M$594,$O66)) | O66: =IFERROR(MATCH(47,'ETF데이터'!$AB$4:$AB$594,0),0) | P66: =IF(AND($B66<>"",$N66<>""),1,0) | Q66: =IF($P66=1,$Q65+1,$Q65) | R66: =IFERROR(INDEX($B$20:$B$79,MATCH(47,$Q$20:$Q$79,0)),"")
B67: =IF($O67=0,"",INDEX('ETF데이터'!$A$4:$A$594,$O67)) | C67: =IF($O67=0,"",INDEX('ETF데이터'!$R$4:$R$594,$O67)) | D67: =IF($O67=0,"",INDEX('ETF데이터'!$J$4:$J$594,$O67)) | E67: =IF($O67=0,"",$D67/12) | F67: =IF($O67=0,"",INDEX('ETF데이터'!$D$4:$D$594,$O67)) | G67: =IF($O67=0,"",INDEX('ETF데이터'!$H$4:$H$594,$O67)) | H67: =IF($O67=0,"",INDEX('ETF데이터'!$E$4:$E$594,$O67)/100000000) | I67: =IF($O67=0,"",IF(INDEX('ETF데이터'!$U$4:$U$594,$O67)="","",INDEX('ETF데이터'!$U$4:$U$594,$O67))) | J67: =IF($O67=0,"",IF(INDEX('ETF데이터'!$V$4:$V$594,$O67)="","",INDEX('ETF데이터'!$V$4:$V$594,$O67))) | K67: =IF($O67=0,"",IF(INDEX('ETF데이터'!$W$4:$W$594,$O67)="","",INDEX('ETF데이터'!$W$4:$W$594,$O67))) | L67: =IF($O67=0,"",IF(INDEX('ETF데이터'!$X$4:$X$594,$O67)="","",INDEX('ETF데이터'!$X$4:$X$594,$O67))) | M67: =IF($O67=0,"",INDEX('ETF데이터'!$M$4:$M$594,$O67)) | O67: =IFERROR(MATCH(48,'ETF데이터'!$AB$4:$AB$594,0),0) | P67: =IF(AND($B67<>"",$N67<>""),1,0) | Q67: =IF($P67=1,$Q66+1,$Q66) | R67: =IFERROR(INDEX($B$20:$B$79,MATCH(48,$Q$20:$Q$79,0)),"")
B68: =IF($O68=0,"",INDEX('ETF데이터'!$A$4:$A$594,$O68)) | C68: =IF($O68=0,"",INDEX('ETF데이터'!$R$4:$R$594,$O68)) | D68: =IF($O68=0,"",INDEX('ETF데이터'!$J$4:$J$594,$O68)) | E68: =IF($O68=0,"",$D68/12) | F68: =IF($O68=0,"",INDEX('ETF데이터'!$D$4:$D$594,$O68)) | G68: =IF($O68=0,"",INDEX('ETF데이터'!$H$4:$H$594,$O68)) | H68: =IF($O68=0,"",INDEX('ETF데이터'!$E$4:$E$594,$O68)/100000000) | I68: =IF($O68=0,"",IF(INDEX('ETF데이터'!$U$4:$U$594,$O68)="","",INDEX('ETF데이터'!$U$4:$U$594,$O68))) | J68: =IF($O68=0,"",IF(INDEX('ETF데이터'!$V$4:$V$594,$O68)="","",INDEX('ETF데이터'!$V$4:$V$594,$O68))) | K68: =IF($O68=0,"",IF(INDEX('ETF데이터'!$W$4:$W$594,$O68)="","",INDEX('ETF데이터'!$W$4:$W$594,$O68))) | L68: =IF($O68=0,"",IF(INDEX('ETF데이터'!$X$4:$X$594,$O68)="","",INDEX('ETF데이터'!$X$4:$X$594,$O68))) | M68: =IF($O68=0,"",INDEX('ETF데이터'!$M$4:$M$594,$O68)) | O68: =IFERROR(MATCH(49,'ETF데이터'!$AB$4:$AB$594,0),0) | P68: =IF(AND($B68<>"",$N68<>""),1,0) | Q68: =IF($P68=1,$Q67+1,$Q67) | R68: =IFERROR(INDEX($B$20:$B$79,MATCH(49,$Q$20:$Q$79,0)),"")
B69: =IF($O69=0,"",INDEX('ETF데이터'!$A$4:$A$594,$O69)) | C69: =IF($O69=0,"",INDEX('ETF데이터'!$R$4:$R$594,$O69)) | D69: =IF($O69=0,"",INDEX('ETF데이터'!$J$4:$J$594,$O69)) | E69: =IF($O69=0,"",$D69/12) | F69: =IF($O69=0,"",INDEX('ETF데이터'!$D$4:$D$594,$O69)) | G69: =IF($O69=0,"",INDEX('ETF데이터'!$H$4:$H$594,$O69)) | H69: =IF($O69=0,"",INDEX('ETF데이터'!$E$4:$E$594,$O69)/100000000) | I69: =IF($O69=0,"",IF(INDEX('ETF데이터'!$U$4:$U$594,$O69)="","",INDEX('ETF데이터'!$U$4:$U$594,$O69))) | J69: =IF($O69=0,"",IF(INDEX('ETF데이터'!$V$4:$V$594,$O69)="","",INDEX('ETF데이터'!$V$4:$V$594,$O69))) | K69: =IF($O69=0,"",IF(INDEX('ETF데이터'!$W$4:$W$594,$O69)="","",INDEX('ETF데이터'!$W$4:$W$594,$O69))) | L69: =IF($O69=0,"",IF(INDEX('ETF데이터'!$X$4:$X$594,$O69)="","",INDEX('ETF데이터'!$X$4:$X$594,$O69))) | M69: =IF($O69=0,"",INDEX('ETF데이터'!$M$4:$M$594,$O69)) | O69: =IFERROR(MATCH(50,'ETF데이터'!$AB$4:$AB$594,0),0) | P69: =IF(AND($B69<>"",$N69<>""),1,0) | Q69: =IF($P69=1,$Q68+1,$Q68) | R69: =IFERROR(INDEX($B$20:$B$79,MATCH(50,$Q$20:$Q$79,0)),"")
B70: =IF($O70=0,"",INDEX('ETF데이터'!$A$4:$A$594,$O70)) | C70: =IF($O70=0,"",INDEX('ETF데이터'!$R$4:$R$594,$O70)) | D70: =IF($O70=0,"",INDEX('ETF데이터'!$J$4:$J$594,$O70)) | E70: =IF($O70=0,"",$D70/12) | F70: =IF($O70=0,"",INDEX('ETF데이터'!$D$4:$D$594,$O70)) | G70: =IF($O70=0,"",INDEX('ETF데이터'!$H$4:$H$594,$O70)) | H70: =IF($O70=0,"",INDEX('ETF데이터'!$E$4:$E$594,$O70)/100000000) | I70: =IF($O70=0,"",IF(INDEX('ETF데이터'!$U$4:$U$594,$O70)="","",INDEX('ETF데이터'!$U$4:$U$594,$O70))) | J70: =IF($O70=0,"",IF(INDEX('ETF데이터'!$V$4:$V$594,$O70)="","",INDEX('ETF데이터'!$V$4:$V$594,$O70))) | K70: =IF($O70=0,"",IF(INDEX('ETF데이터'!$W$4:$W$594,$O70)="","",INDEX('ETF데이터'!$W$4:$W$594,$O70))) | L70: =IF($O70=0,"",IF(INDEX('ETF데이터'!$X$4:$X$594,$O70)="","",INDEX('ETF데이터'!$X$4:$X$594,$O70))) | M70: =IF($O70=0,"",INDEX('ETF데이터'!$M$4:$M$594,$O70)) | O70: =IFERROR(MATCH(51,'ETF데이터'!$AB$4:$AB$594,0),0) | P70: =IF(AND($B70<>"",$N70<>""),1,0) | Q70: =IF($P70=1,$Q69+1,$Q69) | R70: =IFERROR(INDEX($B$20:$B$79,MATCH(51,$Q$20:$Q$79,0)),"")
B71: =IF($O71=0,"",INDEX('ETF데이터'!$A$4:$A$594,$O71)) | C71: =IF($O71=0,"",INDEX('ETF데이터'!$R$4:$R$594,$O71)) | D71: =IF($O71=0,"",INDEX('ETF데이터'!$J$4:$J$594,$O71)) | E71: =IF($O71=0,"",$D71/12) | F71: =IF($O71=0,"",INDEX('ETF데이터'!$D$4:$D$594,$O71)) | G71: =IF($O71=0,"",INDEX('ETF데이터'!$H$4:$H$594,$O71)) | H71: =IF($O71=0,"",INDEX('ETF데이터'!$E$4:$E$594,$O71)/100000000) | I71: =IF($O71=0,"",IF(INDEX('ETF데이터'!$U$4:$U$594,$O71)="","",INDEX('ETF데이터'!$U$4:$U$594,$O71))) | J71: =IF($O71=0,"",IF(INDEX('ETF데이터'!$V$4:$V$594,$O71)="","",INDEX('ETF데이터'!$V$4:$V$594,$O71))) | K71: =IF($O71=0,"",IF(INDEX('ETF데이터'!$W$4:$W$594,$O71)="","",INDEX('ETF데이터'!$W$4:$W$594,$O71))) | L71: =IF($O71=0,"",IF(INDEX('ETF데이터'!$X$4:$X$594,$O71)="","",INDEX('ETF데이터'!$X$4:$X$594,$O71))) | M71: =IF($O71=0,"",INDEX('ETF데이터'!$M$4:$M$594,$O71)) | O71: =IFERROR(MATCH(52,'ETF데이터'!$AB$4:$AB$594,0),0) | P71: =IF(AND($B71<>"",$N71<>""),1,0) | Q71: =IF($P71=1,$Q70+1,$Q70) | R71: =IFERROR(INDEX($B$20:$B$79,MATCH(52,$Q$20:$Q$79,0)),"")
B72: =IF($O72=0,"",INDEX('ETF데이터'!$A$4:$A$594,$O72)) | C72: =IF($O72=0,"",INDEX('ETF데이터'!$R$4:$R$594,$O72)) | D72: =IF($O72=0,"",INDEX('ETF데이터'!$J$4:$J$594,$O72)) | E72: =IF($O72=0,"",$D72/12) | F72: =IF($O72=0,"",INDEX('ETF데이터'!$D$4:$D$594,$O72)) | G72: =IF($O72=0,"",INDEX('ETF데이터'!$H$4:$H$594,$O72)) | H72: =IF($O72=0,"",INDEX('ETF데이터'!$E$4:$E$594,$O72)/100000000) | I72: =IF($O72=0,"",IF(INDEX('ETF데이터'!$U$4:$U$594,$O72)="","",INDEX('ETF데이터'!$U$4:$U$594,$O72))) | J72: =IF($O72=0,"",IF(INDEX('ETF데이터'!$V$4:$V$594,$O72)="","",INDEX('ETF데이터'!$V$4:$V$594,$O72))) | K72: =IF($O72=0,"",IF(INDEX('ETF데이터'!$W$4:$W$594,$O72)="","",INDEX('ETF데이터'!$W$4:$W$594,$O72))) | L72: =IF($O72=0,"",IF(INDEX('ETF데이터'!$X$4:$X$594,$O72)="","",INDEX('ETF데이터'!$X$4:$X$594,$O72))) | M72: =IF($O72=0,"",INDEX('ETF데이터'!$M$4:$M$594,$O72)) | O72: =IFERROR(MATCH(53,'ETF데이터'!$AB$4:$AB$594,0),0) | P72: =IF(AND($B72<>"",$N72<>""),1,0) | Q72: =IF($P72=1,$Q71+1,$Q71) | R72: =IFERROR(INDEX($B$20:$B$79,MATCH(53,$Q$20:$Q$79,0)),"")
B73: =IF($O73=0,"",INDEX('ETF데이터'!$A$4:$A$594,$O73)) | C73: =IF($O73=0,"",INDEX('ETF데이터'!$R$4:$R$594,$O73)) | D73: =IF($O73=0,"",INDEX('ETF데이터'!$J$4:$J$594,$O73)) | E73: =IF($O73=0,"",$D73/12) | F73: =IF($O73=0,"",INDEX('ETF데이터'!$D$4:$D$594,$O73)) | G73: =IF($O73=0,"",INDEX('ETF데이터'!$H$4:$H$594,$O73)) | H73: =IF($O73=0,"",INDEX('ETF데이터'!$E$4:$E$594,$O73)/100000000) | I73: =IF($O73=0,"",IF(INDEX('ETF데이터'!$U$4:$U$594,$O73)="","",INDEX('ETF데이터'!$U$4:$U$594,$O73))) | J73: =IF($O73=0,"",IF(INDEX('ETF데이터'!$V$4:$V$594,$O73)="","",INDEX('ETF데이터'!$V$4:$V$594,$O73))) | K73: =IF($O73=0,"",IF(INDEX('ETF데이터'!$W$4:$W$594,$O73)="","",INDEX('ETF데이터'!$W$4:$W$594,$O73))) | L73: =IF($O73=0,"",IF(INDEX('ETF데이터'!$X$4:$X$594,$O73)="","",INDEX('ETF데이터'!$X$4:$X$594,$O73))) | M73: =IF($O73=0,"",INDEX('ETF데이터'!$M$4:$M$594,$O73)) | O73: =IFERROR(MATCH(54,'ETF데이터'!$AB$4:$AB$594,0),0) | P73: =IF(AND($B73<>"",$N73<>""),1,0) | Q73: =IF($P73=1,$Q72+1,$Q72) | R73: =IFERROR(INDEX($B$20:$B$79,MATCH(54,$Q$20:$Q$79,0)),"")
B74: =IF($O74=0,"",INDEX('ETF데이터'!$A$4:$A$594,$O74)) | C74: =IF($O74=0,"",INDEX('ETF데이터'!$R$4:$R$594,$O74)) | D74: =IF($O74=0,"",INDEX('ETF데이터'!$J$4:$J$594,$O74)) | E74: =IF($O74=0,"",$D74/12) | F74: =IF($O74=0,"",INDEX('ETF데이터'!$D$4:$D$594,$O74)) | G74: =IF($O74=0,"",INDEX('ETF데이터'!$H$4:$H$594,$O74)) | H74: =IF($O74=0,"",INDEX('ETF데이터'!$E$4:$E$594,$O74)/100000000) | I74: =IF($O74=0,"",IF(INDEX('ETF데이터'!$U$4:$U$594,$O74)="","",INDEX('ETF데이터'!$U$4:$U$594,$O74))) | J74: =IF($O74=0,"",IF(INDEX('ETF데이터'!$V$4:$V$594,$O74)="","",INDEX('ETF데이터'!$V$4:$V$594,$O74))) | K74: =IF($O74=0,"",IF(INDEX('ETF데이터'!$W$4:$W$594,$O74)="","",INDEX('ETF데이터'!$W$4:$W$594,$O74))) | L74: =IF($O74=0,"",IF(INDEX('ETF데이터'!$X$4:$X$594,$O74)="","",INDEX('ETF데이터'!$X$4:$X$594,$O74))) | M74: =IF($O74=0,"",INDEX('ETF데이터'!$M$4:$M$594,$O74)) | O74: =IFERROR(MATCH(55,'ETF데이터'!$AB$4:$AB$594,0),0) | P74: =IF(AND($B74<>"",$N74<>""),1,0) | Q74: =IF($P74=1,$Q73+1,$Q73) | R74: =IFERROR(INDEX($B$20:$B$79,MATCH(55,$Q$20:$Q$79,0)),"")
B75: =IF($O75=0,"",INDEX('ETF데이터'!$A$4:$A$594,$O75)) | C75: =IF($O75=0,"",INDEX('ETF데이터'!$R$4:$R$594,$O75)) | D75: =IF($O75=0,"",INDEX('ETF데이터'!$J$4:$J$594,$O75)) | E75: =IF($O75=0,"",$D75/12) | F75: =IF($O75=0,"",INDEX('ETF데이터'!$D$4:$D$594,$O75)) | G75: =IF($O75=0,"",INDEX('ETF데이터'!$H$4:$H$594,$O75)) | H75: =IF($O75=0,"",INDEX('ETF데이터'!$E$4:$E$594,$O75)/100000000) | I75: =IF($O75=0,"",IF(INDEX('ETF데이터'!$U$4:$U$594,$O75)="","",INDEX('ETF데이터'!$U$4:$U$594,$O75))) | J75: =IF($O75=0,"",IF(INDEX('ETF데이터'!$V$4:$V$594,$O75)="","",INDEX('ETF데이터'!$V$4:$V$594,$O75))) | K75: =IF($O75=0,"",IF(INDEX('ETF데이터'!$W$4:$W$594,$O75)="","",INDEX('ETF데이터'!$W$4:$W$594,$O75))) | L75: =IF($O75=0,"",IF(INDEX('ETF데이터'!$X$4:$X$594,$O75)="","",INDEX('ETF데이터'!$X$4:$X$594,$O75))) | M75: =IF($O75=0,"",INDEX('ETF데이터'!$M$4:$M$594,$O75)) | O75: =IFERROR(MATCH(56,'ETF데이터'!$AB$4:$AB$594,0),0) | P75: =IF(AND($B75<>"",$N75<>""),1,0) | Q75: =IF($P75=1,$Q74+1,$Q74) | R75: =IFERROR(INDEX($B$20:$B$79,MATCH(56,$Q$20:$Q$79,0)),"")
B76: =IF($O76=0,"",INDEX('ETF데이터'!$A$4:$A$594,$O76)) | C76: =IF($O76=0,"",INDEX('ETF데이터'!$R$4:$R$594,$O76)) | D76: =IF($O76=0,"",INDEX('ETF데이터'!$J$4:$J$594,$O76)) | E76: =IF($O76=0,"",$D76/12) | F76: =IF($O76=0,"",INDEX('ETF데이터'!$D$4:$D$594,$O76)) | G76: =IF($O76=0,"",INDEX('ETF데이터'!$H$4:$H$594,$O76)) | H76: =IF($O76=0,"",INDEX('ETF데이터'!$E$4:$E$594,$O76)/100000000) | I76: =IF($O76=0,"",IF(INDEX('ETF데이터'!$U$4:$U$594,$O76)="","",INDEX('ETF데이터'!$U$4:$U$594,$O76))) | J76: =IF($O76=0,"",IF(INDEX('ETF데이터'!$V$4:$V$594,$O76)="","",INDEX('ETF데이터'!$V$4:$V$594,$O76))) | K76: =IF($O76=0,"",IF(INDEX('ETF데이터'!$W$4:$W$594,$O76)="","",INDEX('ETF데이터'!$W$4:$W$594,$O76))) | L76: =IF($O76=0,"",IF(INDEX('ETF데이터'!$X$4:$X$594,$O76)="","",INDEX('ETF데이터'!$X$4:$X$594,$O76))) | M76: =IF($O76=0,"",INDEX('ETF데이터'!$M$4:$M$594,$O76)) | O76: =IFERROR(MATCH(57,'ETF데이터'!$AB$4:$AB$594,0),0) | P76: =IF(AND($B76<>"",$N76<>""),1,0) | Q76: =IF($P76=1,$Q75+1,$Q75) | R76: =IFERROR(INDEX($B$20:$B$79,MATCH(57,$Q$20:$Q$79,0)),"")
B77: =IF($O77=0,"",INDEX('ETF데이터'!$A$4:$A$594,$O77)) | C77: =IF($O77=0,"",INDEX('ETF데이터'!$R$4:$R$594,$O77)) | D77: =IF($O77=0,"",INDEX('ETF데이터'!$J$4:$J$594,$O77)) | E77: =IF($O77=0,"",$D77/12) | F77: =IF($O77=0,"",INDEX('ETF데이터'!$D$4:$D$594,$O77)) | G77: =IF($O77=0,"",INDEX('ETF데이터'!$H$4:$H$594,$O77)) | H77: =IF($O77=0,"",INDEX('ETF데이터'!$E$4:$E$594,$O77)/100000000) | I77: =IF($O77=0,"",IF(INDEX('ETF데이터'!$U$4:$U$594,$O77)="","",INDEX('ETF데이터'!$U$4:$U$594,$O77))) | J77: =IF($O77=0,"",IF(INDEX('ETF데이터'!$V$4:$V$594,$O77)="","",INDEX('ETF데이터'!$V$4:$V$594,$O77))) | K77: =IF($O77=0,"",IF(INDEX('ETF데이터'!$W$4:$W$594,$O77)="","",INDEX('ETF데이터'!$W$4:$W$594,$O77))) | L77: =IF($O77=0,"",IF(INDEX('ETF데이터'!$X$4:$X$594,$O77)="","",INDEX('ETF데이터'!$X$4:$X$594,$O77))) | M77: =IF($O77=0,"",INDEX('ETF데이터'!$M$4:$M$594,$O77)) | O77: =IFERROR(MATCH(58,'ETF데이터'!$AB$4:$AB$594,0),0) | P77: =IF(AND($B77<>"",$N77<>""),1,0) | Q77: =IF($P77=1,$Q76+1,$Q76) | R77: =IFERROR(INDEX($B$20:$B$79,MATCH(58,$Q$20:$Q$79,0)),"")
B78: =IF($O78=0,"",INDEX('ETF데이터'!$A$4:$A$594,$O78)) | C78: =IF($O78=0,"",INDEX('ETF데이터'!$R$4:$R$594,$O78)) | D78: =IF($O78=0,"",INDEX('ETF데이터'!$J$4:$J$594,$O78)) | E78: =IF($O78=0,"",$D78/12) | F78: =IF($O78=0,"",INDEX('ETF데이터'!$D$4:$D$594,$O78)) | G78: =IF($O78=0,"",INDEX('ETF데이터'!$H$4:$H$594,$O78)) | H78: =IF($O78=0,"",INDEX('ETF데이터'!$E$4:$E$594,$O78)/100000000) | I78: =IF($O78=0,"",IF(INDEX('ETF데이터'!$U$4:$U$594,$O78)="","",INDEX('ETF데이터'!$U$4:$U$594,$O78))) | J78: =IF($O78=0,"",IF(INDEX('ETF데이터'!$V$4:$V$594,$O78)="","",INDEX('ETF데이터'!$V$4:$V$594,$O78))) | K78: =IF($O78=0,"",IF(INDEX('ETF데이터'!$W$4:$W$594,$O78)="","",INDEX('ETF데이터'!$W$4:$W$594,$O78))) | L78: =IF($O78=0,"",IF(INDEX('ETF데이터'!$X$4:$X$594,$O78)="","",INDEX('ETF데이터'!$X$4:$X$594,$O78))) | M78: =IF($O78=0,"",INDEX('ETF데이터'!$M$4:$M$594,$O78)) | O78: =IFERROR(MATCH(59,'ETF데이터'!$AB$4:$AB$594,0),0) | P78: =IF(AND($B78<>"",$N78<>""),1,0) | Q78: =IF($P78=1,$Q77+1,$Q77) | R78: =IFERROR(INDEX($B$20:$B$79,MATCH(59,$Q$20:$Q$79,0)),"")
B79: =IF($O79=0,"",INDEX('ETF데이터'!$A$4:$A$594,$O79)) | C79: =IF($O79=0,"",INDEX('ETF데이터'!$R$4:$R$594,$O79)) | D79: =IF($O79=0,"",INDEX('ETF데이터'!$J$4:$J$594,$O79)) | E79: =IF($O79=0,"",$D79/12) | F79: =IF($O79=0,"",INDEX('ETF데이터'!$D$4:$D$594,$O79)) | G79: =IF($O79=0,"",INDEX('ETF데이터'!$H$4:$H$594,$O79)) | H79: =IF($O79=0,"",INDEX('ETF데이터'!$E$4:$E$594,$O79)/100000000) | I79: =IF($O79=0,"",IF(INDEX('ETF데이터'!$U$4:$U$594,$O79)="","",INDEX('ETF데이터'!$U$4:$U$594,$O79))) | J79: =IF($O79=0,"",IF(INDEX('ETF데이터'!$V$4:$V$594,$O79)="","",INDEX('ETF데이터'!$V$4:$V$594,$O79))) | K79: =IF($O79=0,"",IF(INDEX('ETF데이터'!$W$4:$W$594,$O79)="","",INDEX('ETF데이터'!$W$4:$W$594,$O79))) | L79: =IF($O79=0,"",IF(INDEX('ETF데이터'!$X$4:$X$594,$O79)="","",INDEX('ETF데이터'!$X$4:$X$594,$O79))) | M79: =IF($O79=0,"",INDEX('ETF데이터'!$M$4:$M$594,$O79)) | O79: =IFERROR(MATCH(60,'ETF데이터'!$AB$4:$AB$594,0),0) | P79: =IF(AND($B79<>"",$N79<>""),1,0) | Q79: =IF($P79=1,$Q78+1,$Q78) | R79: =IFERROR(INDEX($B$20:$B$79,MATCH(60,$Q$20:$Q$79,0)),"")
B81: ※ 조건에 맞는 종목이 60개를 넘으면 위에서부터 60개만 나옵니다. 조건을 좁혀 보십시오.
B82: ※ 담고 싶은 종목의 '담기' 칸에 O 를 넣으십시오. [제안서] 의 포트폴리오에 위에서부터 차례로 올라갑니다. 지우면 내려갑니다. 배분 비율은 제안서에서 직접 넣으십시오.
B83: ※ '담기' 표시는 종목이 아니라 그 줄에 붙습니다. 담은 뒤에 위의 조회 조건을 바꾸면 그 줄에 다른 종목이 올라오면서 담긴 종목도 함께 바뀝니다. 조건을 먼저 정하고 담으십시오.
B84: ※ [제안서] 에서 직접 고르셔도 됩니다. 그 장의 콤보박스는 조건과 상관없이 전체 목록을 담고 있습니다 — 조건을 바꿨다고 이미 담아 둔 종목이 빠지면 안 되기 때문입니다.

Sheet ETF데이터
A1: ETFCHECK 수집 원본 — 이 장의 값은 손으로 고치지 마십시오. 매월 1일 수집기가 덮어씁니다.
A3: 종목명 | B3: 종목코드 | C3: 운용사 | D3: 현재가 | E3: 순자산총액 | F3: 60일 평균거래대금 | G3: 총보수(연) | H3: 변동성(1년) | I3: 최근 월분배율 | J3: 연환산 분배율 | K3: 분배 기록수 | L3: 최근 분배기준일 | M3: 채택 | N3: 제외 사유 | O3: 기초지수 | P3: 유형 | Q3: 자산군 | R3: 지급주기 | S3: 연 지급횟수 | T3: 과세비율 | U3: 총수익 1년 | V3: 기준가 1년 | W3: 기준가 6개월 | X3: 기준가 3개월 | Y3: 수익률 창 | Z3: 수익률 비고
A4: SOL 팔란티어커버드콜OTM채권혼합 | B4: 0040Y0 | C4: 신한자산운용 | D4: 7885 | E4: 364287000000 | F4: 2676209983 | G4: 0.0035 | H4: 0.164 | I4: 0.0196 | J4: 0.277108 | K4: 17 | L4: 20260929 | M4: 채택 | O4: KEDI Palantir Covered Call OTM Treasury Balanced Index NTR | P4: 커버드콜 | Q4: 멀티에셋 | R4: 월배당 | S4: 11 | T4: 0.1904 | U4: -0.0197 | V4: -0.232 | W4: -0.1211 | X4: -0.0325 | Y4: 20250922~20261002 | AA4: =IF(AND($J4<>"",OR(조회_주기="전체",$R4=조회_주기),$J4>=조회_최소,$J4<=조회_최대),1,0) | AB4: =IF($AA4=1,0+1,0) | AC4: =IF(검색어="",1,IF(ISNUMBER(SEARCH(검색어,$A4)),1,0)) | AD4: =IF($AC4=1,0+1,0) | AE4: =IFERROR(INDEX($A$4:$A$594,MATCH(1,$AD$4:$AD$594,0)),"")
A5: SOL 팔란티어미국채커버드콜혼합 | B5: 0040X0 | C5: 신한자산운용 | D5: 9030 | E5: 169764000000 | F5: 1483144816 | G5: 0.0035 | H5: 0.2284 | I5: 0.015 | J5: 0.253156 | K5: 17 | L5: 20260929 | M5: 채택 | O5: KEDI Palantir U.S. Treasury Covered Call Balanced Index NTR | P5: 커버드콜 | Q5: 멀티에셋 | R5: 월배당 | S5: 11 | T5: 0.7183 | U5: -0.0343 | V5: -0.229 | W5: -0.1356 | X5: -0.0794 | Y5: 20250922~20261002 | AA5: =IF(AND($J5<>"",OR(조회_주기="전체",$R5=조회_주기),$J5>=조회_최소,$J5<=조회_최대),1,0) | AB5: =IF($AA5=1,$AB4+1,$AB4) | AC5: =IF(검색어="",1,IF(ISNUMBER(SEARCH(검색어,$A5)),1,0)) | AD5: =IF($AC5=1,$AD4+1,$AD4) | AE5: =IFERROR(INDEX($A$4:$A$594,MATCH(2,$AD$4:$AD$594,0)),"")
A6: PLUS 고배당주위클리커버드콜 | B6: 489030 | C6: 한화자산운용 | D6: 6175 | E6: 305662500000 | F6: 4260074463 | G6: 0.003 | H6: 0.3086 | I6: 0.0147 | J6: 0.237085 | K6: 26 | L6: 20260929 | M6: 채택 | O6: 코스피 고배당 위클리 콜매도 ATM 지수 | P6: 커버드콜 | Q6: 주식 | R6: 월배당 | S6: 11 | T6: 0.2179 | U6: -0.23 | V6: -0.3775 | W6: -0.2742 | X6: -0.023 | Y6: 20250922~20261002 | AA6: =IF(AND($J6<>"",OR(조회_주기="전체",$R6=조회_주기),$J6>=조회_최소,$J6<=조회_최대),1,0) | AB6: =IF($AA6=1,$AB5+1,$AB5) | AC6: =IF(검색어="",1,IF(ISNUMBER(SEARCH(검색어,$A6)),1,0)) | AD6: =IF($AC6=1,$AD5+1,$AD5) | AE6: =IFERROR(INDEX($A$4:$A$594,MATCH(3,$AD$4:$AD$594,0)),"")
A7: KODEX 미국나스닥100데일리커버드콜OTM | B7: 494300 | C7: 삼성자산운용(ETF) | D7: 8855 | E7: 1055516000000 | F7: 12188428828 | G7: 0.0025 | H7: 0.196 | I7: 0.0166 | J7: 0.226426 | K7: 23 | L7: 20260929 | M7: 채택 | O7: Nasdaq-100 Daily Covered Call 101 Index TR | P7: 커버드콜 | Q7: 주식 | R7: 월배당 | S7: 11 | T7: 0.784 | U7: 0.0872 | V7: -0.1141 | W7: -0.0781 | X7: -0.1575 | Y7: 20250922~20261002 | AA7: =IF(AND($J7<>"",OR(조회_주기="전체",$R7=조회_주기),$J7>=조회_최소,$J7<=조회_최대),1,0) | AB7: =IF($AA7=1,$AB6+1,$AB6) | AC7: =IF(검색어="",1,IF(ISNUMBER(SEARCH(검색어,$A7)),1,0)) | AD7: =IF($AC7=1,$AD6+1,$AD6) | AE7: =IFERROR(INDEX($A$4:$A$594,MATCH(4,$AD$4:$AD$594,0)),"")
A8: RISE 미국테크100데일리고정커버드콜 | B8: 491620 | C8: KB자산운용 | D8: 10415 | E8: 595217250000 | F8: 6738144363 | G8: 0.0025 | H8: 0.2035 | I8: 0.0126 | J8: 0.214402 | K8: 24 | L8: 20260929 | M8: 채택 | O8: KEDI U.S. Tech100 90% Participation + Daily Options Premium | P8: 커버드콜 | Q8: 주식 | R8: 월배당 | S8: 11 | T8: 1 | U8: 0.1623 | V8: -0.0436 | W8: 0.0187 | X8: -0.1107 | Y8: 20250922~20261002 | AA8: =IF(AND($J8<>"",OR(조회_주기="전체",$R8=조회_주기),$J8>=조회_최소,$J8<=조회_최대),1,0) | AB8: =IF($AA8=1,$AB7+1,$AB7) | AC8: =IF(검색어="",1,IF(ISNUMBER(SEARCH(검색어,$A8)),1,0)) | AD8: =IF($AC8=1,$AD7+1,$AD7) | AE8: =IFERROR(INDEX($A$4:$A$594,MATCH(5,$AD$4:$AD$594,0)),"")
A9: ACE 미국500데일리타겟커버드콜(합성) | B9: 480030 | C9: 한국투신운용(ETF) | D9: 9545 | E9: 160356000000 | F9: 1319106274 | G9: 0.0045 | H9: 0.151 | I9: 0.0199 | J9: 0.203562 | K9: 29 | L9: 20260914 | M9: 채택 | O9: Bloomberg US 500 Large Cap Premium(SPY) Decrement 15% Distri | P9: 커버드콜 | Q9: 주식 | R9: 월배당 | S9: 11 | T9: 0.9012 | U9: 0.0943 | V9: -0.0919 | W9: -0.101 | X9: -0.1637 | Y9: 20250922~20261002 | AA9: =IF(AND($J9<>"",OR(조회_주기="전체",$R9=조회_주기),$J9>=조회_최소,$J9<=조회_최대),1,0) | AB9: =IF($AA9=1,$AB8+1,$AB8) | AC9: =IF(검색어="",1,IF(ISNUMBER(SEARCH(검색어,$A9)),1,0)) | AD9: =IF($AC9=1,$AD8+1,$AD8) | AE9: =IFERROR(INDEX($A$4:$A$594,MATCH(6,$AD$4:$AD$594,0)),"")
A10: RISE 미국AI밸류체인데일리고정커버드콜 | B10: 490590 | C10: KB자산운용 | D10: 14405 | E10: 834049500000 | F10: 8968858264 | G10: 0.0025 | H10: 0.3256 | I10: 0.013 | J10: 0.201666 | K10: 24 | L10: 20260929 | M10: 채택 | O10: KEDI U.S. AI Value Chain 90% Participation + Daily Options P | P10: 커버드콜 | Q10: 주식 | R10: 월배당 | S10: 11 | T10: 1 | U10: 0.3198 | V10: 0.0974 | W10: 0.138 | X10: -0.0823 | Y10: 20250922~20261002 | AA10: =IF(AND($J10<>"",OR(조회_주기="전체",$R10=조회_주기),$J10>=조회_최소,$J10<=조회_최대),1,0) | AB10: =IF($AA10=1,$AB9+1,$AB9) | AC10: =IF(검색어="",1,IF(ISNUMBER(SEARCH(검색어,$A10)),1,0)) | AD10: =IF($AC10=1,$AD9+1,$AD9) | AE10: =IFERROR(INDEX($A$4:$A$594,MATCH(7,$AD$4:$AD$594,0)),"")
A11: PLUS 고배당주위클리고정커버드콜 | B11: 0018C0 | C11: 한화자산운용 | D11: 10360 | E11: 79254000000 | F11: 960251867 | G11: 0.003 | H11: 0.2676 | I11: 0.0124 | J11: 0.17249 | K11: 19 | L11: 20260914 | M11: 채택 | O11: 코스피 고배당 위클리 고정 커버드콜 지수 | P11: 커버드콜 | Q11: 주식 | R11: 월배당 | S11: 11 | T11: 0.2602 | U11: 0.0253 | V11: -0.1254 | W11: -0.1807 | X11: -0.0347 | Y11: 20250922~20261002 | AA11: =IF(AND($J11<>"",OR(조회_주기="전체",$R11=조회_주기),$J11>=조회_최소,$J11<=조회_최대),1,0) | AB11: =IF($AA11=1,$AB10+1,$AB10) | AC11: =IF(검색어="",1,IF(ISNUMBER(SEARCH(검색어,$A11)),1,0)) | AD11: =IF($AC11=1,$AD10+1,$AD10) | AE11: =IFERROR(INDEX($A$4:$A$594,MATCH(8,$AD$4:$AD$594,0)),"")
A12: KODEX 금융고배당TOP10타겟위클리커버드콜 | B12: 498410 | C12: 삼성자산운용(ETF) | D12: 11350 | E12: 850115000000 | F12: 20811303029 | G12: 0.0039 | H12: 0.3261 | I12: 0.0123 | J12: 0.164758 | K12: 21 | L12: 20260929 | M12: 채택 | O12: 코스피 200 금융 고배당 TOP 10 타겟 15% 분배 위클리 커버드콜 | P12: 커버드콜 | Q12: 주식 | R12: 월배당 | S12: 11 | T12: 0.2 | U12: 0.028 | V12: -0.1179 | W12: -0.0987 | X12: -0.0479 | Y12: 20250922~20261002 | AA12: =IF(AND($J12<>"",OR(조회_주기="전체",$R12=조회_주기),$J12>=조회_최소,$J12<=조회_최대),1,0) | AB12: =IF($AA12=1,$AB11+1,$AB11) | AC12: =IF(검색어="",1,IF(ISNUMBER(SEARCH(검색어,$A12)),1,0)) | AD12: =IF($AC12=1,$AD11+1,$AD11) | AE12: =IFERROR(INDEX($A$4:$A$594,MATCH(9,$AD$4:$AD$594,0)),"")
A13: KODEX 테슬라커버드콜채권혼합액티브 | B13: 475080 | C13: 삼성자산운용(ETF) | D13: 7770 | E13: 282439500000 | F13: 1211042513 | G13: 0.0039 | H13: 0.1246 | I13: 0.0124 | J13: 0.163707 | K13: 32 | L13: 20260929 | M13: 채택 | O13: KEDI Tesla Income Premium Balanced Index | P13: 커버드콜 | Q13: 멀티에셋 | R13: 월배당 | S13: 11 | T13: 0.4937 | U13: -0.014 | V13: -0.1534 | W13: -0.0816 | X13: -0.0831 | Y13: 20250922~20261002 | AA13: =IF(AND($J13<>"",OR(조회_주기="전체",$R13=조회_주기),$J13>=조회_최소,$J13<=조회_최대),1,0) | AB13: =IF($AA13=1,$AB12+1,$AB12) | AC13: =IF(검색어="",1,IF(ISNUMBER(SEARCH(검색어,$A13)),1,0)) | AD13: =IF($AC13=1,$AD12+1,$AD12) | AE13: =IFERROR(INDEX($A$4:$A$594,MATCH(10,$AD$4:$AD$594,0)),"")
A14: KODEX 미국S&P500데일리커버드콜OTM | B14: 0005A0 | C14: 삼성자산운용(ETF) | D14: 9050 | E14: 201815000000 | F14: 1966336033 | G14: 0.0025 | H14: 0.1485 | I14: 0.0128 | J14: 0.163646 | K14: 21 | L14: 20260929 | M14: 채택 | O14: S&P500 Covered Call 1% OTM Daily Index(TR) | P14: 커버드콜 | Q14: 주식 | R14: 월배당 | S14: 11 | T14: 0.921 | U14: 0.0987 | V14: -0.0562 | W14: -0.053 | X14: -0.1345 | Y14: 20250922~20261002 | AA14: =IF(AND($J14<>"",OR(조회_주기="전체",$R14=조회_주기),$J14>=조회_최소,$J14<=조회_최대),1,0) | AB14: =IF($AA14=1,$AB13+1,$AB13) | AC14: =IF(검색어="",1,IF(ISNUMBER(SEARCH(검색어,$A14)),1,0)) | AD14: =IF($AC14=1,$AD13+1,$AD13) | AE14: =IFERROR(INDEX($A$4:$A$594,MATCH(11,$AD$4:$AD$594,0)),"")
A15: TIGER 미국AI빅테크10타겟데일리커버드콜 | B15: 493810 | C15: 미래에셋자산운용 | D15: 11310 | E15: 238641000000 | F15: 1685432658 | G15: 0.0025 | H15: 0.2192 | I15: 0.0124 | J15: 0.160566 | K15: 23 | L15: 20260914 | M15: 채택 | O15: KEDI US AI Big Tech 10+15% Daily Premium Index TR | P15: 커버드콜 | Q15: 주식 | R15: 월배당 | S15: 11 | T15: 1 | U15: 0.1381 | V15: -0.0199 | W15: 0.0159 | X15: -0.0813 | Y15: 20250922~20261002 | AA15: =IF(AND($J15<>"",OR(조회_주기="전체",$R15=조회_주기),$J15>=조회_최소,$J15<=조회_최대),1,0) | AB15: =IF($AA15=1,$AB14+1,$AB14) | AC15: =IF(검색어="",1,IF(ISNUMBER(SEARCH(검색어,$A15)),1,0)) | AD15: =IF($AC15=1,$AD14+1,$AD14) | AE15: =IFERROR(INDEX($A$4:$A$594,MATCH(12,$AD$4:$AD$594,0)),"")
A16: KODEX 미국AI테크TOP10타겟커버드콜 | B16: 483280 | C16: 삼성자산운용(ETF) | D16: 11715 | E16: 461571000000 | F16: 2565746916 | G16: 0.0039 | H16: 0.2464 | I16: 0.0126 | J16: 0.156808 | K16: 28 | L16: 20260929 | M16: 채택 | O16: KEDI US AI Tech Top 10+15% Premium Index | P16: 커버드콜 | Q16: 주식 | R16: 월배당 | S16: 11 | T16: 1 | U16: 0.0959 | V16: -0.0533 | W16: 0.008 | X16: -0.0714 | Y16: 20250922~20261002 | AA16: =IF(AND($J16<>"",OR(조회_주기="전체",$R16=조회_주기),$J16>=조회_최소,$J16<=조회_최대),1,0) | AB16: =IF($AA16=1,$AB15+1,$AB15) | AC16: =IF(검색어="",1,IF(ISNUMBER(SEARCH(검색어,$A16)),1,0)) | AD16: =IF($AC16=1,$AD15+1,$AD15) | AE16: =IFERROR(INDEX($A$4:$A$594,MATCH(13,$AD$4:$AD$594,0)),"")
A17: TIGER 미국나스닥100타겟데일리커버드콜 | B17: 486290 | C17: 미래에셋자산운용 | D17: 10505 | E17: 2627300500000 | F17: 25774494369 | G17: 0.0025 | H17: 0.2085 | I17: 0.0126 | J17: 0.156307 | K17: 27 | L17: 20260929 | M17: 채택 | O17: NASDAQ 100 Daily Covered Call Target Premium 15% Index | P17: 커버드콜 | Q17: 주식 | R17: 월배당 | S17: 11 | T17: 1 | U17: 0.1656 | V17: 0.0074 | W17: 0.0393 | X17: -0.1155 | Y17: 20250922~20261002 | AA17: =IF(AND($J17<>"",OR(조회_주기="전체",$R17=조회_주기),$J17>=조회_최소,$J17<=조회_최대),1,0) | AB17: =IF($AA17=1,$AB16+1,$AB16) | AC17: =IF(검색어="",1,IF(ISNUMBER(SEARCH(검색어,$A17)),1,0)) | AD17: =IF($AC17=1,$AD16+1,$AD16) | AE17: =IFERROR(INDEX($A$4:$A$594,MATCH(14,$AD$4:$AD$594,0)),"")
A18: TIGER 미국30년국채커버드콜액티브(H) | B18: 476550 | C18: 미래에셋자산운용 | D18: 6380 | E18: 740399000000 | F18: 7686742222 | G18: 0.0039 | H18: 0.0969 | I18: 0.0101 | J18: 0.139812 | K18: 31 | L18: 20260929 | M18: 채택 | O18: KEDI US Treasury 30Y Weekly Covered Call 30 Index | P18: 커버드콜 | Q18: 채권 | R18: 월배당 | S18: 11 | T18: 0 | U18: -0.0911 | V18: -0.2025 | W18: -0.1368 | X18: -0.1077 | Y18: 20250922~20261002 | AA18: =IF(AND($J18<>"",OR(조회_주기="전체",$R18=조회_주기),$J18>=조회_최소,$J18<=조회_최대),1,0) | AB18: =IF($AA18=1,$AB17+1,$AB17) | AC18: =IF(검색어="",1,IF(ISNUMBER(SEARCH(검색어,$A18)),1,0)) | AD18: =IF($AC18=1,$AD17+1,$AD17) | AE18: =IFERROR(INDEX($A$4:$A$594,MATCH(15,$AD$4:$AD$594,0)),"")
A19: SOL 미국30년국채커버드콜(합성) | B19: 473330 | C19: 신한자산운용 | D19: 7400 | E19: 267140000000 | F19: 2121333200 | G19: 0.0025 | H19: 0.1393 | I19: 0.0079 | J19: 0.134054 | K19: 33 | L19: 20260929 | M19: 채택 | O19: KEDI US Treasury 20Y+ 2% OTM BuyWrite Index | P19: 커버드콜 | Q19: 채권 | R19: 월배당 | S19: 11 | T19: 0.749 | U19: -0.0771 | V19: -0.186 | W19: -0.2106 | X19: -0.1981 | Y19: 20250922~20261002 | AA19: =IF(AND($J19<>"",OR(조회_주기="전체",$R19=조회_주기),$J19>=조회_최소,$J19<=조회_최대),1,0) | AB19: =IF($AA19=1,$AB18+1,$AB18) | AC19: =IF(검색어="",1,IF(ISNUMBER(SEARCH(검색어,$A19)),1,0)) | AD19: =IF($AC19=1,$AD18+1,$AD18) | AE19: =IFERROR(INDEX($A$4:$A$594,MATCH(16,$AD$4:$AD$594,0)),"")
A20: KODEX 미국배당다우존스타겟커버드콜 | B20: 483290 | C20: 삼성자산운용(ETF) | D20: 9595 | E20: 170791000000 | F20: 2270734018 | G20: 0.0039 | H20: 0.1582 | I20: 0.01 | J20: 0.130797 | K20: 28 | L20: 20260929 | M20: 채택 | O20: Dow Jones US Dividend 100 10% Premium Covered Call Index(PR) | P20: 커버드콜 | Q20: 주식 | R20: 월배당 | S20: 11 | T20: 0.9267 | U20: 0.2011 | V20: 0.062 | W20: -0.111 | X20: -0.1302 | Y20: 20250922~20261002 | AA20: =IF(AND($J20<>"",OR(조회_주기="전체",$R20=조회_주기),$J20>=조회_최소,$J20<=조회_최대),1,0) | AB20: =IF($AA20=1,$AB19+1,$AB19) | AC20: =IF(검색어="",1,IF(ISNUMBER(SEARCH(검색어,$A20)),1,0)) | AD20: =IF($AC20=1,$AD19+1,$AD19) | AE20: =IFERROR(INDEX($A$4:$A$594,MATCH(17,$AD$4:$AD$594,0)),"")
A21: TIGER 미국나스닥100커버드콜(합성) | B21: 441680 | C21: 미래에셋자산운용 | D21: 10705 | E21: 282076750000 | F21: 839368252 | G21: 0.0037 | H21: 0.1476 | I21: 0.01 | J21: 0.125642 | K21: 48 | L21: 20260929 | M21: 채택 | O21: Cboe NASDAQ-100 BuyWrite V2 Index | P21: 커버드콜 | Q21: 주식 | R21: 월배당 | S21: 11 | T21: 1 | U21: 0.1704 | V21: 0.0396 | W21: -0.0454 | X21: -0.0988 | Y21: 20250922~20261002 | AA21: =IF(AND($J21<>"",OR(조회_주기="전체",$R21=조회_주기),$J21>=조회_최소,$J21<=조회_최대),1,0) | AB21: =IF($AA21=1,$AB20+1,$AB20) | AC21: =IF(검색어="",1,IF(ISNUMBER(SEARCH(검색어,$A21)),1,0)) | AD21: =IF($AC21=1,$AD20+1,$AD20) | AE21: =IFERROR(INDEX($A$4:$A$594,MATCH(18,$AD$4:$AD$594,0)),"")
A22: TIGER 미국S&P500타겟데일리커버드콜 | B22: 482730 | C22: 미래에셋자산운용 | D22: 11440 | E22: 669812000000 | F22: 4581835132 | G22: 0.0025 | H22: 0.1488 | I22: 0.01 | J22: 0.10708 | K22: 28 | L22: 20260914 | M22: 채택 | O22: S&P 500 10% Daily Premium Covered Call Index (USD) PR | P22: 커버드콜 | Q22: 주식 | R22: 월배당 | S22: 11 | T22: 1 | U22: 0.1104 | V22: 0.0027 | W22: -0.0084 | X22: -0.1156 | Y22: 20250922~20261002 | AA22: =IF(AND($J22<>"",OR(조회_주기="전체",$R22=조회_주기),$J22>=조회_최소,$J22<=조회_최대),1,0) | AB22: =IF($AA22=1,$AB21+1,$AB21) | AC22: =IF(검색어="",1,IF(ISNUMBER(SEARCH(검색어,$A22)),1,0)) | AD22: =IF($AC22=1,$AD21+1,$AD21) | AE22: =IFERROR(INDEX($A$4:$A$594,MATCH(19,$AD$4:$AD$594,0)),"")
A23: TIGER 미국배당다우존스타겟커버드콜2호 | B23: 458760 | C23: 미래에셋자산운용 | D23: 10260 | E23: 660231000000 | F23: 3061823728 | G23: 0.0039 | H23: 0.1513 | I23: 0.0086 | J23: 0.10653 | K23: 39 | L23: 20260929 | M23: 채택 | O23: Dow Jones U.S. Dividend 100 7% Premium Covered Call Index | P23: 커버드콜 | Q23: 주식 | R23: 월배당 | S23: 11 | T23: 1 | U23: 0.1975 | V23: 0.0818 | W23: -0.0926 | X23: -0.123 | Y23: 20250922~20261002 | AA23: =IF(AND($J23<>"",OR(조회_주기="전체",$R23=조회_주기),$J23>=조회_최소,$J23<=조회_최대),1,0) | AB23: =IF($AA23=1,$AB22+1,$AB22) | AC23: =IF(검색어="",1,IF(ISNUMBER(SEARCH(검색어,$A23)),1,0)) | AD23: =IF($AC23=1,$AD22+1,$AD22) | AE23: =IFERROR(INDEX($A$4:$A$594,MATCH(20,$AD$4:$AD$594,0)),"")
A24: TIGER 미국테크TOP10타겟커버드콜 | B24: 474220 | C24: 미래에셋자산운용 | D24: 14925 | E24: 420138750000 | F24: 1604795245 | G24: 0.005 | H24: 0.1955 | I24: 0.0083 | J24: 0.105059 | K24: 32 | L24: 20260914 | M24: 채택 | O24: Bloomberg U.S. Tech Top10 + 10% Premium Covered Call Index | P24: 커버드콜 | Q24: 주식 | R24: 월배당 | S24: 11 | T24: 1 | U24: 0.096 | V24: -0.0086 | W24: 0.0018 | X24: -0.0614 | Y24: 20250922~20261002 | AA24: =IF(AND($J24<>"",OR(조회_주기="전체",$R24=조회_주기),$J24>=조회_최소,$J24<=조회_최대),1,0) | AB24: =IF($AA24=1,$AB23+1,$AB23) | AC24: =IF(검색어="",1,IF(ISNUMBER(SEARCH(검색어,$A24)),1,0)) | AD24: =IF($AC24=1,$AD23+1,$AD23) | AE24: =IFERROR(INDEX($A$4:$A$594,MATCH(21,$AD$4:$AD$594,0)),"")
A25: TIGER 리츠부동산인프라 | B25: 329200 | C25: 미래에셋자산운용 | D25: 4045 | E25: 1577145500000 | F25: 11833485434 | G25: 0.0008 | H25: 0.1777 | I25: 0.0081 | J25: 0.097899 | K25: 52 | L25: 20260929 | M25: 채택 | O25: FnGuide 리츠부동산인프라 | P25: 일반 | Q25: 부동산 | R25: 월배당 | S25: 11 | T25: 1 | U25: 0.0207 | V25: -0.07 | W25: -0.1225 | X25: 0.0128 | Y25: 20250922~20261002 | AA25: =IF(AND($J25<>"",OR(조회_주기="전체",$R25=조회_주기),$J25>=조회_최소,$J25<=조회_최대),1,0) | AB25: =IF($AA25=1,$AB24+1,$AB24) | AC25: =IF(검색어="",1,IF(ISNUMBER(SEARCH(검색어,$A25)),1,0)) | AD25: =IF($AC25=1,$AD24+1,$AD24) | AE25: =IFERROR(INDEX($A$4:$A$594,MATCH(22,$AD$4:$AD$594,0)),"")
A26: KODEX 한국부동산리츠인프라 | B26: 476800 | C26: 삼성자산운용(ETF) | D26: 4205 | E26: 488200500000 | F26: 2363556859 | G26: 0.0009 | H26: 0.1488 | I26: 0.0141 | J26: 0.092033 | K26: 30 | L26: 20260914 | M26: 채택 | O26: KRX 부동산리츠인프라 지수 | P26: 일반 | Q26: 부동산 | R26: 월배당 | S26: 11 | T26: 0.9121 | U26: -0.0319 | V26: -0.1134 | W26: -0.1399 | X26: -0.0159 | Y26: 20250922~20261002 | AA26: =IF(AND($J26<>"",OR(조회_주기="전체",$R26=조회_주기),$J26>=조회_최소,$J26<=조회_최대),1,0) | AB26: =IF($AA26=1,$AB25+1,$AB25) | AC26: =IF(검색어="",1,IF(ISNUMBER(SEARCH(검색어,$A26)),1,0)) | AD26: =IF($AC26=1,$AD25+1,$AD25) | AE26: =IFERROR(INDEX($A$4:$A$594,MATCH(23,$AD$4:$AD$594,0)),"")
A27: ACE 글로벌인컴TOP10 | B27: 460960 | C27: 한국투신운용(ETF) | D27: 10395 | E27: 82120500000 | F27: 955805793 | G27: 0.0024 | H27: 0.1134 | I27: 0.0061 | J27: 0.082347 | K27: 38 | L27: 20260929 | M27: 채택 | O27: Solactive Global Superior Income TOP 10 Index PR | P27: 일반 | Q27: 멀티에셋 | R27: 월배당 | S27: 11 | T27: 1 | U27: 0.0012 | V27: -0.0751 | W27: -0.1197 | X27: -0.151 | Y27: 20250922~20261002 | AA27: =IF(AND($J27<>"",OR(조회_주기="전체",$R27=조회_주기),$J27>=조회_최소,$J27<=조회_최대),1,0) | AB27: =IF($AA27=1,$AB26+1,$AB26) | AC27: =IF(검색어="",1,IF(ISNUMBER(SEARCH(검색어,$A27)),1,0)) | AD27: =IF($AC27=1,$AD26+1,$AD26) | AE27: =IFERROR(INDEX($A$4:$A$594,MATCH(24,$AD$4:$AD$594,0)),"")
A28: KODEX iShares미국하이일드액티브 | B28: 468380 | C28: 삼성자산운용(ETF) | D28: 10365 | E28: 87480600000 | F28: 722203366 | G28: 0.0015 | H28: 0.1038 | I28: 0.0057 | J28: 0.074674 | K28: 35 | L28: 20260929 | M28: 채택 | O28: ICE BofAML US HY Constrained Index | P28: 일반 | Q28: 채권 | R28: 월배당 | S28: 11 | T28: 1 | U28: -0.0231 | V28: -0.0911 | W28: -0.1346 | X28: -0.1477 | Y28: 20250922~20261002 | AA28: =IF(AND($J28<>"",OR(조회_주기="전체",$R28=조회_주기),$J28>=조회_최소,$J28<=조회_최대),1,0) | AB28: =IF($AA28=1,$AB27+1,$AB27) | AC28: =IF(검색어="",1,IF(ISNUMBER(SEARCH(검색어,$A28)),1,0)) | AD28: =IF($AC28=1,$AD27+1,$AD27) | AE28: =IFERROR(INDEX($A$4:$A$594,MATCH(25,$AD$4:$AD$594,0)),"")
A29: SOL 코리아고배당 | B29: 0105E0 | C29: 신한자산운용 | D29: 12615 | E29: 524784000000 | F29: 5874730200 | G29: 0.0015 | H29: 0.3016 | I29: 0.0046 | J29: 0.055172 | K29: 11 | L29: 20260914 | M29: 채택 | O29: FnGuide 코리아 고배당 지수 | P29: 일반 | Q29: 주식 | R29: 월배당 | S29: 11 | T29: 0.6078 | U29: 0.3233 | V29: 0.2542 | W29: -0.0022 | X29: -0.0451 | Y29: 20250923~20261002 | AA29: =IF(AND($J29<>"",OR(조회_주기="전체",$R29=조회_주기),$J29>=조회_최소,$J29<=조회_최대),1,0) | AB29: =IF($AA29=1,$AB28+1,$AB28) | AC29: =IF(검색어="",1,IF(ISNUMBER(SEARCH(검색어,$A29)),1,0)) | AD29: =IF($AC29=1,$AD28+1,$AD28) | AE29: =IFERROR(INDEX($A$4:$A$594,MATCH(26,$AD$4:$AD$594,0)),"")
A30: KODEX 미국30년국채액티브(H) | B30: 484790 | C30: 삼성자산운용(ETF) | D30: 7810 | E30: 574581700000 | F30: 4362137267 | G30: 0.00015 | H30: 0.0965 | I30: 0.0044 | J30: 0.05493 | K30: 27 | L30: 20260929 | M30: 채택 | O30: KEDI-KAP 미 국채 20년+ 지수(TR) | P30: 일반 | Q30: 채권 | R30: 월배당 | S30: 11 | T30: 0 | U30: -0.0939 | V30: -0.1411 | W30: -0.1064 | X30: -0.0901 | Y30: 20250922~20261002 | AA30: =IF(AND($J30<>"",OR(조회_주기="전체",$R30=조회_주기),$J30>=조회_최소,$J30<=조회_최대),1,0) | AB30: =IF($AA30=1,$AB29+1,$AB29) | AC30: =IF(검색어="",1,IF(ISNUMBER(SEARCH(검색어,$A30)),1,0)) | AD30: =IF($AC30=1,$AD29+1,$AD29) | AE30: =IFERROR(INDEX($A$4:$A$594,MATCH(27,$AD$4:$AD$594,0)),"")
A31: PLUS 자사주매입고배당주 | B31: 0098N0 | C31: 한화자산운용 | D31: 12810 | E31: 76860000000 | F31: 710268936 | G31: 0.003 | H31: 0.2816 | I31: 0.0053 | J31: 0.050351 | K31: 12 | L31: 20260914 | M31: 채택 | O31: FnGuide 고배당주 플러스 자사주 지수 | P31: 일반 | Q31: 주식 | R31: 월배당 | S31: 11 | T31: 0.6636 | U31: 0.3375 | V31: 0.2736 | W31: 0.0391 | X31: 0.0016 | Y31: 20250922~20261002 | AA31: =IF(AND($J31<>"",OR(조회_주기="전체",$R31=조회_주기),$J31>=조회_최소,$J31<=조회_최대),1,0) | AB31: =IF($AA31=1,$AB30+1,$AB30) | AC31: =IF(검색어="",1,IF(ISNUMBER(SEARCH(검색어,$A31)),1,0)) | AD31: =IF($AC31=1,$AD30+1,$AD30) | AE31: =IFERROR(INDEX($A$4:$A$594,MATCH(28,$AD$4:$AD$594,0)),"")
A32: ACE 미국30년국채액티브 | B32: 476760 | C32: 한국투자신탁운용 | D32: 8270 | E32: 398614000000 | F32: 5347196367 | G32: 0.0005 | H32: 0.1371 | I32: 0.0038 | J32: 0.048126 | K32: 30 | L32: 20260929 | M32: 채택 | O32: Bloomberg US Treasury 20+ Year Total Return Index | P32: 일반 | Q32: 채권 | R32: 월배당 | S32: 11 | T32: 0.6734 | U32: -0.1126 | V32: -0.1534 | W32: -0.1951 | X32: -0.1951 | Y32: 20250922~20261002 | AA32: =IF(AND($J32<>"",OR(조회_주기="전체",$R32=조회_주기),$J32>=조회_최소,$J32<=조회_최대),1,0) | AB32: =IF($AA32=1,$AB31+1,$AB31) | AC32: =IF(검색어="",1,IF(ISNUMBER(SEARCH(검색어,$A32)),1,0)) | AD32: =IF($AC32=1,$AD31+1,$AD31) | AE32: =IFERROR(INDEX($A$4:$A$594,MATCH(29,$AD$4:$AD$594,0)),"")
A33: KODEX 미국머니마켓액티브 | B33: 0048J0 | C33: 삼성자산운용(ETF) | D33: 13445 | E33: 924720210000 | F33: 8155166655 | G33: 0.0005 | H33: 0.107 | I33: 0.0045 | J33: 0.047527 | K33: 16 | L33: 20260929 | M33: 채택 | O33: KAP 미국 머니마켓 지수 | P33: 일반 | Q33: 단기자금(파킹형) | R33: 월배당 | S33: 11 | T33: 0.8091 | U33: 0.0079 | V33: -0.0379 | W33: -0.1066 | X33: -0.1184 | Y33: 20250922~20261002 | AA33: =IF(AND($J33<>"",OR(조회_주기="전체",$R33=조회_주기),$J33>=조회_최소,$J33<=조회_최대),1,0) | AB33: =IF($AA33=1,$AB32+1,$AB32) | AC33: =IF(검색어="",1,IF(ISNUMBER(SEARCH(검색어,$A33)),1,0)) | AD33: =IF($AC33=1,$AD32+1,$AD32) | AE33: =IFERROR(INDEX($A$4:$A$594,MATCH(30,$AD$4:$AD$594,0)),"")
A34: SOL 국제금커버드콜액티브 | B34: 0022T0 | C34: 신한자산운용 | D34: 12235 | E34: 69739500000 | F34: 952302235 | G34: 0.0045 | H34: 0.293 | I34: 0.0035 | J34: 0.047405 | K34: 18 | L34: 20260929 | M34: 채택 | O34: KEDI Gold Income Premium Index (Net Total Return) | P34: 커버드콜 | Q34: 원자재 | R34: 월배당 | S34: 11 | T34: 1 | U34: 0.0899 | V34: 0.0404 | W34: -0.2101 | X34: -0.1152 | Y34: 20250922~20261002 | AA34: =IF(AND($J34<>"",OR(조회_주기="전체",$R34=조회_주기),$J34>=조회_최소,$J34<=조회_최대),1,0) | AB34: =IF($AA34=1,$AB33+1,$AB33) | AC34: =IF(검색어="",1,IF(ISNUMBER(SEARCH(검색어,$A34)),1,0)) | AD34: =IF($AC34=1,$AD33+1,$AD33) | AE34: =IFERROR(INDEX($A$4:$A$594,MATCH(31,$AD$4:$AD$594,0)),"")
A35: RISE KIS국고채30년Enhanced | B35: 385560 | C35: KB자산운용 | D35: 51675 | E35: 425336925000 | F35: 1646394021 | G35: 0.0005 | H35: 0.1814 | I35: 0.0224 | J35: 0.047005 | K35: 10 | L35: 20260908 | M35: 채택 | O35: KIS 국고채30년 Enhanced 지수(시장가격지수) | P35: 일반 | Q35: 채권 | R35: 반기배당 | S35: 2 | T35: 0 | U35: -0.3342 | V35: -0.3641 | W35: -0.1918 | X35: -0.046 | Y35: 20250922~20261002 | AA35: =IF(AND($J35<>"",OR(조회_주기="전체",$R35=조회_주기),$J35>=조회_최소,$J35<=조회_최대),1,0) | AB35: =IF($AA35=1,$AB34+1,$AB34) | AC35: =IF(검색어="",1,IF(ISNUMBER(SEARCH(검색어,$A35)),1,0)) | AD35: =IF($AC35=1,$AD34+1,$AD34) | AE35: =IFERROR(INDEX($A$4:$A$594,MATCH(32,$AD$4:$AD$594,0)),"")
A36: TIGER 코리아배당다우존스 | B36: 0052D0 | C36: 미래에셋자산운용 | D36: 15230 | E36: 334298500000 | F36: 2151507477 | G36: 0.0025 | H36: 0.3054 | I36: 0.0042 | J36: 0.043926 | K36: 15 | L36: 20260914 | M36: 채택 | O36: Dow Jones Korea Dividend 30 Index (KRW) | P36: 일반 | Q36: 주식 | R36: 월배당 | S36: 11 | T36: 0.7758 | U36: 0.2657 | V36: 0.2124 | W36: -0.0262 | X36: -0.0361 | Y36: 20250922~20261002 | AA36: =IF(AND($J36<>"",OR(조회_주기="전체",$R36=조회_주기),$J36>=조회_최소,$J36<=조회_최대),1,0) | AB36: =IF($AA36=1,$AB35+1,$AB35) | AC36: =IF(검색어="",1,IF(ISNUMBER(SEARCH(검색어,$A36)),1,0)) | AD36: =IF($AC36=1,$AD35+1,$AD35) | AE36: =IFERROR(INDEX($A$4:$A$594,MATCH(33,$AD$4:$AD$594,0)),"")
A37: ACE 미국30년국채액티브(H) | B37: 453850 | C37: 한국투자신탁운용 | D37: 6780 | E37: 1408884000000 | F37: 6476816538 | G37: 0.0005 | H37: 0.0947 | I37: 0.0036 | J37: 0.043658 | K37: 42 | L37: 20260929 | M37: 채택 | O37: Bloomberg US Treasury 20+ Year Total Return Index | P37: 일반 | Q37: 채권 | R37: 월배당 | S37: 11 | T37: 0 | U37: -0.0977 | V37: -0.1354 | W37: -0.1058 | X37: -0.0907 | Y37: 20250922~20261002 | AA37: =IF(AND($J37<>"",OR(조회_주기="전체",$R37=조회_주기),$J37>=조회_최소,$J37<=조회_최대),1,0) | AB37: =IF($AA37=1,$AB36+1,$AB36) | AC37: =IF(검색어="",1,IF(ISNUMBER(SEARCH(검색어,$A37)),1,0)) | AD37: =IF($AC37=1,$AD36+1,$AD36) | AE37: =IFERROR(INDEX($A$4:$A$594,MATCH(34,$AD$4:$AD$594,0)),"")
A38: KODEX 고배당주 | B38: 279530 | C38: 삼성자산운용(ETF) | D38: 17310 | E38: 346200000000 | F38: 4339172585 | G38: 0.003 | H38: 0.2978 | I38: 0.0043 | J38: 0.043559 | K38: 37 | L38: 20260929 | M38: 채택 | O38: FnGuide 고배당 Plus 지수 | P38: 일반 | Q38: 주식 | R38: 월배당 | S38: 11 | T38: 1 | U38: 0.3567 | V38: 0.3002 | W38: 0.0367 | X38: -0.0144 | Y38: 20250922~20261002 | AA38: =IF(AND($J38<>"",OR(조회_주기="전체",$R38=조회_주기),$J38>=조회_최소,$J38<=조회_최대),1,0) | AB38: =IF($AA38=1,$AB37+1,$AB37) | AC38: =IF(검색어="",1,IF(ISNUMBER(SEARCH(검색어,$A38)),1,0)) | AD38: =IF($AC38=1,$AD37+1,$AD37) | AE38: =IFERROR(INDEX($A$4:$A$594,MATCH(35,$AD$4:$AD$594,0)),"")
A39: KODEX 미국10년국채액티브(H) | B39: 0091C0 | C39: 삼성자산운용(ETF) | D39: 9250 | E39: 186110000000 | F39: 921787991 | G39: 0.0015 | H39: 0.0472 | I39: 0.0036 | J39: 0.043243 | K39: 12 | L39: 20260914 | M39: 채택 | O39: KAP 미국 국채 10년 지수(총수익) | P39: 일반 | Q39: 채권 | R39: 월배당 | S39: 11 | T39: 0.495 | U39: -0.0479 | V39: -0.0874 | W39: -0.0671 | X39: -0.0529 | Y39: 20250922~20261002 | AA39: =IF(AND($J39<>"",OR(조회_주기="전체",$R39=조회_주기),$J39>=조회_최소,$J39<=조회_최대),1,0) | AB39: =IF($AA39=1,$AB38+1,$AB38) | AC39: =IF(검색어="",1,IF(ISNUMBER(SEARCH(검색어,$A39)),1,0)) | AD39: =IF($AC39=1,$AD38+1,$AD38) | AE39: =IFERROR(INDEX($A$4:$A$594,MATCH(36,$AD$4:$AD$594,0)),"")
A40: PLUS 고배당주 | B40: 161510 | C40: 한화자산운용 | D40: 24490 | E40: 2364264600000 | F40: 18509006119 | G40: 0.0023 | H40: 0.3059 | I40: 0.0041 | J40: 0.043242 | K40: 32 | L40: 20260929 | M40: 채택 | O40: FnGuide 고배당주 | P40: 일반 | Q40: 주식 | R40: 월배당 | S40: 11 | T40: 0.9603 | U40: 0.2811 | V40: 0.2281 | W40: -0.0233 | X40: -0.0272 | Y40: 20250922~20261002 | AA40: =IF(AND($J40<>"",OR(조회_주기="전체",$R40=조회_주기),$J40>=조회_최소,$J40<=조회_최대),1,0) | AB40: =IF($AA40=1,$AB39+1,$AB39) | AC40: =IF(검색어="",1,IF(ISNUMBER(SEARCH(검색어,$A40)),1,0)) | AD40: =IF($AC40=1,$AD39+1,$AD39) | AE40: =IFERROR(INDEX($A$4:$A$594,MATCH(37,$AD$4:$AD$594,0)),"")
A41: KODEX 미국달러SOFR금리액티브(합성) | B41: 455030 | C41: 삼성자산운용(ETF) | D41: 11580 | E41: 533838000000 | F41: 1560127659 | G41: 0.0015 | H41: 0.1077 | I41: 0.0037 | J41: 0.042746 | K41: 15 | L41: 20260929 | M41: 채택 | O41: Bloomberg SOFR Index | P41: 일반 | Q41: 단기자금(파킹형) | R41: 월배당 | S41: 11 | T41: 1 | U41: 0.0058 | V41: -0.0355 | W41: -0.1048 | X41: -0.1163 | Y41: 20250922~20261002 | AA41: =IF(AND($J41<>"",OR(조회_주기="전체",$R41=조회_주기),$J41>=조회_최소,$J41<=조회_최대),1,0) | AB41: =IF($AA41=1,$AB40+1,$AB40) | AC41: =IF(검색어="",1,IF(ISNUMBER(SEARCH(검색어,$A41)),1,0)) | AD41: =IF($AC41=1,$AD40+1,$AD40) | AE41: =IFERROR(INDEX($A$4:$A$594,MATCH(38,$AD$4:$AD$594,0)),"")
A42: ACE 미국10년국채액티브 | B42: 0085P0 | C42: 한국투신운용(ETF) | D42: 9295 | E42: 137566000000 | F42: 1975987259 | G42: 0.0015 | H42: 0.11 | I42: 0.0032 | J42: 0.040452 | K42: 14 | L42: 20260929 | M42: 채택 | O42: ICE U.S.Treasury 7-10 Year Bond Index | P42: 일반 | Q42: 채권 | R42: 월배당 | S42: 11 | T42: 0.8378 | U42: -0.0607 | V42: -0.0973 | W42: -0.1529 | X42: -0.1565 | Y42: 20250922~20261002 | AA42: =IF(AND($J42<>"",OR(조회_주기="전체",$R42=조회_주기),$J42>=조회_최소,$J42<=조회_최대),1,0) | AB42: =IF($AA42=1,$AB41+1,$AB41) | AC42: =IF(검색어="",1,IF(ISNUMBER(SEARCH(검색어,$A42)),1,0)) | AD42: =IF($AC42=1,$AD41+1,$AD41) | AE42: =IFERROR(INDEX($A$4:$A$594,MATCH(39,$AD$4:$AD$594,0)),"")
A43: KODEX 은행 | B43: 091170 | C43: 삼성자산운용(ETF) | D43: 15755 | E43: 280439000000 | F43: 23845225509 | G43: 0.003 | H43: 0.3456 | I43: 0.0037 | J43: 0.03986 | K43: 30 | L43: 20260929 | M43: 채택 | O43: KRX 은행 | P43: 일반 | Q43: 주식 | R43: 월배당 | S43: 11 | T43: 0.8089 | U43: 0.3558 | V43: 0.304 | W43: 0.0801 | X43: -0.0039 | Y43: 20250922~20261002 | AA43: =IF(AND($J43<>"",OR(조회_주기="전체",$R43=조회_주기),$J43>=조회_최소,$J43<=조회_최대),1,0) | AB43: =IF($AA43=1,$AB42+1,$AB42) | AC43: =IF(검색어="",1,IF(ISNUMBER(SEARCH(검색어,$A43)),1,0)) | AD43: =IF($AC43=1,$AD42+1,$AD42) | AE43: =IFERROR(INDEX($A$4:$A$594,MATCH(40,$AD$4:$AD$594,0)),"")
A44: TIGER 은행고배당플러스TOP10 | B44: 466940 | C44: 미래에셋자산운용 | D44: 25900 | E44: 819735000000 | F44: 19567358075 | G44: 0.003 | H44: 0.337 | I44: 0.0038 | J44: 0.039691 | K44: 33 | L44: 20260929 | M44: 채택 | O44: FnGuide 은행 고배당 플러스 TOP 10 지수 | P44: 일반 | Q44: 주식 | R44: 월배당 | S44: 11 | T44: 0.9747 | U44: 0.3327 | V44: 0.2819 | W44: 0.0623 | X44: -0.0173 | Y44: 20250922~20261002 | AA44: =IF(AND($J44<>"",OR(조회_주기="전체",$R44=조회_주기),$J44>=조회_최소,$J44<=조회_최대),1,0) | AB44: =IF($AA44=1,$AB43+1,$AB43) | AC44: =IF(검색어="",1,IF(ISNUMBER(SEARCH(검색어,$A44)),1,0)) | AD44: =IF($AC44=1,$AD43+1,$AD43) | AE44: =IFERROR(INDEX($A$4:$A$594,MATCH(41,$AD$4:$AD$594,0)),"")
A45: PLUS 고배당주채권혼합 | B45: 251600 | C45: 한화자산운용 | D45: 15210 | E45: 590148000000 | F45: 3185640992 | G45: 0.002 | H45: 0.154 | I45: 0.0033 | J45: 0.037673 | K45: 34 | L45: 20260929 | M45: 채택 | O45: FnGuide 고배당 채권혼합 지수 | P45: 일반 | Q45: 멀티에셋 | R45: 월배당 | S45: 11 | T45: 1 | U45: 0.1242 | V45: 0.0835 | W45: -0.0129 | X45: -0.0136 | Y45: 20250922~20261002 | AA45: =IF(AND($J45<>"",OR(조회_주기="전체",$R45=조회_주기),$J45>=조회_최소,$J45<=조회_최대),1,0) | AB45: =IF($AA45=1,$AB44+1,$AB44) | AC45: =IF(검색어="",1,IF(ISNUMBER(SEARCH(검색어,$A45)),1,0)) | AD45: =IF($AC45=1,$AD44+1,$AD44) | AE45: =IFERROR(INDEX($A$4:$A$594,MATCH(42,$AD$4:$AD$594,0)),"")
A46: ACE 미국30년국채엔화노출액티브(H) | B46: 476750 | C46: 한국투자신탁운용 | D46: 6915 | E46: 56011500000 | F46: 676090167 | G46: 0.0015 | H46: 0.1333 | I46: 0.0031 | J46: 0.037021 | K46: 30 | L46: 20260929 | M46: 채택 | O46: Bloomberg U.S. Treasury 20+ Year Index T1530 JPY Currency He | P46: 일반 | Q46: 채권 | R46: 월배당 | S46: 11 | T46: 0 | U46: -0.2024 | V46: -0.2309 | W46: -0.1973 | X46: -0.1898 | Y46: 20250922~20261002 | AA46: =IF(AND($J46<>"",OR(조회_주기="전체",$R46=조회_주기),$J46>=조회_최소,$J46<=조회_최대),1,0) | AB46: =IF($AA46=1,$AB45+1,$AB45) | AC46: =IF(검색어="",1,IF(ISNUMBER(SEARCH(검색어,$A46)),1,0)) | AD46: =IF($AC46=1,$AD45+1,$AD45) | AE46: =IFERROR(INDEX($A$4:$A$594,MATCH(43,$AD$4:$AD$594,0)),"")
A47: RISE 미국30년국채엔화노출(합성 H) | B47: 472870 | C47: KB자산운용 | D47: 6400 | E47: 155200000000 | F47: 1579357166 | G47: 0.0015 | H47: 0.1435 | I47: 0.0024 | J47: 0.036563 | K47: 30 | L47: 20260929 | M47: 채택 | O47: KIS 미국채 30년 엔화노출 지수(USD/JPY 헤지) | P47: 일반 | Q47: 채권 | R47: 월배당 | S47: 11 | T47: 0 | U47: -0.2057 | V47: -0.2337 | W47: -0.1921 | X47: -0.1897 | Y47: 20250922~20261002 | AA47: =IF(AND($J47<>"",OR(조회_주기="전체",$R47=조회_주기),$J47>=조회_최소,$J47<=조회_최대),1,0) | AB47: =IF($AA47=1,$AB46+1,$AB46) | AC47: =IF(검색어="",1,IF(ISNUMBER(SEARCH(검색어,$A47)),1,0)) | AD47: =IF($AC47=1,$AD46+1,$AD46) | AE47: =IFERROR(INDEX($A$4:$A$594,MATCH(44,$AD$4:$AD$594,0)),"")
A48: TIGER 미국초단기(3개월이하)국채 | B48: 0046A0 | C48: 미래에셋자산운용 | D48: 9340 | E48: 391439400000 | F48: 7265714404 | G48: 0.0009 | H48: 0.1064 | I48: 0.0025 | J48: 0.035974 | K48: 17 | L48: 20260929 | M48: 채택 | O48: ICE 0-3 Month US Treasury Securities Index | P48: 일반 | Q48: 단기자금(파킹형) | R48: 월배당 | S48: 11 | T48: 0.8512 | U48: 0.0006 | V48: -0.0341 | W48: -0.1025 | X48: -0.1138 | Y48: 20250922~20261002 | AA48: =IF(AND($J48<>"",OR(조회_주기="전체",$R48=조회_주기),$J48>=조회_최소,$J48<=조회_최대),1,0) | AB48: =IF($AA48=1,$AB47+1,$AB47) | AC48: =IF(검색어="",1,IF(ISNUMBER(SEARCH(검색어,$A48)),1,0)) | AD48: =IF($AC48=1,$AD47+1,$AD47) | AE48: =IFERROR(INDEX($A$4:$A$594,MATCH(45,$AD$4:$AD$594,0)),"")
A49: KIWOOM 국고채10년 | B49: 148070 | C49: 키움투자자산운용 | D49: 104855 | E49: 394045090000 | F49: 1928782142 | G49: 0.0005 | H49: 0.0739 | I49: 0.0332 | J49: 0.035687 | K49: 4 | L49: 20251229 | M49: 채택 | O49: KIS 10Y KTB | P49: 일반 | Q49: 채권 | R49: 연배당 | S49: 1 | T49: 1 | U49: -0.074 | V49: -0.1059 | W49: -0.0239 | X49: -0.0013 | Y49: 20250922~20261002 | AA49: =IF(AND($J49<>"",OR(조회_주기="전체",$R49=조회_주기),$J49>=조회_최소,$J49<=조회_최대),1,0) | AB49: =IF($AA49=1,$AB48+1,$AB48) | AC49: =IF(검색어="",1,IF(ISNUMBER(SEARCH(검색어,$A49)),1,0)) | AD49: =IF($AC49=1,$AD48+1,$AD48) | AE49: =IFERROR(INDEX($A$4:$A$594,MATCH(46,$AD$4:$AD$594,0)),"")
A50: ACE 미국달러단기채권액티브 | B50: 440650 | C50: 한국투자신탁운용 | D50: 11350 | E50: 43130000000 | F50: 697444954 | G50: 0.003 | H50: 0.1103 | I50: 0.0303 | J50: 0.032599 | K50: 1 | L50: 20251229 | M50: 채택 | O50: Bloomberg Short-term Treasury Total Return Index | P50: 일반 | Q50: 채권 | R50: 연배당 | S50: 1 | T50: 1 | U50: 0.0008 | V50: -0.0308 | W50: -0.0897 | X50: -0.1085 | Y50: 20250922~20261002 | AA50: =IF(AND($J50<>"",OR(조회_주기="전체",$R50=조회_주기),$J50>=조회_최소,$J50<=조회_최대),1,0) | AB50: =IF($AA50=1,$AB49+1,$AB49) | AC50: =IF(검색어="",1,IF(ISNUMBER(SEARCH(검색어,$A50)),1,0)) | AD50: =IF($AC50=1,$AD49+1,$AD49) | AE50: =IFERROR(INDEX($A$4:$A$594,MATCH(47,$AD$4:$AD$594,0)),"")
A51: ACE 국고채10년 | B51: 365780 | C51: 한국투신운용(ETF) | D51: 82655 | E51: 528661380000 | F51: 1141901906 | G51: 0.0002 | H51: 0.072 | I51: 0.0301 | J51: 0.032303 | K51: 5 | L51: 20251229 | M51: 채택 | O51: KIS 10Y KTB | P51: 일반 | Q51: 채권 | R51: 연배당 | S51: 1 | T51: 0 | U51: -0.0734 | V51: -0.1024 | W51: -0.024 | X51: -0.0014 | Y51: 20250922~20261002 | AA51: =IF(AND($J51<>"",OR(조회_주기="전체",$R51=조회_주기),$J51>=조회_최소,$J51<=조회_최대),1,0) | AB51: =IF($AA51=1,$AB50+1,$AB50) | AC51: =IF(검색어="",1,IF(ISNUMBER(SEARCH(검색어,$A51)),1,0)) | AD51: =IF($AC51=1,$AD50+1,$AD50) | AE51: =IFERROR(INDEX($A$4:$A$594,MATCH(48,$AD$4:$AD$594,0)),"")
A52: SOL 미국배당다우존스 | B52: 446720 | C52: 신한자산운용 | D52: 12875 | E52: 990087500000 | F52: 4385191953 | G52: 0.0001 | H52: 0.1422 | I52: 0.0028 | J52: 0.031689 | K52: 46 | L52: 20260929 | M52: 채택 | O52: Dow Jones U.S. Dividend 100 Price Return Index | P52: 일반 | Q52: 주식 | R52: 월배당 | S52: 11 | T52: 1 | U52: 0.1959 | V52: 0.159 | W52: -0.0425 | X52: -0.1079 | Y52: 20250922~20261002 | AA52: =IF(AND($J52<>"",OR(조회_주기="전체",$R52=조회_주기),$J52>=조회_최소,$J52<=조회_최대),1,0) | AB52: =IF($AA52=1,$AB51+1,$AB51) | AC52: =IF(검색어="",1,IF(ISNUMBER(SEARCH(검색어,$A52)),1,0)) | AD52: =IF($AC52=1,$AD51+1,$AD51) | AE52: =IFERROR(INDEX($A$4:$A$594,MATCH(49,$AD$4:$AD$594,0)),"")
A53: SOL CD금리&머니마켓액티브 | B53: 497880 | C53: 신한자산운용 | D53: 50045 | E53: 299569370000 | F53: 5672018434 | G53: 0.0005 | H53: 0.0094 | I53: 0.0028 | J53: 0.031671 | K53: 22 | L53: 20260929 | M53: 채택 | O53: KAP CD & 단기자금시장 지수 | P53: 일반 | Q53: 단기자금(파킹형) | R53: 월배당 | S53: 11 | T53: 1 | U53: 0.0306 | V53: -0.001 | W53: 0.0002 | X53: 0.0002 | Y53: 20250922~20261002 | AA53: =IF(AND($J53<>"",OR(조회_주기="전체",$R53=조회_주기),$J53>=조회_최소,$J53<=조회_최대),1,0) | AB53: =IF($AA53=1,$AB52+1,$AB52) | AC53: =IF(검색어="",1,IF(ISNUMBER(SEARCH(검색어,$A53)),1,0)) | AD53: =IF($AC53=1,$AD52+1,$AD52) | AE53: =IFERROR(INDEX($A$4:$A$594,MATCH(50,$AD$4:$AD$594,0)),"")
A54: TIGER 미국배당다우존스 | B54: 458730 | C54: 미래에셋자산운용 | D54: 14055 | E54: 4188390000000 | F54: 31822680942 | G54: 0.0001 | H54: 0.1422 | I54: 0.0027 | J54: 0.030879 | K54: 39 | L54: 20260929 | M54: 채택 | O54: Dow Jones U.S. Dividend 100 Price Return Index | P54: 일반 | Q54: 주식 | R54: 월배당 | S54: 11 | T54: 1 | U54: 0.1963 | V54: 0.1603 | W54: -0.0421 | X54: -0.1075 | Y54: 20250922~20261002 | AA54: =IF(AND($J54<>"",OR(조회_주기="전체",$R54=조회_주기),$J54>=조회_최소,$J54<=조회_최대),1,0) | AB54: =IF($AA54=1,$AB53+1,$AB53) | AC54: =IF(검색어="",1,IF(ISNUMBER(SEARCH(검색어,$A54)),1,0)) | AD54: =IF($AC54=1,$AD53+1,$AD53) | AE54: =IFERROR(INDEX($A$4:$A$594,MATCH(51,$AD$4:$AD$594,0)),"")
A55: SOL 미국배당미국채혼합50 | B55: 490490 | C55: 신한자산운용 | D55: 10450 | E55: 452485000000 | F55: 2418494195 | G55: 0.0015 | H55: 0.1083 | I55: 0.0026 | J55: 0.030813 | K55: 23 | L55: 20260914 | M55: 채택 | O55: KRX 다우존스 미국배당국채 혼합지수 | P55: 일반 | Q55: 멀티에셋 | R55: 월배당 | S55: 11 | T55: 1 | U55: 0.062 | V55: 0.0302 | W55: -0.0967 | X55: -0.1291 | Y55: 20250922~20261002 | AA55: =IF(AND($J55<>"",OR(조회_주기="전체",$R55=조회_주기),$J55>=조회_최소,$J55<=조회_최대),1,0) | AB55: =IF($AA55=1,$AB54+1,$AB54) | AC55: =IF(검색어="",1,IF(ISNUMBER(SEARCH(검색어,$A55)),1,0)) | AD55: =IF($AC55=1,$AD54+1,$AD54) | AE55: =IFERROR(INDEX($A$4:$A$594,MATCH(52,$AD$4:$AD$594,0)),"")
A56: ACE 미국배당다우존스 | B56: 402970 | C56: 한국투신운용(ETF) | D56: 14330 | E56: 928584000000 | F56: 4584464345 | G56: 0.0001 | H56: 0.1413 | I56: 0.0024 | J56: 0.030775 | K56: 44 | L56: 20260914 | M56: 채택 | O56: Dow Jones U.S. Dividend 100 Price Return Index | P56: 일반 | Q56: 주식 | R56: 월배당 | S56: 11 | T56: 1 | U56: 0.2018 | V56: 0.1658 | W56: -0.0417 | X56: -0.1075 | Y56: 20250922~20261002 | AA56: =IF(AND($J56<>"",OR(조회_주기="전체",$R56=조회_주기),$J56>=조회_최소,$J56<=조회_최대),1,0) | AB56: =IF($AA56=1,$AB55+1,$AB55) | AC56: =IF(검색어="",1,IF(ISNUMBER(SEARCH(검색어,$A56)),1,0)) | AD56: =IF($AC56=1,$AD55+1,$AD55) | AE56: =IFERROR(INDEX($A$4:$A$594,MATCH(53,$AD$4:$AD$594,0)),"")
A57: KODEX 미국배당다우존스 | B57: 489250 | C57: 삼성자산운용(ETF) | D57: 12115 | E57: 593635000000 | F57: 5478065045 | G57: 9.9e-05 | H57: 0.1422 | I57: 0.0019 | J57: 0.030376 | K57: 25 | L57: 20260914 | M57: 채택 | O57: Dow Jones U.S. Dividend 100 Price Return Index | P57: 일반 | Q57: 주식 | R57: 월배당 | S57: 11 | T57: 1 | U57: 0.2032 | V57: 0.1676 | W57: -0.042 | X57: -0.1078 | Y57: 20250922~20261002 | AA57: =IF(AND($J57<>"",OR(조회_주기="전체",$R57=조회_주기),$J57>=조회_최소,$J57<=조회_최대),1,0) | AB57: =IF($AA57=1,$AB56+1,$AB56) | AC57: =IF(검색어="",1,IF(ISNUMBER(SEARCH(검색어,$A57)),1,0)) | AD57: =IF($AC57=1,$AD56+1,$AD56) | AE57: =IFERROR(INDEX($A$4:$A$594,MATCH(54,$AD$4:$AD$594,0)),"")
A58: KODEX 코리아배당성장채권혼합 | B58: 237370 | C58: 삼성자산운용(ETF) | D58: 15535 | E58: 161564000000 | F58: 904598682 | G58: 0.0019 | H58: 0.1083 | I58: 0.003 | J58: 0.029868 | K58: 24 | L58: 20260914 | M58: 채택 | O58: 배당성장채권혼합지수 | P58: 일반 | Q58: 멀티에셋 | R58: 월배당 | S58: 11 | T58: 1 | U58: 0.1026 | V58: 0.0707 | W58: -0.0069 | X58: -0.0205 | Y58: 20250922~20261002 | AA58: =IF(AND($J58<>"",OR(조회_주기="전체",$R58=조회_주기),$J58>=조회_최소,$J58<=조회_최대),1,0) | AB58: =IF($AA58=1,$AB57+1,$AB57) | AC58: =IF(검색어="",1,IF(ISNUMBER(SEARCH(검색어,$A58)),1,0)) | AD58: =IF($AC58=1,$AD57+1,$AD57) | AE58: =IFERROR(INDEX($A$4:$A$594,MATCH(55,$AD$4:$AD$594,0)),"")
A59: KODEX CD1년금리플러스액티브(합성) | B59: 481050 | C59: 삼성자산운용(ETF) | D59: 1021990 | E59: 2663816935000 | F59: 26920311248 | G59: 0.0005 | H59: 0.0087 | I59: 0.0028 | J59: 0.029375 | K59: 22 | L59: 20260929 | M59: 채택 | O59: KAP 1년은행CD+추가금리 지수 | P59: 일반 | Q59: 단기자금(파킹형) | R59: 월배당 | S59: 11 | T59: 1 | U59: 0.028 | V59: -0.0013 | W59: 0.0001 | X59: 0 | Y59: 20250922~20261002 | AA59: =IF(AND($J59<>"",OR(조회_주기="전체",$R59=조회_주기),$J59>=조회_최소,$J59<=조회_최대),1,0) | AB59: =IF($AA59=1,$AB58+1,$AB58) | AC59: =IF(검색어="",1,IF(ISNUMBER(SEARCH(검색어,$A59)),1,0)) | AD59: =IF($AC59=1,$AD58+1,$AD58) | AE59: =IFERROR(INDEX($A$4:$A$594,MATCH(56,$AD$4:$AD$594,0)),"")
A60: SOL 미국배당다우존스(H) | B60: 452360 | C60: 신한자산운용 | D60: 12850 | E60: 215880000000 | F60: 1962742979 | G60: 0.0005 | H60: 0.1113 | I60: 0.0028 | J60: 0.029183 | K60: 42 | L60: 20260929 | M60: 채택 | O60: Dow Jones U.S. Dividend 100 Price Return Index | P60: 일반 | Q60: 주식 | R60: 월배당 | S60: 11 | T60: 1 | U60: 0.212 | V60: 0.1776 | W60: 0.0612 | X60: 0.005 | Y60: 20250922~20261002 | AA60: =IF(AND($J60<>"",OR(조회_주기="전체",$R60=조회_주기),$J60>=조회_최소,$J60<=조회_최대),1,0) | AB60: =IF($AA60=1,$AB59+1,$AB59) | AC60: =IF(검색어="",1,IF(ISNUMBER(SEARCH(검색어,$A60)),1,0)) | AD60: =IF($AC60=1,$AD59+1,$AD59) | AE60: =IFERROR(INDEX($A$4:$A$594,MATCH(57,$AD$4:$AD$594,0)),"")
A61: TIGER CD금리플러스액티브(합성) | B61: 499660 | C61: 미래에셋자산운용 | D61: 1000470 | E61: 455714085000 | F61: 13842008410 | G61: 9.8e-05 | H61: 0.0086 | I61: 0.003 | J61: 0.028956 | K61: 22 | L61: 20260929 | M61: 채택 | O61: KIS CD+CPI연동금리 월분배 지수(PR지수) | P61: 일반 | Q61: 단기자금(파킹형) | R61: 월배당 | S61: 11 | T61: 0.9951 | U61: 0.0276 | V61: -0.0014 | W61: 0 | X61: -0.0001 | Y61: 20250922~20261002 | AA61: =IF(AND($J61<>"",OR(조회_주기="전체",$R61=조회_주기),$J61>=조회_최소,$J61<=조회_최대),1,0) | AB61: =IF($AA61=1,$AB60+1,$AB60) | AC61: =IF(검색어="",1,IF(ISNUMBER(SEARCH(검색어,$A61)),1,0)) | AD61: =IF($AC61=1,$AD60+1,$AD60) | AE61: =IFERROR(INDEX($A$4:$A$594,MATCH(58,$AD$4:$AD$594,0)),"")
A62: KODEX CD금리액티브(합성) | B62: 459580 | C62: 삼성자산운용(ETF) | D62: 1073765 | E62: 6985270831000 | F62: 604830690787 | G62: 0.0002 | H62: 0.0083 | I62: 0.0026 | J62: 0.027945 | K62: 15 | L62: 20260929 | M62: 채택 | O62: KAP 양도성예금증서(CD) 금리 지수 | P62: 일반 | Q62: 단기자금(파킹형) | R62: 월배당 | S62: 11 | T62: 1 | U62: 0.0269 | V62: -0.001 | W62: 0.0002 | X62: 0.0002 | Y62: 20250922~20261002 | AA62: =IF(AND($J62<>"",OR(조회_주기="전체",$R62=조회_주기),$J62>=조회_최소,$J62<=조회_최대),1,0) | AB62: =IF($AA62=1,$AB61+1,$AB61) | AC62: =IF(검색어="",1,IF(ISNUMBER(SEARCH(검색어,$A62)),1,0)) | AD62: =IF($AC62=1,$AD61+1,$AD61) | AE62: =IFERROR(INDEX($A$4:$A$594,MATCH(59,$AD$4:$AD$594,0)),"")
A63: TIGER 차이나CSI300 | B63: 192090 | C63: 미래에셋자산운용 | D63: 11405 | E63: 116901250000 | F63: 691820362 | G63: 0.0063 | H63: 0.2287 | I63: 0.0242 | J63: 0.027181 | K63: 5 | L63: 20251229 | M63: 채택 | O63: CSI 300 INDEX | P63: 일반 | Q63: 주식 | R63: 연배당 | S63: 1 | T63: 1 | U63: 0.0138 | V63: -0.0126 | W63: -0.0987 | X63: -0.191 | Y63: 20250922~20261002 | AA63: =IF(AND($J63<>"",OR(조회_주기="전체",$R63=조회_주기),$J63>=조회_최소,$J63<=조회_최대),1,0) | AB63: =IF($AA63=1,$AB62+1,$AB62) | AC63: =IF(검색어="",1,IF(ISNUMBER(SEARCH(검색어,$A63)),1,0)) | AD63: =IF($AC63=1,$AD62+1,$AD62) | AE63: =IFERROR(INDEX($A$4:$A$594,MATCH(60,$AD$4:$AD$594,0)),"")
A64: KODEX 단기채권PLUS | B64: 214980 | C64: 삼성자산운용(ETF) | D64: 114580 | E64: 1939266500000 | F64: 4150412942 | G64: 0.0015 | H64: 0.0081 | I64: 0.0025 | J64: 0.026924 | K64: 14 | L64: 20260914 | M64: 채택 | O64: KRW Cash+PLUS Index | P64: 일반 | Q64: 채권 | R64: 월배당 | S64: 11 | T64: 1 | U64: 0.0232 | V64: -0.0036 | W64: -0.0017 | X64: 0.0002 | Y64: 20250922~20261002 | AA64: =IF(AND($J64<>"",OR(조회_주기="전체",$R64=조회_주기),$J64>=조회_최소,$J64<=조회_최대),1,0) | AB64: =IF($AA64=1,$AB63+1,$AB63) | AC64: =IF(검색어="",1,IF(ISNUMBER(SEARCH(검색어,$A64)),1,0)) | AD64: =IF($AC64=1,$AD63+1,$AD63) | AE64: =IFERROR(INDEX($A$4:$A$594,MATCH(61,$AD$4:$AD$594,0)),"")
A65: RISE 국고채3년 | B65: 114100 | C65: KB자산운용 | D65: 106290 | E65: 89283600000 | F65: 855561077 | G65: 0.00115 | H65: 0.0258 | I65: 0.0056 | J65: 0.026691 | K65: 20 | L65: 20260908 | M65: 채택 | O65: KTB Index | P65: 일반 | Q65: 채권 | R65: 분기배당 | S65: 4 | T65: 1 | U65: -0.0065 | V65: -0.0323 | W65: -0.0087 | X65: 0.0001 | Y65: 20250922~20261002 | AA65: =IF(AND($J65<>"",OR(조회_주기="전체",$R65=조회_주기),$J65>=조회_최소,$J65<=조회_최대),1,0) | AB65: =IF($AA65=1,$AB64+1,$AB64) | AC65: =IF(검색어="",1,IF(ISNUMBER(SEARCH(검색어,$A65)),1,0)) | AD65: =IF($AC65=1,$AD64+1,$AD64) | AE65: =IFERROR(INDEX($A$4:$A$594,MATCH(62,$AD$4:$AD$594,0)),"")
A66: KODEX KOFR금리액티브(합성) | B66: 423160 | C66: 삼성자산운용(ETF) | D66: 110715 | E66: 3497708280000 | F66: 10963878976 | G66: 0.0005 | H66: 0.0078 | I66: 0.0024 | J66: 0.026383 | K66: 15 | L66: 20260929 | M66: 채택 | O66: KOFR 인덱스 | P66: 일반 | Q66: 단기자금(파킹형) | R66: 월배당 | S66: 11 | T66: 1 | U66: 0.0253 | V66: -0.0011 | W66: 0.0002 | X66: 0.0002 | Y66: 20250922~20261002 | AA66: =IF(AND($J66<>"",OR(조회_주기="전체",$R66=조회_주기),$J66>=조회_최소,$J66<=조회_최대),1,0) | AB66: =IF($AA66=1,$AB65+1,$AB65) | AC66: =IF(검색어="",1,IF(ISNUMBER(SEARCH(검색어,$A66)),1,0)) | AD66: =IF($AC66=1,$AD65+1,$AD65) | AE66: =IFERROR(INDEX($A$4:$A$594,MATCH(63,$AD$4:$AD$594,0)),"")
A67: KODEX TRF3070 | B67: 329650 | C67: 삼성자산운용(ETF) | D67: 13980 | E67: 230670000000 | F67: 575127569 | G67: 0.0024 | H67: 0.049 | I67: 0.0022 | J67: 0.025966 | K67: 14 | L67: 20260914 | M67: 채택 | O67: FnGuide TRF 3070 지수 | P67: 일반 | Q67: 멀티에셋 | R67: 월배당 | S67: 11 | T67: 1 | U67: 0.0119 | V67: -0.0137 | W67: -0.0253 | X67: -0.0369 | Y67: 20250922~20261002 | AA67: =IF(AND($J67<>"",OR(조회_주기="전체",$R67=조회_주기),$J67>=조회_최소,$J67<=조회_최대),1,0) | AB67: =IF($AA67=1,$AB66+1,$AB66) | AC67: =IF(검색어="",1,IF(ISNUMBER(SEARCH(검색어,$A67)),1,0)) | AD67: =IF($AC67=1,$AD66+1,$AD66) | AE67: =IFERROR(INDEX($A$4:$A$594,MATCH(64,$AD$4:$AD$594,0)),"")
A68: RISE 중기우량회사채 | B68: 136340 | C68: KB자산운용 | D68: 104140 | E68: 291175440000 | F68: 730276417 | G68: 0.0007 | H68: 0.0221 | I68: 0.0023 | J68: 0.025917 | K68: 46 | L68: 20260929 | M68: 채택 | O68: KOBI Credit | P68: 일반 | Q68: 채권 | R68: 월배당 | S68: 11 | T68: 1 | U68: -0.0084 | V68: -0.0335 | W68: -0.0045 | X68: 0.0015 | Y68: 20250922~20261002 | AA68: =IF(AND($J68<>"",OR(조회_주기="전체",$R68=조회_주기),$J68>=조회_최소,$J68<=조회_최대),1,0) | AB68: =IF($AA68=1,$AB67+1,$AB67) | AC68: =IF(검색어="",1,IF(ISNUMBER(SEARCH(검색어,$A68)),1,0)) | AD68: =IF($AC68=1,$AD67+1,$AD67) | AE68: =IFERROR(INDEX($A$4:$A$594,MATCH(65,$AD$4:$AD$594,0)),"")
A69: ACE 단기통안채 | B69: 190620 | C69: 한국투신운용(ETF) | D69: 102235 | E69: 261312660000 | F69: 2143606187 | G69: 0.0007 | H69: 0.0255 | I69: 0.0251 | J69: 0.025236 | K69: 5 | L69: 20251229 | M69: 채택 | O69: KIS MSB 단기 Index | P69: 일반 | Q69: 채권 | R69: 연배당 | S69: 1 | T69: 1 | U69: 0.0238 | V69: -0.0014 | W69: 0.0131 | X69: 0.0069 | Y69: 20250922~20261002 | AA69: =IF(AND($J69<>"",OR(조회_주기="전체",$R69=조회_주기),$J69>=조회_최소,$J69<=조회_최대),1,0) | AB69: =IF($AA69=1,$AB68+1,$AB68) | AC69: =IF(검색어="",1,IF(ISNUMBER(SEARCH(검색어,$A69)),1,0)) | AD69: =IF($AC69=1,$AD68+1,$AD68) | AE69: =IFERROR(INDEX($A$4:$A$594,MATCH(66,$AD$4:$AD$594,0)),"")
A70: KODEX 단기채권 | B70: 153130 | C70: 삼성자산운용(ETF) | D70: 113265 | E70: 986311620000 | F70: 2888657001 | G70: 0.0015 | H70: 0.0074 | I70: 0.0022 | J70: 0.025145 | K70: 14 | L70: 20260914 | M70: 채택 | O70: KRW Cash Index | P70: 일반 | Q70: 채권 | R70: 월배당 | S70: 11 | T70: 1 | U70: 0.0222 | V70: -0.0028 | W70: -0.0007 | X70: -0.0001 | Y70: 20250922~20261002 | AA70: =IF(AND($J70<>"",OR(조회_주기="전체",$R70=조회_주기),$J70>=조회_최소,$J70<=조회_최대),1,0) | AB70: =IF($AA70=1,$AB69+1,$AB69) | AC70: =IF(검색어="",1,IF(ISNUMBER(SEARCH(검색어,$A70)),1,0)) | AD70: =IF($AC70=1,$AD69+1,$AD69) | AE70: =IFERROR(INDEX($A$4:$A$594,MATCH(67,$AD$4:$AD$594,0)),"")
A71: KODEX 차이나CSI300 | B71: 283580 | C71: 삼성자산운용(ETF) | D71: 14020 | E71: 229227000000 | F71: 1820691849 | G71: 0.0012 | H71: 0.2232 | I71: 0.0079 | J71: 0.02475 | K71: 7 | L71: 20260730 | M71: 채택 | O71: CSI 300 INDEX | P71: 일반 | Q71: 주식 | R71: 분기배당 | S71: 3 | T71: 1 | U71: 0.0198 | V71: -0.0044 | W71: -0.0977 | X71: -0.188 | Y71: 20250922~20261002 | AA71: =IF(AND($J71<>"",OR(조회_주기="전체",$R71=조회_주기),$J71>=조회_최소,$J71<=조회_최대),1,0) | AB71: =IF($AA71=1,$AB70+1,$AB70) | AC71: =IF(검색어="",1,IF(ISNUMBER(SEARCH(검색어,$A71)),1,0)) | AD71: =IF($AC71=1,$AD70+1,$AD70) | AE71: =IFERROR(INDEX($A$4:$A$594,MATCH(68,$AD$4:$AD$594,0)),"")
A72: ACE 미국S&P500미국채혼합50액티브 | B72: 438080 | C72: 한국투자신탁운용 | D72: 13770 | E72: 1236546000000 | F72: 6219987377 | G72: 0.0015 | H72: 0.0999 | I72: 0.0236 | J72: 0.024256 | K72: 1 | L72: 20251229 | M72: 채택 | O72: S&P 500 and Short-Term Treasury 50/50 Blend Index (USD) | P72: 일반 | Q72: 멀티에셋 | R72: 연배당 | S72: 1 | T72: 1 | U72: 0.057 | V72: 0.0319 | W72: -0.0218 | X72: -0.1008 | Y72: 20250922~20261002 | AA72: =IF(AND($J72<>"",OR(조회_주기="전체",$R72=조회_주기),$J72>=조회_최소,$J72<=조회_최대),1,0) | AB72: =IF($AA72=1,$AB71+1,$AB71) | AC72: =IF(검색어="",1,IF(ISNUMBER(SEARCH(검색어,$A72)),1,0)) | AD72: =IF($AC72=1,$AD71+1,$AD71) | AE72: =IFERROR(INDEX($A$4:$A$594,MATCH(69,$AD$4:$AD$594,0)),"")
A73: SOL 종합채권(AA-이상)액티브 | B73: 436140 | C73: 신한자산운용 | D73: 106815 | E73: 1280284590000 | F73: 1214290026 | G73: 0.0004 | H73: 0.0464 | I73: 0.0212 | J73: 0.022282 | K73: 1 | L73: 20251212 | M73: 채택 | O73: KAP K-종합채권지수(AA-이상, 총수익) | P73: 일반 | Q73: 채권 | R73: 연배당 | S73: 1 | T73: 1 | U73: -0.0579 | V73: -0.0784 | W73: -0.0197 | X73: 0.0029 | Y73: 20250922~20261002 | AA73: =IF(AND($J73<>"",OR(조회_주기="전체",$R73=조회_주기),$J73>=조회_최소,$J73<=조회_최대),1,0) | AB73: =IF($AA73=1,$AB72+1,$AB72) | AC73: =IF(검색어="",1,IF(ISNUMBER(SEARCH(검색어,$A73)),1,0)) | AD73: =IF($AC73=1,$AD72+1,$AD72) | AE73: =IFERROR(INDEX($A$4:$A$594,MATCH(70,$AD$4:$AD$594,0)),"")
A74: TIGER 미국S&P500배당귀족 | B74: 429000 | C74: 미래에셋자산운용 | D74: 12455 | E74: 179352000000 | F74: 1174193580 | G74: 0.0025 | H74: 0.1473 | I74: 0.002 | J74: 0.02216 | K74: 49 | L74: 20260929 | M74: 채택 | O74: S&P 500 Dividend Aristocrats Index | P74: 일반 | Q74: 주식 | R74: 월배당 | S74: 11 | T74: 1 | U74: 0.0406 | V74: 0.0179 | W74: -0.0836 | X74: -0.1691 | Y74: 20250922~20261002 | AA74: =IF(AND($J74<>"",OR(조회_주기="전체",$R74=조회_주기),$J74>=조회_최소,$J74<=조회_최대),1,0) | AB74: =IF($AA74=1,$AB73+1,$AB73) | AC74: =IF(검색어="",1,IF(ISNUMBER(SEARCH(검색어,$A74)),1,0)) | AD74: =IF($AC74=1,$AD73+1,$AD73) | AE74: =IFERROR(INDEX($A$4:$A$594,MATCH(71,$AD$4:$AD$594,0)),"")
A75: TIGER 일본엔선물 | B75: 292560 | C75: 미래에셋자산운용 | D75: 7925 | E75: 51512500000 | F75: 716182793 | G75: 0.0025 | H75: 0.1053 | I75: 0.0194 | J75: 0.021451 | K75: 1 | L75: 20251229 | M75: 채택 | O75: 엔선물 지수 | P75: 일반 | Q75: 통화 | R75: 연배당 | S75: 1 | T75: 0 | U75: -0.0919 | V75: -0.111 | W75: -0.094 | X75: -0.0972 | Y75: 20250922~20261002 | AA75: =IF(AND($J75<>"",OR(조회_주기="전체",$R75=조회_주기),$J75>=조회_최소,$J75<=조회_최대),1,0) | AB75: =IF($AA75=1,$AB74+1,$AB74) | AC75: =IF(검색어="",1,IF(ISNUMBER(SEARCH(검색어,$A75)),1,0)) | AD75: =IF($AC75=1,$AD74+1,$AD74) | AE75: =IFERROR(INDEX($A$4:$A$594,MATCH(72,$AD$4:$AD$594,0)),"")
A76: KODEX 삼성전자채권혼합 | B76: 448330 | C76: 삼성자산운용(ETF) | D76: 17700 | E76: 1308030000000 | F76: 11650624801 | G76: 0.0007 | H76: 0.2316 | I76: 0.0021 | J76: 0.020452 | K76: 24 | L76: 20260914 | M76: 채택 | O76: Wise 삼성전자 채권혼합 지수 | P76: 일반 | Q76: 멀티에셋 | R76: 월배당 | S76: 11 | T76: 1 | U76: 0.5051 | V76: 0.4751 | W76: 0.1614 | X76: -0.014 | Y76: 20250922~20261002 | AA76: =IF(AND($J76<>"",OR(조회_주기="전체",$R76=조회_주기),$J76>=조회_최소,$J76<=조회_최대),1,0) | AB76: =IF($AA76=1,$AB75+1,$AB75) | AC76: =IF(검색어="",1,IF(ISNUMBER(SEARCH(검색어,$A76)),1,0)) | AD76: =IF($AC76=1,$AD75+1,$AD75) | AE76: =IFERROR(INDEX($A$4:$A$594,MATCH(73,$AD$4:$AD$594,0)),"")
A77: KODEX 미국S&P500 | B77: 379800 | C77: 삼성자산운용(ETF) | D77: 23430 | E77: 10399405500000 | F77: 664545668165 | G77: 6.2e-05 | H77: 0.1475 | I77: 0.0054 | J77: 0.020444 | K77: 6 | L77: 20260730 | M77: 채택 | O77: S&P 500 | P77: 일반 | Q77: 주식 | R77: 분기배당 | S77: 3 | T77: 1 | U77: 0.1253 | V77: 0.1027 | W77: 0.0385 | X77: -0.0962 | Y77: 20250922~20261002 | AA77: =IF(AND($J77<>"",OR(조회_주기="전체",$R77=조회_주기),$J77>=조회_최소,$J77<=조회_최대),1,0) | AB77: =IF($AA77=1,$AB76+1,$AB76) | AC77: =IF(검색어="",1,IF(ISNUMBER(SEARCH(검색어,$A77)),1,0)) | AD77: =IF($AC77=1,$AD76+1,$AD76) | AE77: =IFERROR(INDEX($A$4:$A$594,MATCH(74,$AD$4:$AD$594,0)),"")
A78: SOL 미국S&P500미국채혼합50 | B78: 0080X0 | C78: 신한자산운용 | D78: 10555 | E78: 73885000000 | F78: 673568081 | G78: 0.0015 | H78: 0.1102 | I78: 0.0019 | J78: 0.020369 | K78: 13 | L78: 20260914 | M78: 채택 | O78: S&P 500 and iBoxx $ Treasuries 7-10Y 50/50 Blend Index (USD) | P78: 일반 | Q78: 멀티에셋 | R78: 월배당 | S78: 11 | T78: 1 | U78: 0.0201 | V78: -0.0003 | W78: -0.0617 | X78: -0.1264 | Y78: 20250922~20261002 | AA78: =IF(AND($J78<>"",OR(조회_주기="전체",$R78=조회_주기),$J78>=조회_최소,$J78<=조회_최대),1,0) | AB78: =IF($AA78=1,$AB77+1,$AB77) | AC78: =IF(검색어="",1,IF(ISNUMBER(SEARCH(검색어,$A78)),1,0)) | AD78: =IF($AC78=1,$AD77+1,$AD77) | AE78: =IFERROR(INDEX($A$4:$A$594,MATCH(75,$AD$4:$AD$594,0)),"")
A79: KODEX 국고채30년액티브 | B79: 439870 | C79: 삼성자산운용(ETF) | D79: 88880 | E79: 271261760000 | F79: 655893903 | G79: 0.0005 | H79: 0.1422 | I79: 0.0154 | J79: 0.019161 | K79: 1 | L79: 20251212 | M79: 채택 | O79: KAP 국고채 30년 총수익 지수 | P79: 일반 | Q79: 채권 | R79: 연배당 | S79: 1 | T79: 1 | U79: -0.2591 | V79: -0.273 | W79: -0.1348 | X79: -0.0138 | Y79: 20250922~20261002 | AA79: =IF(AND($J79<>"",OR(조회_주기="전체",$R79=조회_주기),$J79>=조회_최소,$J79<=조회_최대),1,0) | AB79: =IF($AA79=1,$AB78+1,$AB78) | AC79: =IF(검색어="",1,IF(ISNUMBER(SEARCH(검색어,$A79)),1,0)) | AD79: =IF($AC79=1,$AD78+1,$AD78) | AE79: =IFERROR(INDEX($A$4:$A$594,MATCH(76,$AD$4:$AD$594,0)),"")
A80: ACE 미국나스닥100미국채혼합50액티브 | B80: 438100 | C80: 한국투자신탁운용 | D80: 15160 | E80: 949016000000 | F80: 4558567817 | G80: 0.0015 | H80: 0.1151 | I80: 0.0193 | J80: 0.018997 | K80: 1 | L80: 20251229 | M80: 채택 | O80: Nasdaq-100 US T-Bills 30/70 Index | P80: 일반 | Q80: 멀티에셋 | R80: 연배당 | S80: 1 | T80: 1 | U80: 0.0997 | V80: 0.0792 | W80: 0.0217 | X80: -0.0953 | Y80: 20250922~20261002 | AA80: =IF(AND($J80<>"",OR(조회_주기="전체",$R80=조회_주기),$J80>=조회_최소,$J80<=조회_최대),1,0) | AB80: =IF($AA80=1,$AB79+1,$AB79) | AC80: =IF(검색어="",1,IF(ISNUMBER(SEARCH(검색어,$A80)),1,0)) | AD80: =IF($AC80=1,$AD79+1,$AD79) | AE80: =IFERROR(INDEX($A$4:$A$594,MATCH(77,$AD$4:$AD$594,0)),"")
A81: RISE 단기채권알파액티브 | B81: 385550 | C81: KB자산운용 | D81: 114210 | E81: 399163950000 | F81: 542867178 | G81: 0.0005 | H81: 0.0185 | I81: 0.018 | J81: 0.017967 | K81: 1 | L81: 20251212 | M81: 채택 | O81: KIS 단기종합채권 지수(AA-이상) | P81: 일반 | Q81: 채권 | R81: 연배당 | S81: 1 | T81: 1 | U81: 0.0254 | V81: 0.0074 | W81: 0.0147 | X81: 0.0084 | Y81: 20250922~20261002 | AA81: =IF(AND($J81<>"",OR(조회_주기="전체",$R81=조회_주기),$J81>=조회_최소,$J81<=조회_최대),1,0) | AB81: =IF($AA81=1,$AB80+1,$AB80) | AC81: =IF(검색어="",1,IF(ISNUMBER(SEARCH(검색어,$A81)),1,0)) | AD81: =IF($AC81=1,$AD80+1,$AD80) | AE81: =IFERROR(INDEX($A$4:$A$594,MATCH(78,$AD$4:$AD$594,0)),"")
A82: KODEX TDF2040액티브 적격 | B82: 433980 | C82: 삼성자산운용(ETF) | D82: 15650 | E82: 191712500000 | F82: 780613952 | G82: 0.0025 | H82: 0.1008 | I82: 0.0065 | J82: 0.017827 | K82: 11 | L82: 20260730 | M82: 채택 | O82: Samsung Korea Target Date 2040 Index | P82: 일반 | Q82: 멀티에셋 | R82: 분기배당 | S82: 3 | T82: 1 | U82: 0.0799 | V82: 0.061 | W82: 0.0235 | X82: -0.0715 | Y82: 20250922~20261002 | AA82: =IF(AND($J82<>"",OR(조회_주기="전체",$R82=조회_주기),$J82>=조회_최소,$J82<=조회_최대),1,0) | AB82: =IF($AA82=1,$AB81+1,$AB81) | AC82: =IF(검색어="",1,IF(ISNUMBER(SEARCH(검색어,$A82)),1,0)) | AD82: =IF($AC82=1,$AD81+1,$AD81) | AE82: =IFERROR(INDEX($A$4:$A$594,MATCH(79,$AD$4:$AD$594,0)),"")
A83: KIWOOM 미국원유에너지기업 | B83: 474800 | C83: 키움투자자산운용 | D83: 15375 | E83: 32287500000 | F83: 944986128 | G83: 0.0029 | H83: 0.245 | I83: 0.0046 | J83: 0.017626 | K83: 7 | L83: 20260730 | M83: 채택 | O83: MSCI US IMI/ENERGY 25-50 Index(PR) | P83: 일반 | Q83: 주식 | R83: 분기배당 | S83: 3 | T83: 1 | U83: 0.3893 | V83: 0.3653 | W83: -0.0643 | X83: 0.0314 | Y83: 20250922~20261002 | AA83: =IF(AND($J83<>"",OR(조회_주기="전체",$R83=조회_주기),$J83>=조회_최소,$J83<=조회_최대),1,0) | AB83: =IF($AA83=1,$AB82+1,$AB82) | AC83: =IF(검색어="",1,IF(ISNUMBER(SEARCH(검색어,$A83)),1,0)) | AD83: =IF($AC83=1,$AD82+1,$AD82) | AE83: =IFERROR(INDEX($A$4:$A$594,MATCH(80,$AD$4:$AD$594,0)),"")
A84: TIGER 여행레저 | B84: 228800 | C84: 미래에셋자산운용 | D84: 2600 | E84: 66846000000 | F84: 514001718 | G84: 0.005 | H84: 0.3285 | I84: 0.013 | J84: 0.017308 | K84: 5 | L84: 20260429 | M84: 채택 | O84: WISE 여행레저 지수 | P84: 일반 | Q84: 주식 | R84: 연배당 | S84: 1 | T84: 0.6 | U84: -0.3108 | V84: -0.3225 | W84: -0.1417 | X84: -0.0754 | Y84: 20250922~20261002 | AA84: =IF(AND($J84<>"",OR(조회_주기="전체",$R84=조회_주기),$J84>=조회_최소,$J84<=조회_최대),1,0) | AB84: =IF($AA84=1,$AB83+1,$AB83) | AC84: =IF(검색어="",1,IF(ISNUMBER(SEARCH(검색어,$A84)),1,0)) | AD84: =IF($AC84=1,$AD83+1,$AD83) | AE84: =IFERROR(INDEX($A$4:$A$594,MATCH(81,$AD$4:$AD$594,0)),"")
A85: TIGER 국고채30년스트립액티브 | B85: 451530 | C85: 미래에셋자산운용 | D85: 35930 | E85: 133587740000 | F85: 872055423 | G85: 0.0015 | H85: 0.2108 | I85: 0.0114 | J85: 0.017033 | K85: 1 | L85: 20251127 | M85: 채택 | O85: KIS STRIP 30Y Index | P85: 일반 | Q85: 채권 | R85: 연배당 | S85: 1 | T85: 1 | U85: -0.3997 | V85: -0.4097 | W85: -0.232 | X85: -0.0375 | Y85: 20250922~20261002 | AA85: =IF(AND($J85<>"",OR(조회_주기="전체",$R85=조회_주기),$J85>=조회_최소,$J85<=조회_최대),1,0) | AB85: =IF($AA85=1,$AB84+1,$AB84) | AC85: =IF(검색어="",1,IF(ISNUMBER(SEARCH(검색어,$A85)),1,0)) | AD85: =IF($AC85=1,$AD84+1,$AD84) | AE85: =IFERROR(INDEX($A$4:$A$594,MATCH(82,$AD$4:$AD$594,0)),"")
A86: RISE 버크셔포트폴리오TOP10 | B86: 475350 | C86: KB자산운용 | D86: 13975 | E86: 71272500000 | F86: 581737687 | G86: 0.0001 | H86: 0.1412 | I86: 0.0054 | J86: 0.016959 | K86: 2 | L86: 20260730 | M86: 채택 | O86: Solactive Berkshire Portfolio Top10 Index PR | P86: 일반 | Q86: 주식 | R86: 반기배당 | S86: 2 | T86: 1 | U86: 0.0752 | V86: 0.0572 | W86: -0.0259 | X86: -0.126 | Y86: 20250922~20261002 | AA86: =IF(AND($J86<>"",OR(조회_주기="전체",$R86=조회_주기),$J86>=조회_최소,$J86<=조회_최대),1,0) | AB86: =IF($AA86=1,$AB85+1,$AB85) | AC86: =IF(검색어="",1,IF(ISNUMBER(SEARCH(검색어,$A86)),1,0)) | AD86: =IF($AC86=1,$AD85+1,$AD85) | AE86: =IFERROR(INDEX($A$4:$A$594,MATCH(83,$AD$4:$AD$594,0)),"")
A87: PLUS 미국S&P500미국채혼합50액티브 | B87: 0057H0 | C87: 한화자산운용 | D87: 11415 | E87: 78763500000 | F87: 987564599 | G87: 0.0015 | H87: 0.1025 | I87: 0.0012 | J87: 0.016908 | K87: 11 | L87: 20260929 | M87: 채택 | O87: S&P500 and U.S. Treasury Bill 0-3 Month 50/50 Blend Index (U | P87: 일반 | Q87: 멀티에셋 | R87: 월배당 | S87: 10 | T87: 1 | U87: 0.0617 | V87: 0.044 | W87: -0.0267 | X87: -0.1028 | Y87: 20250922~20261002 | AA87: =IF(AND($J87<>"",OR(조회_주기="전체",$R87=조회_주기),$J87>=조회_최소,$J87<=조회_최대),1,0) | AB87: =IF($AA87=1,$AB86+1,$AB86) | AC87: =IF(검색어="",1,IF(ISNUMBER(SEARCH(검색어,$A87)),1,0)) | AD87: =IF($AC87=1,$AD86+1,$AD86) | AE87: =IFERROR(INDEX($A$4:$A$594,MATCH(84,$AD$4:$AD$594,0)),"")
A88: KODEX 200미국채혼합50 | B88: 284430 | C88: 삼성자산운용(ETF) | D88: 20715 | E88: 1995268800000 | F88: 17604286189 | G88: 0.0035 | H88: 0.2517 | I88: 0.0013 | J88: 0.016896 | K88: 14 | L88: 20260914 | M88: 채택 | O88: 코스피 200 미국채 혼합지수 | P88: 일반 | Q88: 멀티에셋 | R88: 월배당 | S88: 11 | T88: 1 | U88: 0.3949 | V88: 0.3717 | W88: 0.0608 | X88: -0.1355 | Y88: 20250922~20261002 | AA88: =IF(AND($J88<>"",OR(조회_주기="전체",$R88=조회_주기),$J88>=조회_최소,$J88<=조회_최대),1,0) | AB88: =IF($AA88=1,$AB87+1,$AB87) | AC88: =IF(검색어="",1,IF(ISNUMBER(SEARCH(검색어,$A88)),1,0)) | AD88: =IF($AC88=1,$AD87+1,$AD87) | AE88: =IFERROR(INDEX($A$4:$A$594,MATCH(85,$AD$4:$AD$594,0)),"")
A89: TIGER 토탈월드스탁액티브 | B89: 0060H0 | C89: 미래에셋자산운용 | D89: 12345 | E89: 387633000000 | F89: 1866497104 | G89: 0.0025 | H89: 0.1361 | I89: 0.0041 | J89: 0.016687 | K89: 5 | L89: 20260730 | M89: 채택 | O89: FTSE GLOBAL ALL CAP INDEX | P89: 일반 | Q89: 주식 | R89: 분기배당 | S89: 3 | T89: 1 | U89: 0.1298 | V89: 0.1112 | W89: 0.0189 | X89: -0.1065 | Y89: 20250922~20261002 | AA89: =IF(AND($J89<>"",OR(조회_주기="전체",$R89=조회_주기),$J89>=조회_최소,$J89<=조회_최대),1,0) | AB89: =IF($AA89=1,$AB88+1,$AB88) | AC89: =IF(검색어="",1,IF(ISNUMBER(SEARCH(검색어,$A89)),1,0)) | AD89: =IF($AC89=1,$AD88+1,$AD88) | AE89: =IFERROR(INDEX($A$4:$A$594,MATCH(86,$AD$4:$AD$594,0)),"")
A90: 1Q 단기금융채액티브 | B90: 463290 | C90: 하나자산운용 | D90: 109545 | E90: 126305385000 | F90: 528201270 | G90: 0.0008 | H90: 0.0168 | I90: 0.0167 | J90: 0.016605 | K90: 1 | L90: 20251229 | M90: 채택 | O90: MK Money Market지수 | P90: 일반 | Q90: 채권 | R90: 연배당 | S90: 1 | T90: 1 | U90: 0.028 | V90: 0.0112 | W90: 0.0151 | X90: 0.0081 | Y90: 20250922~20261002 | AA90: =IF(AND($J90<>"",OR(조회_주기="전체",$R90=조회_주기),$J90>=조회_최소,$J90<=조회_최대),1,0) | AB90: =IF($AA90=1,$AB89+1,$AB89) | AC90: =IF(검색어="",1,IF(ISNUMBER(SEARCH(검색어,$A90)),1,0)) | AD90: =IF($AC90=1,$AD89+1,$AD89) | AE90: =IFERROR(INDEX($A$4:$A$594,MATCH(87,$AD$4:$AD$594,0)),"")
A91: 1Q 미국S&P500미국채혼합50액티브 | B91: 0052S0 | C91: 하나자산운용 | D91: 11330 | E91: 319506000000 | F91: 2124213239 | G91: 0.0015 | H91: 0.1111 | I91: 0.005 | J91: 0.016505 | K91: 4 | L91: 20260730 | M91: 채택 | O91: S&P 500 and Short-Term Treasury 50/50 Blend Index (USD) | P91: 일반 | Q91: 멀티에셋 | R91: 분기배당 | S91: 3 | T91: 1 | U91: 0.0606 | V91: 0.0434 | W91: -0.0293 | X91: -0.1047 | Y91: 20250922~20261002 | AA91: =IF(AND($J91<>"",OR(조회_주기="전체",$R91=조회_주기),$J91>=조회_최소,$J91<=조회_최대),1,0) | AB91: =IF($AA91=1,$AB90+1,$AB90) | AC91: =IF(검색어="",1,IF(ISNUMBER(SEARCH(검색어,$A91)),1,0)) | AD91: =IF($AC91=1,$AD90+1,$AD90) | AE91: =IFERROR(INDEX($A$4:$A$594,MATCH(88,$AD$4:$AD$594,0)),"")
A92: KODEX TDF2050액티브 적격 | B92: 434060 | C92: 삼성자산운용(ETF) | D92: 16685 | E92: 632361500000 | F92: 1997834774 | G92: 0.003 | H92: 0.1246 | I92: 0.007 | J92: 0.016362 | K92: 11 | L92: 20260730 | M92: 채택 | O92: Samsung Korea Target Date 2050 Index | P92: 일반 | Q92: 멀티에셋 | R92: 분기배당 | S92: 3 | T92: 1 | U92: 0.0847 | V92: 0.0672 | W92: 0.0102 | X92: -0.086 | Y92: 20250922~20261002 | AA92: =IF(AND($J92<>"",OR(조회_주기="전체",$R92=조회_주기),$J92>=조회_최소,$J92<=조회_최대),1,0) | AB92: =IF($AA92=1,$AB91+1,$AB91) | AC92: =IF(검색어="",1,IF(ISNUMBER(SEARCH(검색어,$A92)),1,0)) | AD92: =IF($AC92=1,$AD91+1,$AD91) | AE92: =IFERROR(INDEX($A$4:$A$594,MATCH(89,$AD$4:$AD$594,0)),"")
A93: KODEX 인도Nifty50 | B93: 453810 | C93: 삼성자산운용(ETF) | D93: 10630 | E93: 307738500000 | F93: 1409346780 | G93: 0.0019 | H93: 0.1754 | I93: 0.0062 | J93: 0.016275 | K93: 13 | L93: 20260730 | M93: 채택 | O93: CNX NIFTY INDEX | P93: 일반 | Q93: 주식 | R93: 분기배당 | S93: 3 | T93: 1 | U93: -0.2155 | V93: -0.2282 | W93: -0.1553 | X93: -0.1958 | Y93: 20250922~20261002 | AA93: =IF(AND($J93<>"",OR(조회_주기="전체",$R93=조회_주기),$J93>=조회_최소,$J93<=조회_최대),1,0) | AB93: =IF($AA93=1,$AB92+1,$AB92) | AC93: =IF(검색어="",1,IF(ISNUMBER(SEARCH(검색어,$A93)),1,0)) | AD93: =IF($AC93=1,$AD92+1,$AD92) | AE93: =IFERROR(INDEX($A$4:$A$594,MATCH(90,$AD$4:$AD$594,0)),"")
A94: TIGER 차이나전기차SOLACTIVE | B94: 371460 | C94: 미래에셋자산운용 | D94: 8915 | E94: 639383800000 | F94: 1816782106 | G94: 0.0049 | H94: 0.2893 | I94: 0.011 | J94: 0.015704 | K94: 1 | L94: 20251229 | M94: 채택 | O94: Solactive China Electric Vehicle and Battery Index PR | P94: 일반 | Q94: 주식 | R94: 연배당 | S94: 1 | T94: 1 | U94: -0.2528 | V94: -0.2642 | W94: -0.3228 | X94: -0.2763 | Y94: 20250922~20261002 | AA94: =IF(AND($J94<>"",OR(조회_주기="전체",$R94=조회_주기),$J94>=조회_최소,$J94<=조회_최대),1,0) | AB94: =IF($AA94=1,$AB93+1,$AB93) | AC94: =IF(검색어="",1,IF(ISNUMBER(SEARCH(검색어,$A94)),1,0)) | AD94: =IF($AC94=1,$AD93+1,$AD93) | AE94: =IFERROR(INDEX($A$4:$A$594,MATCH(91,$AD$4:$AD$594,0)),"")
A95: KODEX 종합채권(AA-이상)액티브 | B95: 273130 | C95: 삼성자산운용(ETF) | D95: 110440 | E95: 3578145560000 | F95: 3122311038 | G95: 0.00045 | H95: 0.0419 | I95: 0.0149 | J95: 0.015637 | K95: 1 | L95: 20251212 | M95: 채택 | O95: KAP 한국종합채권 | P95: 일반 | Q95: 채권 | R95: 연배당 | S95: 1 | T95: 1 | U95: -0.0608 | V95: -0.0752 | W95: -0.022 | X95: 0.0023 | Y95: 20250922~20261002 | AA95: =IF(AND($J95<>"",OR(조회_주기="전체",$R95=조회_주기),$J95>=조회_최소,$J95<=조회_최대),1,0) | AB95: =IF($AA95=1,$AB94+1,$AB94) | AC95: =IF(검색어="",1,IF(ISNUMBER(SEARCH(검색어,$A95)),1,0)) | AD95: =IF($AC95=1,$AD94+1,$AD94) | AE95: =IFERROR(INDEX($A$4:$A$594,MATCH(92,$AD$4:$AD$594,0)),"")
A96: SOL 초단기채권액티브 | B96: 469830 | C96: 신한자산운용 | D96: 54545 | E96: 1051082150000 | F96: 11363539030 | G96: 0.0005 | H96: 0.0161 | I96: 0.0158 | J96: 0.015583 | K96: 1 | L96: 20251212 | M96: 채택 | O96: KAP 단기자금시장 지수 | P96: 일반 | Q96: 단기자금(파킹형) | R96: 연배당 | S96: 1 | T96: 1 | U96: 0.0324 | V96: 0.0165 | W96: 0.0169 | X96: 0.0089 | Y96: 20250922~20261002 | AA96: =IF(AND($J96<>"",OR(조회_주기="전체",$R96=조회_주기),$J96>=조회_최소,$J96<=조회_최대),1,0) | AB96: =IF($AA96=1,$AB95+1,$AB95) | AC96: =IF(검색어="",1,IF(ISNUMBER(SEARCH(검색어,$A96)),1,0)) | AD96: =IF($AC96=1,$AD95+1,$AD95) | AE96: =IFERROR(INDEX($A$4:$A$594,MATCH(93,$AD$4:$AD$594,0)),"")
A97: KODEX 국고채10년액티브 | B97: 471230 | C97: 삼성자산운용(ETF) | D97: 104125 | E97: 463252125000 | F97: 1758681949 | G97: 0.00015 | H97: 0.0679 | I97: 0.0147 | J97: 0.015491 | K97: 1 | L97: 20251212 | M97: 채택 | O97: KAP 국고채 10년 지수(TR) | P97: 일반 | Q97: 채권 | R97: 연배당 | S97: 1 | T97: 1 | U97: -0.0797 | V97: -0.0937 | W97: -0.0262 | X97: -0.0021 | Y97: 20250922~20261002 | AA97: =IF(AND($J97<>"",OR(조회_주기="전체",$R97=조회_주기),$J97>=조회_최소,$J97<=조회_최대),1,0) | AB97: =IF($AA97=1,$AB96+1,$AB96) | AC97: =IF(검색어="",1,IF(ISNUMBER(SEARCH(검색어,$A97)),1,0)) | AD97: =IF($AC97=1,$AD96+1,$AD96) | AE97: =IFERROR(INDEX($A$4:$A$594,MATCH(94,$AD$4:$AD$594,0)),"")
A98: TIGER 미국S&P500동일가중 | B98: 488500 | C98: 미래에셋자산운용 | D98: 11950 | E98: 108147500000 | F98: 896580688 | G98: 0.002 | H98: 0.1387 | I98: 0.0037 | J98: 0.015314 | K98: 8 | L98: 20260730 | M98: 채택 | O98: S&P 500 EQUAL WEIGHTED | P98: 일반 | Q98: 주식 | R98: 분기배당 | S98: 3 | T98: 1 | U98: 0.0879 | V98: 0.0714 | W98: -0.0312 | X98: -0.1398 | Y98: 20250922~20261002 | AA98: =IF(AND($J98<>"",OR(조회_주기="전체",$R98=조회_주기),$J98>=조회_최소,$J98<=조회_최대),1,0) | AB98: =IF($AA98=1,$AB97+1,$AB97) | AC98: =IF(검색어="",1,IF(ISNUMBER(SEARCH(검색어,$A98)),1,0)) | AD98: =IF($AC98=1,$AD97+1,$AD97) | AE98: =IFERROR(INDEX($A$4:$A$594,MATCH(95,$AD$4:$AD$594,0)),"")
A99: KODEX TDF2060액티브 적격 | B99: 0082V0 | C99: 삼성자산운용(ETF) | D99: 11230 | E99: 189225500000 | F99: 872862894 | G99: 0.003 | H99: 0.1206 | I99: 0.0071 | J99: 0.015138 | K99: 4 | L99: 20260730 | M99: 채택 | O99: Samsung Korea Target Date 2060 Index | P99: 일반 | Q99: 멀티에셋 | R99: 분기배당 | S99: 3 | T99: 1 | U99: 0.0753 | V99: 0.0591 | W99: 0.0115 | X99: -0.086 | Y99: 20250922~20261002 | AA99: =IF(AND($J99<>"",OR(조회_주기="전체",$R99=조회_주기),$J99>=조회_최소,$J99<=조회_최대),1,0) | AB99: =IF($AA99=1,$AB98+1,$AB98) | AC99: =IF(검색어="",1,IF(ISNUMBER(SEARCH(검색어,$A99)),1,0)) | AD99: =IF($AC99=1,$AD98+1,$AD98) | AE99: =IFERROR(INDEX($A$4:$A$594,MATCH(96,$AD$4:$AD$594,0)),"")
A100: KODEX 미국S&P500헬스케어 | B100: 453640 | C100: 삼성자산운용(ETF) | D100: 13580 | E100: 58394000000 | F100: 513025968 | G100: 0.0025 | H100: 0.1844 | I100: 0.0038 | J100: 0.014948 | K100: 13 | L100: 20260730 | M100: 채택 | O100: S&P Health Care Select Sector Index | P100: 일반 | Q100: 주식 | R100: 분기배당 | S100: 3 | T100: 1 | U100: 0.1897 | V100: 0.1722 | W100: 0.0127 | X100: -0.104 | Y100: 20250922~20261002 | AA100: =IF(AND($J100<>"",OR(조회_주기="전체",$R100=조회_주기),$J100>=조회_최소,$J100<=조회_최대),1,0) | AB100: =IF($AA100=1,$AB99+1,$AB99) | AC100: =IF(검색어="",1,IF(ISNUMBER(SEARCH(검색어,$A100)),1,0)) | AD100: =IF($AC100=1,$AD99+1,$AD99) | AE100: =IFERROR(INDEX($A$4:$A$594,MATCH(97,$AD$4:$AD$594,0)),"")
A101: TIGER 테슬라채권혼합Fn | B101: 447770 | C101: 미래에셋자산운용 | D101: 13710 | E101: 433236000000 | F101: 1910649964 | G101: 0.0025 | H101: 0.1436 | I101: 0.0049 | J101: 0.014588 | K101: 11 | L101: 20260730 | M101: 채택 | O101: FnGuide 테슬라채권혼합 지수 | P101: 일반 | Q101: 멀티에셋 | R101: 분기배당 | S101: 3 | T101: 1 | U101: -0.0659 | V101: -0.0793 | W101: -0.0375 | X101: -0.0601 | Y101: 20250922~20261002 | AA101: =IF(AND($J101<>"",OR(조회_주기="전체",$R101=조회_주기),$J101>=조회_최소,$J101<=조회_최대),1,0) | AB101: =IF($AA101=1,$AB100+1,$AB100) | AC101: =IF(검색어="",1,IF(ISNUMBER(SEARCH(검색어,$A101)),1,0)) | AD101: =IF($AC101=1,$AD100+1,$AD100) | AE101: =IFERROR(INDEX($A$4:$A$594,MATCH(98,$AD$4:$AD$594,0)),"")
...

Sheet 사용법
B1: 이 파일을 쓰는 법
B5: 1. [제안서] 장의 노란 칸만 고치면 됩니다.
B6: · 고객명 — 그대로 인쇄됩니다.
B7: · 총 투자금액 — 원 단위로 넣으십시오. 예: 100000000
B8: · 배분 방식 — '비율' 또는 '금액'. 포트폴리오 표의 배분 칸 뜻이 이것에 따라 바뀝니다.
B9: · 배당소득세율 — 기본 15.4%. 금융소득종합과세 대상자면 여기만 바꾸십시오.
B11: 2. 포트폴리오는 10줄까지 담을 수 있습니다.
B12: · 투자 ETF 칸을 누르면 ▼ 가 나옵니다. 목록에서 고르십시오.
B13: · 종목이 많아 찾기 어려우면 표 위의 '종목 검색' 에 글자 일부를 넣으십시오 (예: 커버드콜). ▼ 목록이 그만큼만 남고, 비우면 전체로 돌아옵니다.
B14: · [종목조회] 장에서 '담기' 칸에 O 를 넣으면 이 표에 자동으로 올라옵니다. 담은 순서대로 채워지고, O 를 지우면 내려갑니다. 배분 비율은 직접 넣으십시오.
B15: · 손으로 ▼ 로 고르면 그 줄은 손으로 고른 값이 남습니다(그 줄만 [종목조회] 를 따라가지 않습니다). 다음 달 파일에서는 다시 연결됩니다.
B16: · '비율' 이면 배분 칸에 %를 넣습니다. 합이 100 이 되어야 합니다.
... B41: 그 장의 값이 ETFCHECK 화면과 다르면 수집이 어긋난 것이니 알려 주십시오.
